{
  "ascent": 1000,
  "capHeight": 708,
  "codePoints": [
    {
      "advanceWidth": 278,
      "codePoint": 32,
      "height": 0,
      "leftSideBearing": 0,
      "width": 0,
      "xMax": 0,
      "xMin": 0,
      "yMax": 0,
      "yMin": 0
    },
    {
      "advanceWidth": 278,
      "codePoint": 33,
      "height": 424,
      "leftSideBearing": 77,
      "width": -83,
      "xMax": -6,
      "xMin": 77,
      "yMax": 708,
      "yMin": 284
    },
    {
      "advanceWidth": 519,
      "codePoint": 34,
      "height": 236,
      "leftSideBearing": 210,
      "width": 252,
      "xMax": 462,
      "xMin": 210,
      "yMax": 708,
      "yMin": 472
    },
    {
      "advanceWidth": 556,
      "codePoint": 35,
      "height": 107,
      "leftSideBearing": 53,
      "width": -53,
      "xMax": 0,
      "xMin": 53,
      "yMax": 708,
      "yMin": 601
    },
    {
      "advanceWidth": 556,
      "codePoint": 36,
      "height": 204,
      "leftSideBearing": 37,
      "width": -121,
      "xMax": -84,
      "xMin": 37,
      "yMax": 792,
      "yMin": 588
    },
    {
      "advanceWidth": 852,
      "codePoint": 37,
      "height": -102,
      "leftSideBearing": 109,
      "width": -140,
      "xMax": -31,
      "xMin": 109,
      "yMax": 740,
      "yMin": 842
    },
    {
      "advanceWidth": 722,
      "codePoint": 38,
      "height": -20,
      "leftSideBearing": 67,
      "width": -85,
      "xMax": -18,
      "xMin": 67,
      "yMax": 720,
      "yMin": 740
    },
    {
      "advanceWidth": 278,
      "codePoint": 39,
      "height": 431,
      "leftSideBearing": 164,
      "width": 298,
      "xMax": 462,
      "xMin": 164,
      "yMax": 708,
      "yMin": 277
    },
    {
      "advanceWidth": 278,
      "codePoint": 40,
      "height": 377,
      "leftSideBearing": 71,
      "width": -231,
      "xMax": -160,
      "xMin": 71,
      "yMax": 728,
      "yMin": 351
    },
    {
      "advanceWidth": 278,
      "codePoint": 41,
      "height": 441,
      "leftSideBearing": 7,
      "width": -167,
      "xMax": -160,
      "xMin": 7,
      "yMax": 728,
      "yMin": 287
    },
    {
      "advanceWidth": 464,
      "codePoint": 42,
      "height": 203,
      "leftSideBearing": 111,
      "width": 225,
      "xMax": 336,
      "xMin": 111,
      "yMax": 708,
      "yMin": 505
    },
    {
      "advanceWidth": 666,
      "codePoint": 43,
      "height": -78,
      "leftSideBearing": 103,
      "width": -67,
      "xMax": 36,
      "xMin": 103,
      "yMax": 570,
      "yMin": 648
    },
    {
      "advanceWidth": 278,
      "codePoint": 44,
      "height": -116,
      "leftSideBearing": 29,
      "width": -161,
      "xMax": -132,
      "xMin": 29,
      "yMax": 114,
      "yMin": 230
    },
    {
      "advanceWidth": 316,
      "codePoint": 45,
      "height": -36,
      "leftSideBearing": 63,
      "width": 137,
      "xMax": 200,
      "xMin": 63,
      "yMax": 284,
      "yMin": 320
    },
    {
      "advanceWidth": 278,
      "codePoint": 46,
      "height": -91,
      "leftSideBearing": 77,
      "width": -83,
      "xMax": -6,
      "xMin": 77,
      "yMax": 126,
      "yMin": 217
    },
    {
      "advanceWidth": 389,
      "codePoint": 47,
      "height": 261,
      "leftSideBearing": -2,
      "width": -42,
      "xMax": -44,
      "xMin": -2,
      "yMax": 752,
      "yMin": 491
    },
    {
      "advanceWidth": 556,
      "codePoint": 48,
      "height": 140,
      "leftSideBearing": 75,
      "width": -87,
      "xMax": -12,
      "xMin": 75,
      "yMax": 720,
      "yMin": 580
    },
    {
      "advanceWidth": 556,
      "codePoint": 49,
      "height": 243,
      "leftSideBearing": 160,
      "width": -160,
      "xMax": 0,
      "xMin": 160,
      "yMax": 708,
      "yMin": 465
    },
    {
      "advanceWidth": 556,
      "codePoint": 50,
      "height": 135,
      "leftSideBearing": 46,
      "width": -46,
      "xMax": 0,
      "xMin": 46,
      "yMax": 726,
      "yMin": 591
    },
    {
      "advanceWidth": 556,
      "codePoint": 51,
      "height": 153,
      "leftSideBearing": 65,
      "width": -77,
      "xMax": -12,
      "xMin": 65,
      "yMax": 726,
      "yMin": 573
    },
    {
      "advanceWidth": 556,
      "codePoint": 52,
      "height": 143,
      "leftSideBearing": 55,
      "width": -55,
      "xMax": 0,
      "xMin": 55,
      "yMax": 708,
      "yMin": 565
    },
    {
      "advanceWidth": 556,
      "codePoint": 53,
      "height": 138,
      "leftSideBearing": 52,
      "width": -64,
      "xMax": -12,
      "xMin": 52,
      "yMax": 708,
      "yMin": 570
    },
    {
      "advanceWidth": 556,
      "codePoint": 54,
      "height": 148,
      "leftSideBearing": 57,
      "width": -69,
      "xMax": -12,
      "xMin": 57,
      "yMax": 708,
      "yMin": 560
    },
    {
      "advanceWidth": 556,
      "codePoint": 55,
      "height": 122,
      "leftSideBearing": 97,
      "width": -97,
      "xMax": 0,
      "xMin": 97,
      "yMax": 708,
      "yMin": 586
    },
    {
      "advanceWidth": 556,
      "codePoint": 56,
      "height": 153,
      "leftSideBearing": 68,
      "width": -80,
      "xMax": -12,
      "xMin": 68,
      "yMax": 720,
      "yMin": 567
    },
    {
      "advanceWidth": 556,
      "codePoint": 57,
      "height": 123,
      "leftSideBearing": 94,
      "width": -94,
      "xMax": 0,
      "xMin": 94,
      "yMax": 720,
      "yMin": 597
    },
    {
      "advanceWidth": 278,
      "codePoint": 58,
      "height": 213,
      "leftSideBearing": 77,
      "width": -83,
      "xMax": -6,
      "xMin": 77,
      "yMax": 480,
      "yMin": 267
    },
    {
      "advanceWidth": 278,
      "codePoint": 59,
      "height": 212,
      "leftSideBearing": 29,
      "width": -161,
      "xMax": -132,
      "xMin": 29,
      "yMax": 479,
      "yMin": 267
    },
    {
      "advanceWidth": 666,
      "codePoint": 60,
      "height": -115,
      "leftSideBearing": 102,
      "width": -59,
      "xMax": 43,
      "xMin": 102,
      "yMax": 564,
      "yMin": 679
    },
    {
      "advanceWidth": 666,
      "codePoint": 61,
      "height": -239,
      "leftSideBearing": 92,
      "width": 93,
      "xMax": 185,
      "xMin": 92,
      "yMax": 420,
      "yMin": 659
    },
    {
      "advanceWidth": 666,
      "codePoint": 62,
      "height": -85,
      "leftSideBearing": 71,
      "width": -29,
      "xMax": 42,
      "xMin": 71,
      "yMax": 563,
      "yMin": 648
    },
    {
      "advanceWidth": 500,
      "codePoint": 63,
      "height": 176,
      "leftSideBearing": 123,
      "width": -129,
      "xMax": -6,
      "xMin": 123,
      "yMax": 726,
      "yMin": 550
    },
    {
      "advanceWidth": 800,
      "codePoint": 64,
      "height": -98,
      "leftSideBearing": 83,
      "width": -101,
      "xMax": -18,
      "xMin": 83,
      "yMax": 726,
      "yMin": 824
    },
    {
      "advanceWidth": 704,
      "codePoint": 65,
      "height": 5,
      "leftSideBearing": 1,
      "width": -1,
      "xMax": 0,
      "xMin": 1,
      "yMax": 708,
      "yMin": 703
    },
    {
      "advanceWidth": 630,
      "codePoint": 66,
      "height": 76,
      "leftSideBearing": 91,
      "width": -91,
      "xMax": 0,
      "xMin": 91,
      "yMax": 708,
      "yMin": 632
    },
    {
      "advanceWidth": 704,
      "codePoint": 67,
      "height": -24,
      "leftSideBearing": 86,
      "width": -104,
      "xMax": -18,
      "xMin": 86,
      "yMax": 726,
      "yMin": 750
    },
    {
      "advanceWidth": 741,
      "codePoint": 68,
      "height": -40,
      "leftSideBearing": 75,
      "width": -75,
      "xMax": 0,
      "xMin": 75,
      "yMax": 708,
      "yMin": 748
    },
    {
      "advanceWidth": 611,
      "codePoint": 69,
      "height": 61,
      "leftSideBearing": 91,
      "width": -91,
      "xMax": 0,
      "xMin": 91,
      "yMax": 708,
      "yMin": 647
    },
    {
      "advanceWidth": 574,
      "codePoint": 70,
      "height": 73,
      "leftSideBearing": 91,
      "width": -91,
      "xMax": 0,
      "xMin": 91,
      "yMax": 708,
      "yMin": 635
    },
    {
      "advanceWidth": 778,
      "codePoint": 71,
      "height": -43,
      "leftSideBearing": 85,
      "width": -103,
      "xMax": -18,
      "xMin": 85,
      "yMax": 726,
      "yMin": 769
    },
    {
      "advanceWidth": 741,
      "codePoint": 72,
      "height": -41,
      "leftSideBearing": 91,
      "width": -91,
      "xMax": 0,
      "xMin": 91,
      "yMax": 708,
      "yMin": 749
    },
    {
      "advanceWidth": 278,
      "codePoint": 73,
      "height": 422,
      "leftSideBearing": 91,
      "width": -91,
      "xMax": 0,
      "xMin": 91,
      "yMax": 708,
      "yMin": 286
    },
    {
      "advanceWidth": 482,
      "codePoint": 74,
      "height": 201,
      "leftSideBearing": 28,
      "width": -46,
      "xMax": -18,
      "xMin": 28,
      "yMax": 708,
      "yMin": 507
    },
    {
      "advanceWidth": 648,
      "codePoint": 75,
      "height": -33,
      "leftSideBearing": 91,
      "width": -91,
      "xMax": 0,
      "xMin": 91,
      "yMax": 708,
      "yMin": 741
    },
    {
      "advanceWidth": 519,
      "codePoint": 76,
      "height": 184,
      "leftSideBearing": 91,
      "width": -91,
      "xMax": 0,
      "xMin": 91,
      "yMax": 708,
      "yMin": 524
    },
    {
      "advanceWidth": 906,
      "codePoint": 77,
      "height": -213,
      "leftSideBearing": 84,
      "width": -84,
      "xMax": 0,
      "xMin": 84,
      "yMax": 708,
      "yMin": 921
    },
    {
      "advanceWidth": 796,
      "codePoint": 78,
      "height": -96,
      "leftSideBearing": 91,
      "width": -91,
      "xMax": 0,
      "xMin": 91,
      "yMax": 708,
      "yMin": 804
    },
    {
      "advanceWidth": 832,
      "codePoint": 79,
      "height": -119,
      "leftSideBearing": 85,
      "width": -103,
      "xMax": -18,
      "xMin": 85,
      "yMax": 726,
      "yMin": 845
    },
    {
      "advanceWidth": 593,
      "codePoint": 80,
      "height": 65,
      "leftSideBearing": 91,
      "width": -91,
      "xMax": 0,
      "xMin": 91,
      "yMax": 708,
      "yMin": 643
    },
    {
      "advanceWidth": 832,
      "codePoint": 81,
      "height": -110,
      "leftSideBearing": 86,
      "width": -86,
      "xMax": 0,
      "xMin": 86,
      "yMax": 726,
      "yMin": 836
    },
    {
      "advanceWidth": 611,
      "codePoint": 82,
      "height": 65,
      "leftSideBearing": 91,
      "width": -91,
      "xMax": 0,
      "xMin": 91,
      "yMax": 708,
      "yMin": 643
    },
    {
      "advanceWidth": 556,
      "codePoint": 83,
      "height": 138,
      "leftSideBearing": 44,
      "width": -62,
      "xMax": -18,
      "xMin": 44,
      "yMax": 726,
      "yMin": 588
    },
    {
      "advanceWidth": 574,
      "codePoint": 84,
      "height": 46,
      "leftSideBearing": 97,
      "width": -97,
      "xMax": 0,
      "xMin": 97,
      "yMax": 708,
      "yMin": 662
    },
    {
      "advanceWidth": 704,
      "codePoint": 85,
      "height": -17,
      "leftSideBearing": 105,
      "width": -123,
      "xMax": -18,
      "xMin": 105,
      "yMax": 708,
      "yMin": 725
    },
    {
      "advanceWidth": 630,
      "codePoint": 86,
      "height": -27,
      "leftSideBearing": 93,
      "width": -93,
      "xMax": 0,
      "xMin": 93,
      "yMax": 708,
      "yMin": 735
    },
    {
      "advanceWidth": 962,
      "codePoint": 87,
      "height": -352,
      "leftSideBearing": 100,
      "width": -100,
      "xMax": 0,
      "xMin": 100,
      "yMax": 708,
      "yMin": 1060
    },
    {
      "advanceWidth": 648,
      "codePoint": 88,
      "height": -17,
      "leftSideBearing": -2,
      "width": 2,
      "xMax": 0,
      "xMin": -2,
      "yMax": 708,
      "yMin": 725
    },
    {
      "advanceWidth": 612,
      "codePoint": 89,
      "height": -13,
      "leftSideBearing": 89,
      "width": -89,
      "xMax": 0,
      "xMin": 89,
      "yMax": 708,
      "yMin": 721
    },
    {
      "advanceWidth": 593,
      "codePoint": 90,
      "height": 54,
      "leftSideBearing": 32,
      "width": -32,
      "xMax": 0,
      "xMin": 32,
      "yMax": 708,
      "yMin": 654
    },
    {
      "advanceWidth": 278,
      "codePoint": 91,
      "height": 380,
      "leftSideBearing": 50,
      "width": -210,
      "xMax": -160,
      "xMin": 50,
      "yMax": 728,
      "yMin": 348
    },
    {
      "advanceWidth": 389,
      "codePoint": 92,
      "height": 366,
      "leftSideBearing": 102,
      "width": -146,
      "xMax": -44,
      "xMin": 102,
      "yMax": 752,
      "yMin": 386
    },
    {
      "advanceWidth": 278,
      "codePoint": 93,
      "height": 420,
      "leftSideBearing": 10,
      "width": -170,
      "xMax": -160,
      "xMin": 10,
      "yMax": 728,
      "yMin": 308
    },
    {
      "advanceWidth": 666,
      "codePoint": 94,
      "height": 84,
      "leftSideBearing": 118,
      "width": 158,
      "xMax": 276,
      "xMin": 118,
      "yMax": 708,
      "yMin": 624
    },
    {
      "advanceWidth": 500,
      "codePoint": 95,
      "height": -564,
      "leftSideBearing": -17,
      "width": -108,
      "xMax": -125,
      "xMin": -17,
      "yMax": -75,
      "yMin": 489
    },
    {
      "advanceWidth": 240,
      "codePoint": 96,
      "height": 443,
      "leftSideBearing": 53,
      "width": 511,
      "xMax": 564,
      "xMin": 53,
      "yMax": 708,
      "yMin": 265
    },
    {
      "advanceWidth": 519,
      "codePoint": 97,
      "height": -20,
      "leftSideBearing": 58,
      "width": -70,
      "xMax": -12,
      "xMin": 58,
      "yMax": 486,
      "yMin": 506
    },
    {
      "advanceWidth": 611,
      "codePoint": 98,
      "height": 150,
      "leftSideBearing": 68,
      "width": -80,
      "xMax": -12,
      "xMin": 68,
      "yMax": 756,
      "yMin": 606
    },
    {
      "advanceWidth": 482,
      "codePoint": 99,
      "height": -47,
      "leftSideBearing": 70,
      "width": -82,
      "xMax": -12,
      "xMin": 70,
      "yMax": 485,
      "yMin": 532
    },
    {
      "advanceWidth": 611,
      "codePoint": 100,
      "height": 107,
      "leftSideBearing": 70,
      "width": -82,
      "xMax": -12,
      "xMin": 70,
      "yMax": 756,
      "yMin": 649
    },
    {
      "advanceWidth": 556,
      "codePoint": 101,
      "height": -69,
      "leftSideBearing": 65,
      "width": -77,
      "xMax": -12,
      "xMin": 65,
      "yMax": 486,
      "yMin": 555
    },
    {
      "advanceWidth": 333,
      "codePoint": 102,
      "height": 330,
      "leftSideBearing": 56,
      "width": -56,
      "xMax": 0,
      "xMin": 56,
      "yMax": 768,
      "yMin": 438
    },
    {
      "advanceWidth": 611,
      "codePoint": 103,
      "height": -123,
      "leftSideBearing": 30,
      "width": -270,
      "xMax": -240,
      "xMin": 30,
      "yMax": 486,
      "yMin": 609
    },
    {
      "advanceWidth": 556,
      "codePoint": 104,
      "height": 219,
      "leftSideBearing": 68,
      "width": -68,
      "xMax": 0,
      "xMin": 68,
      "yMax": 756,
      "yMin": 537
    },
    {
      "advanceWidth": 240,
      "codePoint": 105,
      "height": 430,
      "leftSideBearing": 75,
      "width": -75,
      "xMax": 0,
      "xMin": 75,
      "yMax": 710,
      "yMin": 280
    },
    {
      "advanceWidth": 240,
      "codePoint": 106,
      "height": 430,
      "leftSideBearing": -70,
      "width": -170,
      "xMax": -240,
      "xMin": -70,
      "yMax": 710,
      "yMin": 280
    },
    {
      "advanceWidth": 519,
      "codePoint": 107,
      "height": 203,
      "leftSideBearing": 68,
      "width": -68,
      "xMax": 0,
      "xMin": 68,
      "yMax": 756,
      "yMin": 553
    },
    {
      "advanceWidth": 240,
      "codePoint": 108,
      "height": 485,
      "leftSideBearing": 75,
      "width": -75,
      "xMax": 0,
      "xMin": 75,
      "yMax": 756,
      "yMin": 271
    },
    {
      "advanceWidth": 852,
      "codePoint": 109,
      "height": -342,
      "leftSideBearing": 68,
      "width": -68,
      "xMax": 0,
      "xMin": 68,
      "yMax": 486,
      "yMin": 828
    },
    {
      "advanceWidth": 556,
      "codePoint": 110,
      "height": -51,
      "leftSideBearing": 68,
      "width": -68,
      "xMax": 0,
      "xMin": 68,
      "yMax": 486,
      "yMin": 537
    },
    {
      "advanceWidth": 594,
      "codePoint": 111,
      "height": -103,
      "leftSideBearing": 70,
      "width": -82,
      "xMax": -12,
      "xMin": 70,
      "yMax": 486,
      "yMin": 589
    },
    {
      "advanceWidth": 611,
      "codePoint": 112,
      "height": -120,
      "leftSideBearing": 28,
      "width": -310,
      "xMax": -282,
      "xMin": 28,
      "yMax": 486,
      "yMin": 606
    },
    {
      "advanceWidth": 611,
      "codePoint": 113,
      "height": -123,
      "leftSideBearing": 70,
      "width": -298,
      "xMax": -228,
      "xMin": 70,
      "yMax": 486,
      "yMin": 609
    },
    {
      "advanceWidth": 370,
      "codePoint": 114,
      "height": 77,
      "leftSideBearing": 68,
      "width": -68,
      "xMax": 0,
      "xMin": 68,
      "yMax": 486,
      "yMin": 409
    },
    {
      "advanceWidth": 444,
      "codePoint": 115,
      "height": 39,
      "leftSideBearing": 38,
      "width": -50,
      "xMax": -12,
      "xMin": 38,
      "yMax": 486,
      "yMin": 447
    },
    {
      "advanceWidth": 370,
      "codePoint": 116,
      "height": 219,
      "leftSideBearing": 54,
      "width": -66,
      "xMax": -12,
      "xMin": 54,
      "yMax": 607,
      "yMin": 388
    },
    {
      "advanceWidth": 556,
      "codePoint": 117,
      "height": -80,
      "leftSideBearing": 85,
      "width": -97,
      "xMax": -12,
      "xMin": 85,
      "yMax": 474,
      "yMin": 554
    },
    {
      "advanceWidth": 500,
      "codePoint": 118,
      "height": -81,
      "leftSideBearing": 77,
      "width": -77,
      "xMax": 0,
      "xMin": 77,
      "yMax": 474,
      "yMin": 555
    },
    {
      "advanceWidth": 759,
      "codePoint": 119,
      "height": -340,
      "leftSideBearing": 77,
      "width": -77,
      "xMax": 0,
      "xMin": 77,
      "yMax": 474,
      "yMin": 814
    },
    {
      "advanceWidth": 519,
      "codePoint": 120,
      "height": -75,
      "leftSideBearing": 6,
      "width": -6,
      "xMax": 0,
      "xMin": 6,
      "yMax": 474,
      "yMin": 549
    },
    {
      "advanceWidth": 500,
      "codePoint": 121,
      "height": -81,
      "leftSideBearing": -9,
      "width": -231,
      "xMax": -240,
      "xMin": -9,
      "yMax": 474,
      "yMin": 555
    },
    {
      "advanceWidth": 463,
      "codePoint": 122,
      "height": -6,
      "leftSideBearing": 35,
      "width": -35,
      "xMax": 0,
      "xMin": 35,
      "yMax": 474,
      "yMin": 480
    },
    {
      "advanceWidth": 333,
      "codePoint": 123,
      "height": 322,
      "leftSideBearing": 74,
      "width": -234,
      "xMax": -160,
      "xMin": 74,
      "yMax": 728,
      "yMin": 406
    },
    {
      "advanceWidth": 222,
      "codePoint": 124,
      "height": 500,
      "leftSideBearing": 69,
      "width": -87,
      "xMax": -18,
      "xMin": 69,
      "yMax": 756,
      "yMin": 256
    },
    {
      "advanceWidth": 333,
      "codePoint": 125,
      "height": 389,
      "leftSideBearing": 7,
      "width": -167,
      "xMax": -160,
      "xMin": 7,
      "yMax": 728,
      "yMin": 339
    },
    {
      "advanceWidth": 666,
      "codePoint": 126,
      "height": -236,
      "leftSideBearing": 136,
      "width": 92,
      "xMax": 228,
      "xMin": 136,
      "yMax": 378,
      "yMin": 614
    },
    {
      "advanceWidth": 278,
      "codePoint": 160,
      "height": 0,
      "leftSideBearing": 0,
      "width": 0,
      "xMax": 0,
      "xMin": 0,
      "yMax": 0,
      "yMin": 0
    },
    {
      "advanceWidth": 278,
      "codePoint": 161,
      "height": 224,
      "leftSideBearing": 61,
      "width": -283,
      "xMax": -222,
      "xMin": 61,
      "yMax": 492,
      "yMin": 268
    },
    {
      "advanceWidth": 556,
      "codePoint": 162,
      "height": -14,
      "leftSideBearing": 98,
      "width": -176,
      "xMax": -78,
      "xMin": 98,
      "yMax": 552,
      "yMin": 566
    },
    {
      "advanceWidth": 556,
      "codePoint": 163,
      "height": 65,
      "leftSideBearing": 72,
      "width": -72,
      "xMax": 0,
      "xMin": 72,
      "yMax": 720,
      "yMin": 655
    },
    {
      "advanceWidth": 556,
      "codePoint": 164,
      "height": -1,
      "leftSideBearing": 42,
      "width": 56,
      "xMax": 98,
      "xMin": 42,
      "yMax": 612,
      "yMin": 613
    },
    {
      "advanceWidth": 556,
      "codePoint": 165,
      "height": 48,
      "leftSideBearing": 91,
      "width": -91,
      "xMax": 0,
      "xMin": 91,
      "yMax": 708,
      "yMin": 660
    },
    {
      "advanceWidth": 222,
      "codePoint": 166,
      "height": 500,
      "leftSideBearing": 69,
      "width": -87,
      "xMax": -18,
      "xMin": 69,
      "yMax": 756,
      "yMin": 256
    },
    {
      "advanceWidth": 556,
      "codePoint": 167,
      "height": 156,
      "leftSideBearing": 58,
      "width": -202,
      "xMax": -144,
      "xMin": 58,
      "yMax": 726,
      "yMin": 570
    },
    {
      "advanceWidth": 240,
      "codePoint": 168,
      "height": 335,
      "leftSideBearing": 44,
      "width": 550,
      "xMax": 594,
      "xMin": 44,
      "yMax": 714,
      "yMin": 379
    },
    {
      "advanceWidth": 800,
      "codePoint": 169,
      "height": -106,
      "leftSideBearing": 66,
      "width": -84,
      "xMax": -18,
      "xMin": 66,
      "yMax": 726,
      "yMin": 832
    },
    {
      "advanceWidth": 337,
      "codePoint": 170,
      "height": 322,
      "leftSideBearing": 101,
      "width": 318,
      "xMax": 419,
      "xMin": 101,
      "yMax": 720,
      "yMin": 398
    },
    {
      "advanceWidth": 500,
      "codePoint": 171,
      "height": -51,
      "leftSideBearing": 81,
      "width": -54,
      "xMax": 27,
      "xMin": 81,
      "yMax": 459,
      "yMin": 510
    },
    {
      "advanceWidth": 666,
      "codePoint": 172,
      "height": -239,
      "leftSideBearing": 114,
      "width": 27,
      "xMax": 141,
      "xMin": 114,
      "yMax": 420,
      "yMin": 659
    },
    {
      "advanceWidth": 316,
      "codePoint": 173,
      "height": -36,
      "leftSideBearing": 63,
      "width": 137,
      "xMax": 200,
      "xMin": 63,
      "yMax": 284,
      "yMin": 320
    },
    {
      "advanceWidth": 800,
      "codePoint": 174,
      "height": -106,
      "leftSideBearing": 66,
      "width": -84,
      "xMax": -18,
      "xMin": 66,
      "yMax": 726,
      "yMin": 832
    },
    {
      "advanceWidth": 240,
      "codePoint": 175,
      "height": 309,
      "leftSideBearing": 60,
      "width": 540,
      "xMax": 600,
      "xMin": 60,
      "yMax": 666,
      "yMin": 357
    },
    {
      "advanceWidth": 400,
      "codePoint": 176,
      "height": 287,
      "leftSideBearing": 126,
      "width": 296,
      "xMax": 422,
      "xMin": 126,
      "yMax": 720,
      "yMin": 433
    },
    {
      "advanceWidth": 666,
      "codePoint": 177,
      "height": -99,
      "leftSideBearing": 73,
      "width": -22,
      "xMax": 51,
      "xMin": 73,
      "yMax": 556,
      "yMin": 655
    },
    {
      "advanceWidth": 361,
      "codePoint": 178,
      "height": 298,
      "leftSideBearing": 66,
      "width": 223,
      "xMax": 289,
      "xMin": 66,
      "yMax": 720,
      "yMin": 422
    },
    {
      "advanceWidth": 361,
      "codePoint": 179,
      "height": 305,
      "leftSideBearing": 77,
      "width": 206,
      "xMax": 283,
      "xMin": 77,
      "yMax": 720,
      "yMin": 415
    },
    {
      "advanceWidth": 240,
      "codePoint": 180,
      "height": 323,
      "leftSideBearing": 133,
      "width": 431,
      "xMax": 564,
      "xMin": 133,
      "yMax": 708,
      "yMin": 385
    },
    {
      "advanceWidth": 556,
      "codePoint": 181,
      "height": -80,
      "leftSideBearing": 35,
      "width": -263,
      "xMax": -228,
      "xMin": 35,
      "yMax": 474,
      "yMin": 554
    },
    {
      "advanceWidth": 600,
      "codePoint": 182,
      "height": 81,
      "leftSideBearing": 116,
      "width": -242,
      "xMax": -126,
      "xMin": 116,
      "yMax": 708,
      "yMin": 627
    },
    {
      "advanceWidth": 278,
      "codePoint": 183,
      "height": 118,
      "leftSideBearing": 111,
      "width": 126,
      "xMax": 237,
      "xMin": 111,
      "yMax": 369,
      "yMin": 251
    },
    {
      "advanceWidth": 240,
      "codePoint": 184,
      "height": -219,
      "leftSideBearing": -23,
      "width": -205,
      "xMax": -228,
      "xMin": -23,
      "yMax": 0,
      "yMin": 219
    },
    {
      "advanceWidth": 361,
      "codePoint": 185,
      "height": 393,
      "leftSideBearing": 114,
      "width": 175,
      "xMax": 289,
      "xMin": 114,
      "yMax": 720,
      "yMin": 327
    },
    {
      "advanceWidth": 386,
      "codePoint": 186,
      "height": 274,
      "leftSideBearing": 99,
      "width": 320,
      "xMax": 419,
      "xMin": 99,
      "yMax": 720,
      "yMin": 446
    },
    {
      "advanceWidth": 500,
      "codePoint": 187,
      "height": -28,
      "leftSideBearing": 57,
      "width": -30,
      "xMax": 27,
      "xMin": 57,
      "yMax": 459,
      "yMin": 487
    },
    {
      "advanceWidth": 834,
      "codePoint": 188,
      "height": -83,
      "leftSideBearing": 120,
      "width": -152,
      "xMax": -32,
      "xMin": 120,
      "yMax": 740,
      "yMin": 823
    },
    {
      "advanceWidth": 834,
      "codePoint": 189,
      "height": -109,
      "leftSideBearing": 118,
      "width": -150,
      "xMax": -32,
      "xMin": 118,
      "yMax": 740,
      "yMin": 849
    },
    {
      "advanceWidth": 834,
      "codePoint": 190,
      "height": -103,
      "leftSideBearing": 76,
      "width": -108,
      "xMax": -32,
      "xMin": 76,
      "yMax": 740,
      "yMin": 843
    },
    {
      "advanceWidth": 500,
      "codePoint": 191,
      "height": 48,
      "leftSideBearing": 18,
      "width": -258,
      "xMax": -240,
      "xMin": 18,
      "yMax": 492,
      "yMin": 444
    },
    {
      "advanceWidth": 704,
      "codePoint": 192,
      "height": 189,
      "leftSideBearing": 1,
      "width": -1,
      "xMax": 0,
      "xMin": 1,
      "yMax": 892,
      "yMin": 703
    },
    {
      "advanceWidth": 704,
      "codePoint": 193,
      "height": 189,
      "leftSideBearing": 1,
      "width": -1,
      "xMax": 0,
      "xMin": 1,
      "yMax": 892,
      "yMin": 703
    },
    {
      "advanceWidth": 704,
      "codePoint": 194,
      "height": 189,
      "leftSideBearing": 1,
      "width": -1,
      "xMax": 0,
      "xMin": 1,
      "yMax": 892,
      "yMin": 703
    },
    {
      "advanceWidth": 704,
      "codePoint": 195,
      "height": 165,
      "leftSideBearing": 1,
      "width": -1,
      "xMax": 0,
      "xMin": 1,
      "yMax": 868,
      "yMin": 703
    },
    {
      "advanceWidth": 704,
      "codePoint": 196,
      "height": 195,
      "leftSideBearing": 1,
      "width": -1,
      "xMax": 0,
      "xMin": 1,
      "yMax": 898,
      "yMin": 703
    },
    {
      "advanceWidth": 704,
      "codePoint": 197,
      "height": 221,
      "leftSideBearing": 1,
      "width": -1,
      "xMax": 0,
      "xMin": 1,
      "yMax": 924,
      "yMin": 703
    },
    {
      "advanceWidth": 963,
      "codePoint": 198,
      "height": -297,
      "leftSideBearing": -8,
      "width": 8,
      "xMax": 0,
      "xMin": -8,
      "yMax": 708,
      "yMin": 1005
    },
    {
      "advanceWidth": 704,
      "codePoint": 199,
      "height": -24,
      "leftSideBearing": 86,
      "width": -314,
      "xMax": -228,
      "xMin": 86,
      "yMax": 726,
      "yMin": 750
    },
    {
      "advanceWidth": 611,
      "codePoint": 200,
      "height": 245,
      "leftSideBearing": 91,
      "width": -91,
      "xMax": 0,
      "xMin": 91,
      "yMax": 892,
      "yMin": 647
    },
    {
      "advanceWidth": 611,
      "codePoint": 201,
      "height": 245,
      "leftSideBearing": 91,
      "width": -91,
      "xMax": 0,
      "xMin": 91,
      "yMax": 892,
      "yMin": 647
    },
    {
      "advanceWidth": 611,
      "codePoint": 202,
      "height": 245,
      "leftSideBearing": 91,
      "width": -91,
      "xMax": 0,
      "xMin": 91,
      "yMax": 892,
      "yMin": 647
    },
    {
      "advanceWidth": 611,
      "codePoint": 203,
      "height": 251,
      "leftSideBearing": 91,
      "width": -91,
      "xMax": 0,
      "xMin": 91,
      "yMax": 898,
      "yMin": 647
    },
    {
      "advanceWidth": 278,
      "codePoint": 204,
      "height": 583,
      "leftSideBearing": 91,
      "width": -91,
      "xMax": 0,
      "xMin": 91,
      "yMax": 892,
      "yMin": 309
    },
    {
      "advanceWidth": 278,
      "codePoint": 205,
      "height": 463,
      "leftSideBearing": 91,
      "width": -91,
      "xMax": 0,
      "xMin": 91,
      "yMax": 892,
      "yMin": 429
    },
    {
      "advanceWidth": 278,
      "codePoint": 206,
      "height": 484,
      "leftSideBearing": 78,
      "width": -78,
      "xMax": 0,
      "xMin": 78,
      "yMax": 892,
      "yMin": 408
    },
    {
      "advanceWidth": 278,
      "codePoint": 207,
      "height": 475,
      "leftSideBearing": 88,
      "width": -88,
      "xMax": 0,
      "xMin": 88,
      "yMax": 898,
      "yMin": 423
    },
    {
      "advanceWidth": 741,
      "codePoint": 208,
      "height": -40,
      "leftSideBearing": 50,
      "width": -50,
      "xMax": 0,
      "xMin": 50,
      "yMax": 708,
      "yMin": 748
    },
    {
      "advanceWidth": 796,
      "codePoint": 209,
      "height": 64,
      "leftSideBearing": 91,
      "width": -91,
      "xMax": 0,
      "xMin": 91,
      "yMax": 868,
      "yMin": 804
    },
    {
      "advanceWidth": 832,
      "codePoint": 210,
      "height": 47,
      "leftSideBearing": 85,
      "width": -103,
      "xMax": -18,
      "xMin": 85,
      "yMax": 892,
      "yMin": 845
    },
    {
      "advanceWidth": 832,
      "codePoint": 211,
      "height": 47,
      "leftSideBearing": 85,
      "width": -103,
      "xMax": -18,
      "xMin": 85,
      "yMax": 892,
      "yMin": 845
    },
    {
      "advanceWidth": 832,
      "codePoint": 212,
      "height": 47,
      "leftSideBearing": 85,
      "width": -103,
      "xMax": -18,
      "xMin": 85,
      "yMax": 892,
      "yMin": 845
    },
    {
      "advanceWidth": 832,
      "codePoint": 213,
      "height": 23,
      "leftSideBearing": 85,
      "width": -103,
      "xMax": -18,
      "xMin": 85,
      "yMax": 868,
      "yMin": 845
    },
    {
      "advanceWidth": 832,
      "codePoint": 214,
      "height": 53,
      "leftSideBearing": 85,
      "width": -103,
      "xMax": -18,
      "xMin": 85,
      "yMax": 898,
      "yMin": 845
    },
    {
      "advanceWidth": 666,
      "codePoint": 215,
      "height": -102,
      "leftSideBearing": 80,
      "width": -44,
      "xMax": 36,
      "xMin": 80,
      "yMax": 570,
      "yMin": 672
    },
    {
      "advanceWidth": 832,
      "codePoint": 216,
      "height": -129,
      "leftSideBearing": 56,
      "width": -86,
      "xMax": -30,
      "xMin": 56,
      "yMax": 740,
      "yMin": 869
    },
    {
      "advanceWidth": 704,
      "codePoint": 217,
      "height": 167,
      "leftSideBearing": 105,
      "width": -123,
      "xMax": -18,
      "xMin": 105,
      "yMax": 892,
      "yMin": 725
    },
    {
      "advanceWidth": 704,
      "codePoint": 218,
      "height": 167,
      "leftSideBearing": 105,
      "width": -123,
      "xMax": -18,
      "xMin": 105,
      "yMax": 892,
      "yMin": 725
    },
    {
      "advanceWidth": 704,
      "codePoint": 219,
      "height": 167,
      "leftSideBearing": 105,
      "width": -123,
      "xMax": -18,
      "xMin": 105,
      "yMax": 892,
      "yMin": 725
    },
    {
      "advanceWidth": 704,
      "codePoint": 220,
      "height": 173,
      "leftSideBearing": 105,
      "width": -123,
      "xMax": -18,
      "xMin": 105,
      "yMax": 898,
      "yMin": 725
    },
    {
      "advanceWidth": 612,
      "codePoint": 221,
      "height": 171,
      "leftSideBearing": 89,
      "width": -89,
      "xMax": 0,
      "xMin": 89,
      "yMax": 892,
      "yMin": 721
    },
    {
      "advanceWidth": 593,
      "codePoint": 222,
      "height": 86,
      "leftSideBearing": 91,
      "width": -91,
      "xMax": 0,
      "xMin": 91,
      "yMax": 708,
      "yMin": 622
    },
    {
      "advanceWidth": 611,
      "codePoint": 223,
      "height": 176,
      "leftSideBearing": 68,
      "width": -80,
      "xMax": -12,
      "xMin": 68,
      "yMax": 768,
      "yMin": 592
    },
    {
      "advanceWidth": 519,
      "codePoint": 224,
      "height": 202,
      "leftSideBearing": 58,
      "width": -70,
      "xMax": -12,
      "xMin": 58,
      "yMax": 708,
      "yMin": 506
    },
    {
      "advanceWidth": 519,
      "codePoint": 225,
      "height": 183,
      "leftSideBearing": 58,
      "width": -70,
      "xMax": -12,
      "xMin": 58,
      "yMax": 708,
      "yMin": 525
    },
    {
      "advanceWidth": 519,
      "codePoint": 226,
      "height": 202,
      "leftSideBearing": 58,
      "width": -70,
      "xMax": -12,
      "xMin": 58,
      "yMax": 708,
      "yMin": 506
    },
    {
      "advanceWidth": 519,
      "codePoint": 227,
      "height": 160,
      "leftSideBearing": 58,
      "width": -70,
      "xMax": -12,
      "xMin": 58,
      "yMax": 684,
      "yMin": 524
    },
    {
      "advanceWidth": 519,
      "codePoint": 228,
      "height": 195,
      "leftSideBearing": 58,
      "width": -70,
      "xMax": -12,
      "xMin": 58,
      "yMax": 714,
      "yMin": 519
    },
    {
      "advanceWidth": 519,
      "codePoint": 229,
      "height": 244,
      "leftSideBearing": 58,
      "width": -70,
      "xMax": -12,
      "xMin": 58,
      "yMax": 750,
      "yMin": 506
    },
    {
      "advanceWidth": 852,
      "codePoint": 230,
      "height": -365,
      "leftSideBearing": 53,
      "width": -71,
      "xMax": -18,
      "xMin": 53,
      "yMax": 486,
      "yMin": 851
    },
    {
      "advanceWidth": 482,
      "codePoint": 231,
      "height": -47,
      "leftSideBearing": 70,
      "width": -298,
      "xMax": -228,
      "xMin": 70,
      "yMax": 485,
      "yMin": 532
    },
    {
      "advanceWidth": 556,
      "codePoint": 232,
      "height": 153,
      "leftSideBearing": 65,
      "width": -77,
      "xMax": -12,
      "xMin": 65,
      "yMax": 708,
      "yMin": 555
    },
    {
      "advanceWidth": 556,
      "codePoint": 233,
      "height": 153,
      "leftSideBearing": 65,
      "width": -77,
      "xMax": -12,
      "xMin": 65,
      "yMax": 708,
      "yMin": 555
    },
    {
      "advanceWidth": 556,
      "codePoint": 234,
      "height": 153,
      "leftSideBearing": 65,
      "width": -77,
      "xMax": -12,
      "xMin": 65,
      "yMax": 708,
      "yMin": 555
    },
    {
      "advanceWidth": 556,
      "codePoint": 235,
      "height": 159,
      "leftSideBearing": 65,
      "width": -77,
      "xMax": -12,
      "xMin": 65,
      "yMax": 714,
      "yMin": 555
    },
    {
      "advanceWidth": 240,
      "codePoint": 236,
      "height": 443,
      "leftSideBearing": 53,
      "width": -53,
      "xMax": 0,
      "xMin": 53,
      "yMax": 708,
      "yMin": 265
    },
    {
      "advanceWidth": 240,
      "codePoint": 237,
      "height": 323,
      "leftSideBearing": 75,
      "width": -75,
      "xMax": 0,
      "xMin": 75,
      "yMax": 708,
      "yMin": 385
    },
    {
      "advanceWidth": 240,
      "codePoint": 238,
      "height": 344,
      "leftSideBearing": 34,
      "width": -34,
      "xMax": 0,
      "xMin": 34,
      "yMax": 708,
      "yMin": 364
    },
    {
      "advanceWidth": 240,
      "codePoint": 239,
      "height": 335,
      "leftSideBearing": 44,
      "width": -44,
      "xMax": 0,
      "xMin": 44,
      "yMax": 714,
      "yMin": 379
    },
    {
      "advanceWidth": 594,
      "codePoint": 240,
      "height": 188,
      "leftSideBearing": 70,
      "width": -82,
      "xMax": -12,
      "xMin": 70,
      "yMax": 782,
      "yMin": 594
    },
    {
      "advanceWidth": 556,
      "codePoint": 241,
      "height": 142,
      "leftSideBearing": 68,
      "width": -68,
      "xMax": 0,
      "xMin": 68,
      "yMax": 684,
      "yMin": 542
    },
    {
      "advanceWidth": 594,
      "codePoint": 242,
      "height": 119,
      "leftSideBearing": 70,
      "width": -82,
      "xMax": -12,
      "xMin": 70,
      "yMax": 708,
      "yMin": 589
    },
    {
      "advanceWidth": 594,
      "codePoint": 243,
      "height": 119,
      "leftSideBearing": 70,
      "width": -82,
      "xMax": -12,
      "xMin": 70,
      "yMax": 708,
      "yMin": 589
    },
    {
      "advanceWidth": 594,
      "codePoint": 244,
      "height": 119,
      "leftSideBearing": 70,
      "width": -82,
      "xMax": -12,
      "xMin": 70,
      "yMax": 708,
      "yMin": 589
    },
    {
      "advanceWidth": 594,
      "codePoint": 245,
      "height": 95,
      "leftSideBearing": 70,
      "width": -82,
      "xMax": -12,
      "xMin": 70,
      "yMax": 684,
      "yMin": 589
    },
    {
      "advanceWidth": 594,
      "codePoint": 246,
      "height": 125,
      "leftSideBearing": 70,
      "width": -82,
      "xMax": -12,
      "xMin": 70,
      "yMax": 714,
      "yMin": 589
    },
    {
      "advanceWidth": 666,
      "codePoint": 247,
      "height": -111,
      "leftSideBearing": 102,
      "width": -34,
      "xMax": 68,
      "xMin": 102,
      "yMax": 536,
      "yMin": 647
    },
    {
      "advanceWidth": 594,
      "codePoint": 248,
      "height": -132,
      "leftSideBearing": 41,
      "width": -73,
      "xMax": -32,
      "xMin": 41,
      "yMax": 503,
      "yMin": 635
    },
    {
      "advanceWidth": 556,
      "codePoint": 249,
      "height": 154,
      "leftSideBearing": 85,
      "width": -97,
      "xMax": -12,
      "xMin": 85,
      "yMax": 708,
      "yMin": 554
    },
    {
      "advanceWidth": 556,
      "codePoint": 250,
      "height": 154,
      "leftSideBearing": 85,
      "width": -97,
      "xMax": -12,
      "xMin": 85,
      "yMax": 708,
      "yMin": 554
    },
    {
      "advanceWidth": 556,
      "codePoint": 251,
      "height": 154,
      "leftSideBearing": 85,
      "width": -97,
      "xMax": -12,
      "xMin": 85,
      "yMax": 708,
      "yMin": 554
    },
    {
      "advanceWidth": 556,
      "codePoint": 252,
      "height": 160,
      "leftSideBearing": 85,
      "width": -97,
      "xMax": -12,
      "xMin": 85,
      "yMax": 714,
      "yMin": 554
    },
    {
      "advanceWidth": 500,
      "codePoint": 253,
      "height": 153,
      "leftSideBearing": -9,
      "width": -231,
      "xMax": -240,
      "xMin": -9,
      "yMax": 708,
      "yMin": 555
    },
    {
      "advanceWidth": 611,
      "codePoint": 254,
      "height": 150,
      "leftSideBearing": 35,
      "width": -263,
      "xMax": -228,
      "xMin": 35,
      "yMax": 756,
      "yMin": 606
    },
    {
      "advanceWidth": 500,
      "codePoint": 255,
      "height": 159,
      "leftSideBearing": -9,
      "width": -231,
      "xMax": -240,
      "xMin": -9,
      "yMax": 714,
      "yMin": 555
    },
    {
      "advanceWidth": 704,
      "codePoint": 256,
      "height": 151,
      "leftSideBearing": 1,
      "width": -1,
      "xMax": 0,
      "xMin": 1,
      "yMax": 854,
      "yMin": 703
    },
    {
      "advanceWidth": 519,
      "codePoint": 257,
      "height": 160,
      "leftSideBearing": 58,
      "width": -70,
      "xMax": -12,
      "xMin": 58,
      "yMax": 666,
      "yMin": 506
    },
    {
      "advanceWidth": 704,
      "codePoint": 258,
      "height": 203,
      "leftSideBearing": 1,
      "width": -1,
      "xMax": 0,
      "xMin": 1,
      "yMax": 906,
      "yMin": 703
    },
    {
      "advanceWidth": 519,
      "codePoint": 259,
      "height": 196,
      "leftSideBearing": 58,
      "width": -70,
      "xMax": -12,
      "xMin": 58,
      "yMax": 702,
      "yMin": 506
    },
    {
      "advanceWidth": 704,
      "codePoint": 260,
      "height": 5,
      "leftSideBearing": 1,
      "width": -222,
      "xMax": -221,
      "xMin": 1,
      "yMax": 708,
      "yMin": 703
    },
    {
      "advanceWidth": 519,
      "codePoint": 261,
      "height": -20,
      "leftSideBearing": 58,
      "width": -279,
      "xMax": -221,
      "xMin": 58,
      "yMax": 486,
      "yMin": 506
    },
    {
      "advanceWidth": 704,
      "codePoint": 262,
      "height": 154,
      "leftSideBearing": 86,
      "width": -104,
      "xMax": -18,
      "xMin": 86,
      "yMax": 904,
      "yMin": 750
    },
    {
      "advanceWidth": 482,
      "codePoint": 263,
      "height": 162,
      "leftSideBearing": 70,
      "width": -82,
      "xMax": -12,
      "xMin": 70,
      "yMax": 708,
      "yMin": 546
    },
    {
      "advanceWidth": 704,
      "codePoint": 264,
      "height": 154,
      "leftSideBearing": 86,
      "width": -104,
      "xMax": -18,
      "xMin": 86,
      "yMax": 904,
      "yMin": 750
    },
    {
      "advanceWidth": 482,
      "codePoint": 265,
      "height": 176,
      "leftSideBearing": 70,
      "width": -82,
      "xMax": -12,
      "xMin": 70,
      "yMax": 708,
      "yMin": 532
    },
    {
      "advanceWidth": 704,
      "codePoint": 266,
      "height": 148,
      "leftSideBearing": 86,
      "width": -104,
      "xMax": -18,
      "xMin": 86,
      "yMax": 898,
      "yMin": 750
    },
    {
      "advanceWidth": 482,
      "codePoint": 267,
      "height": 182,
      "leftSideBearing": 70,
      "width": -82,
      "xMax": -12,
      "xMin": 70,
      "yMax": 714,
      "yMin": 532
    },
    {
      "advanceWidth": 704,
      "codePoint": 268,
      "height": 154,
      "leftSideBearing": 86,
      "width": -104,
      "xMax": -18,
      "xMin": 86,
      "yMax": 904,
      "yMin": 750
    },
    {
      "advanceWidth": 482,
      "codePoint": 269,
      "height": 171,
      "leftSideBearing": 70,
      "width": -82,
      "xMax": -12,
      "xMin": 70,
      "yMax": 708,
      "yMin": 537
    },
    {
      "advanceWidth": 741,
      "codePoint": 270,
      "height": 156,
      "leftSideBearing": 75,
      "width": -75,
      "xMax": 0,
      "xMin": 75,
      "yMax": 904,
      "yMin": 748
    },
    {
      "advanceWidth": 611,
      "codePoint": 271,
      "height": -99,
      "leftSideBearing": 70,
      "width": -82,
      "xMax": -12,
      "xMin": 70,
      "yMax": 756,
      "yMin": 855
    },
    {
      "advanceWidth": 741,
      "codePoint": 272,
      "height": -40,
      "leftSideBearing": 50,
      "width": -50,
      "xMax": 0,
      "xMin": 50,
      "yMax": 708,
      "yMin": 748
    },
    {
      "advanceWidth": 611,
      "codePoint": 273,
      "height": 62,
      "leftSideBearing": 70,
      "width": -82,
      "xMax": -12,
      "xMin": 70,
      "yMax": 756,
      "yMin": 694
    },
    {
      "advanceWidth": 611,
      "codePoint": 274,
      "height": 207,
      "leftSideBearing": 91,
      "width": -91,
      "xMax": 0,
      "xMin": 91,
      "yMax": 854,
      "yMin": 647
    },
    {
      "advanceWidth": 556,
      "codePoint": 275,
      "height": 111,
      "leftSideBearing": 65,
      "width": -77,
      "xMax": -12,
      "xMin": 65,
      "yMax": 666,
      "yMin": 555
    },
    {
      "advanceWidth": 611,
      "codePoint": 276,
      "height": 259,
      "leftSideBearing": 91,
      "width": -91,
      "xMax": 0,
      "xMin": 91,
      "yMax": 906,
      "yMin": 647
    },
    {
      "advanceWidth": 556,
      "codePoint": 277,
      "height": 147,
      "leftSideBearing": 65,
      "width": -77,
      "xMax": -12,
      "xMin": 65,
      "yMax": 702,
      "yMin": 555
    },
    {
      "advanceWidth": 611,
      "codePoint": 278,
      "height": 251,
      "leftSideBearing": 91,
      "width": -91,
      "xMax": 0,
      "xMin": 91,
      "yMax": 898,
      "yMin": 647
    },
    {
      "advanceWidth": 556,
      "codePoint": 279,
      "height": 159,
      "leftSideBearing": 65,
      "width": -77,
      "xMax": -12,
      "xMin": 65,
      "yMax": 714,
      "yMin": 555
    },
    {
      "advanceWidth": 611,
      "codePoint": 280,
      "height": 61,
      "leftSideBearing": 91,
      "width": -312,
      "xMax": -221,
      "xMin": 91,
      "yMax": 708,
      "yMin": 647
    },
    {
      "advanceWidth": 556,
      "codePoint": 281,
      "height": -69,
      "leftSideBearing": 65,
      "width": -286,
      "xMax": -221,
      "xMin": 65,
      "yMax": 486,
      "yMin": 555
    },
    {
      "advanceWidth": 611,
      "codePoint": 282,
      "height": 257,
      "leftSideBearing": 91,
      "width": -91,
      "xMax": 0,
      "xMin": 91,
      "yMax": 904,
      "yMin": 647
    },
    {
      "advanceWidth": 556,
      "codePoint": 283,
      "height": 153,
      "leftSideBearing": 65,
      "width": -77,
      "xMax": -12,
      "xMin": 65,
      "yMax": 708,
      "yMin": 555
    },
    {
      "advanceWidth": 778,
      "codePoint": 284,
      "height": 135,
      "leftSideBearing": 85,
      "width": -103,
      "xMax": -18,
      "xMin": 85,
      "yMax": 904,
      "yMin": 769
    },
    {
      "advanceWidth": 611,
      "codePoint": 285,
      "height": 99,
      "leftSideBearing": 30,
      "width": -270,
      "xMax": -240,
      "xMin": 30,
      "yMax": 708,
      "yMin": 609
    },
    {
      "advanceWidth": 778,
      "codePoint": 286,
      "height": 137,
      "leftSideBearing": 85,
      "width": -103,
      "xMax": -18,
      "xMin": 85,
      "yMax": 906,
      "yMin": 769
    },
    {
      "advanceWidth": 611,
      "codePoint": 287,
      "height": 93,
      "leftSideBearing": 30,
      "width": -270,
      "xMax": -240,
      "xMin": 30,
      "yMax": 702,
      "yMin": 609
    },
    {
      "advanceWidth": 778,
      "codePoint": 288,
      "height": 129,
      "leftSideBearing": 85,
      "width": -103,
      "xMax": -18,
      "xMin": 85,
      "yMax": 898,
      "yMin": 769
    },
    {
      "advanceWidth": 611,
      "codePoint": 289,
      "height": 105,
      "leftSideBearing": 30,
      "width": -270,
      "xMax": -240,
      "xMin": 30,
      "yMax": 714,
      "yMin": 609
    },
    {
      "advanceWidth": 778,
      "codePoint": 290,
      "height": -43,
      "leftSideBearing": 85,
      "width": -320,
      "xMax": -235,
      "xMin": 85,
      "yMax": 726,
      "yMin": 769
    },
    {
      "advanceWidth": 611,
      "codePoint": 291,
      "height": 150,
      "leftSideBearing": 30,
      "width": -270,
      "xMax": -240,
      "xMin": 30,
      "yMax": 759,
      "yMin": 609
    },
    {
      "advanceWidth": 722,
      "codePoint": 292,
      "height": 155,
      "leftSideBearing": 91,
      "width": -91,
      "xMax": 0,
      "xMin": 91,
      "yMax": 904,
      "yMin": 749
    },
    {
      "advanceWidth": 556,
      "codePoint": 293,
      "height": 403,
      "leftSideBearing": 68,
      "width": -68,
      "xMax": 0,
      "xMin": 68,
      "yMax": 940,
      "yMin": 537
    },
    {
      "advanceWidth": 741,
      "codePoint": 294,
      "height": -41,
      "leftSideBearing": 91,
      "width": -91,
      "xMax": 0,
      "xMin": 91,
      "yMax": 708,
      "yMin": 749
    },
    {
      "advanceWidth": 556,
      "codePoint": 295,
      "height": 219,
      "leftSideBearing": 68,
      "width": -68,
      "xMax": 0,
      "xMin": 68,
      "yMax": 756,
      "yMin": 537
    },
    {
      "advanceWidth": 278,
      "codePoint": 296,
      "height": 451,
      "leftSideBearing": 75,
      "width": -75,
      "xMax": 0,
      "xMin": 75,
      "yMax": 878,
      "yMin": 427
    },
    {
      "advanceWidth": 240,
      "codePoint": 297,
      "height": 302,
      "leftSideBearing": 30,
      "width": -30,
      "xMax": 0,
      "xMin": 30,
      "yMax": 684,
      "yMin": 382
    },
    {
      "advanceWidth": 278,
      "codePoint": 298,
      "height": 456,
      "leftSideBearing": 91,
      "width": -91,
      "xMax": 0,
      "xMin": 91,
      "yMax": 854,
      "yMin": 398
    },
    {
      "advanceWidth": 240,
      "codePoint": 299,
      "height": 311,
      "leftSideBearing": 58,
      "width": -58,
      "xMax": 0,
      "xMin": 58,
      "yMax": 666,
      "yMin": 355
    },
    {
      "advanceWidth": 278,
      "codePoint": 302,
      "height": 422,
      "leftSideBearing": -14,
      "width": -207,
      "xMax": -221,
      "xMin": -14,
      "yMax": 708,
      "yMin": 286
    },
    {
      "advanceWidth": 240,
      "codePoint": 303,
      "height": 430,
      "leftSideBearing": -25,
      "width": -196,
      "xMax": -221,
      "xMin": -25,
      "yMax": 710,
      "yMin": 280
    },
    {
      "advanceWidth": 278,
      "codePoint": 304,
      "height": 578,
      "leftSideBearing": 91,
      "width": -91,
      "xMax": 0,
      "xMin": 91,
      "yMax": 898,
      "yMin": 320
    },
    {
      "advanceWidth": 240,
      "codePoint": 305,
      "height": 243,
      "leftSideBearing": 75,
      "width": -75,
      "xMax": 0,
      "xMin": 75,
      "yMax": 474,
      "yMin": 231
    },
    {
      "advanceWidth": 730,
      "codePoint": 306,
      "height": -47,
      "leftSideBearing": 91,
      "width": -109,
      "xMax": -18,
      "xMin": 91,
      "yMax": 708,
      "yMin": 755
    },
    {
      "advanceWidth": 477,
      "codePoint": 307,
      "height": 193,
      "leftSideBearing": 75,
      "width": -315,
      "xMax": -240,
      "xMin": 75,
      "yMax": 710,
      "yMin": 517
    },
    {
      "advanceWidth": 482,
      "codePoint": 308,
      "height": 272,
      "leftSideBearing": 28,
      "width": -46,
      "xMax": -18,
      "xMin": 28,
      "yMax": 904,
      "yMin": 632
    },
    {
      "advanceWidth": 240,
      "codePoint": 309,
      "height": 344,
      "leftSideBearing": -70,
      "width": -170,
      "xMax": -240,
      "xMin": -70,
      "yMax": 708,
      "yMin": 364
    },
    {
      "advanceWidth": 648,
      "codePoint": 310,
      "height": -33,
      "leftSideBearing": 91,
      "width": -326,
      "xMax": -235,
      "xMin": 91,
      "yMax": 708,
      "yMin": 741
    },
    {
      "advanceWidth": 519,
      "codePoint": 311,
      "height": 203,
      "leftSideBearing": 68,
      "width": -303,
      "xMax": -235,
      "xMin": 68,
      "yMax": 756,
      "yMin": 553
    },
    {
      "advanceWidth": 519,
      "codePoint": 313,
      "height": 380,
      "leftSideBearing": 91,
      "width": -91,
      "xMax": 0,
      "xMin": 91,
      "yMax": 904,
      "yMin": 524
    },
    {
      "advanceWidth": 240,
      "codePoint": 314,
      "height": 494,
      "leftSideBearing": 75,
      "width": -75,
      "xMax": 0,
      "xMin": 75,
      "yMax": 936,
      "yMin": 442
    },
    {
      "advanceWidth": 519,
      "codePoint": 315,
      "height": 184,
      "leftSideBearing": 91,
      "width": -326,
      "xMax": -235,
      "xMin": 91,
      "yMax": 708,
      "yMin": 524
    },
    {
      "advanceWidth": 240,
      "codePoint": 316,
      "height": 485,
      "leftSideBearing": -39,
      "width": -196,
      "xMax": -235,
      "xMin": -39,
      "yMax": 756,
      "yMin": 271
    },
    {
      "advanceWidth": 519,
      "codePoint": 317,
      "height": 184,
      "leftSideBearing": 91,
      "width": -91,
      "xMax": 0,
      "xMin": 91,
      "yMax": 708,
      "yMin": 524
    },
    {
      "advanceWidth": 240,
      "codePoint": 318,
      "height": 289,
      "leftSideBearing": 75,
      "width": -75,
      "xMax": 0,
      "xMin": 75,
      "yMax": 756,
      "yMin": 467
    },
    {
      "advanceWidth": 519,
      "codePoint": 319,
      "height": 184,
      "leftSideBearing": 91,
      "width": -91,
      "xMax": 0,
      "xMin": 91,
      "yMax": 708,
      "yMin": 524
    },
    {
      "advanceWidth": 300,
      "codePoint": 320,
      "height": 363,
      "leftSideBearing": 75,
      "width": -75,
      "xMax": 0,
      "xMin": 75,
      "yMax": 756,
      "yMin": 393
    },
    {
      "advanceWidth": 519,
      "codePoint": 321,
      "height": 184,
      "leftSideBearing": 39,
      "width": -39,
      "xMax": 0,
      "xMin": 39,
      "yMax": 708,
      "yMin": 524
    },
    {
      "advanceWidth": 240,
      "codePoint": 322,
      "height": 435,
      "leftSideBearing": 27,
      "width": -27,
      "xMax": 0,
      "xMin": 27,
      "yMax": 756,
      "yMin": 321
    },
    {
      "advanceWidth": 796,
      "codePoint": 323,
      "height": 100,
      "leftSideBearing": 91,
      "width": -91,
      "xMax": 0,
      "xMin": 91,
      "yMax": 904,
      "yMin": 804
    },
    {
      "advanceWidth": 556,
      "codePoint": 324,
      "height": 164,
      "leftSideBearing": 68,
      "width": -68,
      "xMax": 0,
      "xMin": 68,
      "yMax": 708,
      "yMin": 544
    },
    {
      "advanceWidth": 796,
      "codePoint": 325,
      "height": -96,
      "leftSideBearing": 91,
      "width": -326,
      "xMax": -235,
      "xMin": 91,
      "yMax": 708,
      "yMin": 804
    },
    {
      "advanceWidth": 556,
      "codePoint": 326,
      "height": -51,
      "leftSideBearing": 68,
      "width": -303,
      "xMax": -235,
      "xMin": 68,
      "yMax": 486,
      "yMin": 537
    },
    {
      "advanceWidth": 796,
      "codePoint": 327,
      "height": 100,
      "leftSideBearing": 91,
      "width": -91,
      "xMax": 0,
      "xMin": 91,
      "yMax": 904,
      "yMin": 804
    },
    {
      "advanceWidth": 556,
      "codePoint": 328,
      "height": 171,
      "leftSideBearing": 68,
      "width": -68,
      "xMax": 0,
      "xMin": 68,
      "yMax": 708,
      "yMin": 537
    },
    {
      "advanceWidth": 556,
      "codePoint": 329,
      "height": 171,
      "leftSideBearing": 51,
      "width": -51,
      "xMax": 0,
      "xMin": 51,
      "yMax": 708,
      "yMin": 537
    },
    {
      "advanceWidth": 832,
      "codePoint": 332,
      "height": 9,
      "leftSideBearing": 85,
      "width": -103,
      "xMax": -18,
      "xMin": 85,
      "yMax": 854,
      "yMin": 845
    },
    {
      "advanceWidth": 594,
      "codePoint": 333,
      "height": 77,
      "leftSideBearing": 70,
      "width": -82,
      "xMax": -12,
      "xMin": 70,
      "yMax": 666,
      "yMin": 589
    },
    {
      "advanceWidth": 832,
      "codePoint": 334,
      "height": 61,
      "leftSideBearing": 85,
      "width": -103,
      "xMax": -18,
      "xMin": 85,
      "yMax": 906,
      "yMin": 845
    },
    {
      "advanceWidth": 594,
      "codePoint": 335,
      "height": 113,
      "leftSideBearing": 70,
      "width": -82,
      "xMax": -12,
      "xMin": 70,
      "yMax": 702,
      "yMin": 589
    },
    {
      "advanceWidth": 832,
      "codePoint": 336,
      "height": 59,
      "leftSideBearing": 85,
      "width": -103,
      "xMax": -18,
      "xMin": 85,
      "yMax": 904,
      "yMin": 845
    },
    {
      "advanceWidth": 593,
      "codePoint": 337,
      "height": 52,
      "leftSideBearing": 70,
      "width": -82,
      "xMax": -12,
      "xMin": 70,
      "yMax": 708,
      "yMin": 656
    },
    {
      "advanceWidth": 981,
      "codePoint": 338,
      "height": -302,
      "leftSideBearing": 96,
      "width": -96,
      "xMax": 0,
      "xMin": 96,
      "yMax": 708,
      "yMin": 1010
    },
    {
      "advanceWidth": 926,
      "codePoint": 339,
      "height": -442,
      "leftSideBearing": 64,
      "width": -76,
      "xMax": -12,
      "xMin": 64,
      "yMax": 486,
      "yMin": 928
    },
    {
      "advanceWidth": 611,
      "codePoint": 340,
      "height": 261,
      "leftSideBearing": 91,
      "width": -91,
      "xMax": 0,
      "xMin": 91,
      "yMax": 904,
      "yMin": 643
    },
    {
      "advanceWidth": 370,
      "codePoint": 341,
      "height": 284,
      "leftSideBearing": 68,
      "width": -68,
      "xMax": 0,
      "xMin": 68,
      "yMax": 708,
      "yMin": 424
    },
    {
      "advanceWidth": 611,
      "codePoint": 342,
      "height": 65,
      "leftSideBearing": 91,
      "width": -326,
      "xMax": -235,
      "xMin": 91,
      "yMax": 708,
      "yMin": 643
    },
    {
      "advanceWidth": 370,
      "codePoint": 343,
      "height": 77,
      "leftSideBearing": -29,
      "width": -206,
      "xMax": -235,
      "xMin": -29,
      "yMax": 486,
      "yMin": 409
    },
    {
      "advanceWidth": 611,
      "codePoint": 344,
      "height": 261,
      "leftSideBearing": 91,
      "width": -91,
      "xMax": 0,
      "xMin": 91,
      "yMax": 904,
      "yMin": 643
    },
    {
      "advanceWidth": 370,
      "codePoint": 345,
      "height": 268,
      "leftSideBearing": 68,
      "width": -68,
      "xMax": 0,
      "xMin": 68,
      "yMax": 708,
      "yMin": 440
    },
    {
      "advanceWidth": 556,
      "codePoint": 346,
      "height": 316,
      "leftSideBearing": 44,
      "width": -62,
      "xMax": -18,
      "xMin": 44,
      "yMax": 904,
      "yMin": 588
    },
    {
      "advanceWidth": 444,
      "codePoint": 347,
      "height": 244,
      "leftSideBearing": 38,
      "width": -50,
      "xMax": -12,
      "xMin": 38,
      "yMax": 708,
      "yMin": 464
    },
    {
      "advanceWidth": 556,
      "codePoint": 348,
      "height": 316,
      "leftSideBearing": 44,
      "width": -62,
      "xMax": -18,
      "xMin": 44,
      "yMax": 904,
      "yMin": 588
    },
    {
      "advanceWidth": 444,
      "codePoint": 349,
      "height": 258,
      "leftSideBearing": 38,
      "width": -50,
      "xMax": -12,
      "xMin": 38,
      "yMax": 708,
      "yMin": 450
    },
    {
      "advanceWidth": 556,
      "codePoint": 350,
      "height": 138,
      "leftSideBearing": 44,
      "width": -272,
      "xMax": -228,
      "xMin": 44,
      "yMax": 726,
      "yMin": 588
    },
    {
      "advanceWidth": 444,
      "codePoint": 351,
      "height": 39,
      "leftSideBearing": 38,
      "width": -266,
      "xMax": -228,
      "xMin": 38,
      "yMax": 486,
      "yMin": 447
    },
    {
      "advanceWidth": 556,
      "codePoint": 352,
      "height": 304,
      "leftSideBearing": 44,
      "width": -62,
      "xMax": -18,
      "xMin": 44,
      "yMax": 892,
      "yMin": 588
    },
    {
      "advanceWidth": 444,
      "codePoint": 353,
      "height": 242,
      "leftSideBearing": 38,
      "width": -50,
      "xMax": -12,
      "xMin": 38,
      "yMax": 708,
      "yMin": 466
    },
    {
      "advanceWidth": 574,
      "codePoint": 354,
      "height": 46,
      "leftSideBearing": 97,
      "width": -332,
      "xMax": -235,
      "xMin": 97,
      "yMax": 708,
      "yMin": 662
    },
    {
      "advanceWidth": 370,
      "codePoint": 355,
      "height": 219,
      "leftSideBearing": 54,
      "width": -289,
      "xMax": -235,
      "xMin": 54,
      "yMax": 607,
      "yMin": 388
    },
    {
      "advanceWidth": 574,
      "codePoint": 356,
      "height": 242,
      "leftSideBearing": 97,
      "width": -97,
      "xMax": 0,
      "xMin": 97,
      "yMax": 904,
      "yMin": 662
    },
    {
      "advanceWidth": 370,
      "codePoint": 357,
      "height": 191,
      "leftSideBearing": 54,
      "width": -66,
      "xMax": -12,
      "xMin": 54,
      "yMax": 708,
      "yMin": 517
    },
    {
      "advanceWidth": 574,
      "codePoint": 358,
      "height": 46,
      "leftSideBearing": 97,
      "width": -97,
      "xMax": 0,
      "xMin": 97,
      "yMax": 708,
      "yMin": 662
    },
    {
      "advanceWidth": 370,
      "codePoint": 359,
      "height": 219,
      "leftSideBearing": 54,
      "width": -66,
      "xMax": -12,
      "xMin": 54,
      "yMax": 607,
      "yMin": 388
    },
    {
      "advanceWidth": 704,
      "codePoint": 360,
      "height": 153,
      "leftSideBearing": 105,
      "width": -123,
      "xMax": -18,
      "xMin": 105,
      "yMax": 878,
      "yMin": 725
    },
    {
      "advanceWidth": 556,
      "codePoint": 361,
      "height": 130,
      "leftSideBearing": 85,
      "width": -97,
      "xMax": -12,
      "xMin": 85,
      "yMax": 684,
      "yMin": 554
    },
    {
      "advanceWidth": 704,
      "codePoint": 362,
      "height": 129,
      "leftSideBearing": 105,
      "width": -123,
      "xMax": -18,
      "xMin": 105,
      "yMax": 854,
      "yMin": 725
    },
    {
      "advanceWidth": 556,
      "codePoint": 363,
      "height": 112,
      "leftSideBearing": 85,
      "width": -97,
      "xMax": -12,
      "xMin": 85,
      "yMax": 666,
      "yMin": 554
    },
    {
      "advanceWidth": 704,
      "codePoint": 364,
      "height": 181,
      "leftSideBearing": 105,
      "width": -123,
      "xMax": -18,
      "xMin": 105,
      "yMax": 906,
      "yMin": 725
    },
    {
      "advanceWidth": 556,
      "codePoint": 365,
      "height": 148,
      "leftSideBearing": 85,
      "width": -97,
      "xMax": -12,
      "xMin": 85,
      "yMax": 702,
      "yMin": 554
    },
    {
      "advanceWidth": 704,
      "codePoint": 366,
      "height": 219,
      "leftSideBearing": 105,
      "width": -123,
      "xMax": -18,
      "xMin": 105,
      "yMax": 944,
      "yMin": 725
    },
    {
      "advanceWidth": 556,
      "codePoint": 367,
      "height": 196,
      "leftSideBearing": 85,
      "width": -97,
      "xMax": -12,
      "xMin": 85,
      "yMax": 750,
      "yMin": 554
    },
    {
      "advanceWidth": 704,
      "codePoint": 368,
      "height": 176,
      "leftSideBearing": 105,
      "width": -123,
      "xMax": -18,
      "xMin": 105,
      "yMax": 904,
      "yMin": 728
    },
    {
      "advanceWidth": 556,
      "codePoint": 369,
      "height": 75,
      "leftSideBearing": 85,
      "width": -97,
      "xMax": -12,
      "xMin": 85,
      "yMax": 708,
      "yMin": 633
    },
    {
      "advanceWidth": 704,
      "codePoint": 370,
      "height": -17,
      "leftSideBearing": 105,
      "width": -326,
      "xMax": -221,
      "xMin": 105,
      "yMax": 708,
      "yMin": 725
    },
    {
      "advanceWidth": 556,
      "codePoint": 371,
      "height": -80,
      "leftSideBearing": 85,
      "width": -306,
      "xMax": -221,
      "xMin": 85,
      "yMax": 474,
      "yMin": 554
    },
    {
      "advanceWidth": 962,
      "codePoint": 372,
      "height": -156,
      "leftSideBearing": 100,
      "width": -100,
      "xMax": 0,
      "xMin": 100,
      "yMax": 904,
      "yMin": 1060
    },
    {
      "advanceWidth": 759,
      "codePoint": 373,
      "height": -106,
      "leftSideBearing": 77,
      "width": -77,
      "xMax": 0,
      "xMin": 77,
      "yMax": 708,
      "yMin": 814
    },
    {
      "advanceWidth": 612,
      "codePoint": 374,
      "height": 183,
      "leftSideBearing": 89,
      "width": -89,
      "xMax": 0,
      "xMin": 89,
      "yMax": 904,
      "yMin": 721
    },
    {
      "advanceWidth": 500,
      "codePoint": 375,
      "height": 153,
      "leftSideBearing": -9,
      "width": -231,
      "xMax": -240,
      "xMin": -9,
      "yMax": 708,
      "yMin": 555
    },
    {
      "advanceWidth": 612,
      "codePoint": 376,
      "height": 177,
      "leftSideBearing": 89,
      "width": -89,
      "xMax": 0,
      "xMin": 89,
      "yMax": 898,
      "yMin": 721
    },
    {
      "advanceWidth": 593,
      "codePoint": 377,
      "height": 250,
      "leftSideBearing": 32,
      "width": -32,
      "xMax": 0,
      "xMin": 32,
      "yMax": 904,
      "yMin": 654
    },
    {
      "advanceWidth": 463,
      "codePoint": 378,
      "height": 223,
      "leftSideBearing": 35,
      "width": -35,
      "xMax": 0,
      "xMin": 35,
      "yMax": 708,
      "yMin": 485
    },
    {
      "advanceWidth": 593,
      "codePoint": 379,
      "height": 244,
      "leftSideBearing": 32,
      "width": -32,
      "xMax": 0,
      "xMin": 32,
      "yMax": 898,
      "yMin": 654
    },
    {
      "advanceWidth": 463,
      "codePoint": 380,
      "height": 234,
      "leftSideBearing": 35,
      "width": -35,
      "xMax": 0,
      "xMin": 35,
      "yMax": 714,
      "yMin": 480
    },
    {
      "advanceWidth": 593,
      "codePoint": 381,
      "height": 238,
      "leftSideBearing": 32,
      "width": -32,
      "xMax": 0,
      "xMin": 32,
      "yMax": 892,
      "yMin": 654
    },
    {
      "advanceWidth": 463,
      "codePoint": 382,
      "height": 212,
      "leftSideBearing": 35,
      "width": -35,
      "xMax": 0,
      "xMin": 35,
      "yMax": 708,
      "yMin": 496
    },
    {
      "advanceWidth": 556,
      "codePoint": 402,
      "height": 92,
      "leftSideBearing": -28,
      "width": -116,
      "xMax": -144,
      "xMin": -28,
      "yMax": 720,
      "yMin": 628
    },
    {
      "advanceWidth": 556,
      "codePoint": 536,
      "height": 138,
      "leftSideBearing": 44,
      "width": -279,
      "xMax": -235,
      "xMin": 44,
      "yMax": 726,
      "yMin": 588
    },
    {
      "advanceWidth": 444,
      "codePoint": 537,
      "height": 39,
      "leftSideBearing": 38,
      "width": -273,
      "xMax": -235,
      "xMin": 38,
      "yMax": 486,
      "yMin": 447
    },
    {
      "advanceWidth": 574,
      "codePoint": 538,
      "height": 46,
      "leftSideBearing": 97,
      "width": -332,
      "xMax": -235,
      "xMin": 97,
      "yMax": 708,
      "yMin": 662
    },
    {
      "advanceWidth": 370,
      "codePoint": 539,
      "height": 219,
      "leftSideBearing": 54,
      "width": -289,
      "xMax": -235,
      "xMin": 54,
      "yMax": 607,
      "yMin": 388
    },
    {
      "advanceWidth": 240,
      "codePoint": 710,
      "height": 344,
      "leftSideBearing": 34,
      "width": 530,
      "xMax": 564,
      "xMin": 34,
      "yMax": 708,
      "yMin": 364
    },
    {
      "advanceWidth": 240,
      "codePoint": 711,
      "height": 324,
      "leftSideBearing": 54,
      "width": 510,
      "xMax": 564,
      "xMin": 54,
      "yMax": 708,
      "yMin": 384
    },
    {
      "advanceWidth": 240,
      "codePoint": 713,
      "height": 309,
      "leftSideBearing": 60,
      "width": 540,
      "xMax": 600,
      "xMin": 60,
      "yMax": 666,
      "yMin": 357
    },
    {
      "advanceWidth": 240,
      "codePoint": 728,
      "height": 327,
      "leftSideBearing": 56,
      "width": 508,
      "xMax": 564,
      "xMin": 56,
      "yMax": 702,
      "yMin": 375
    },
    {
      "advanceWidth": 240,
      "codePoint": 729,
      "height": 437,
      "leftSideBearing": 146,
      "width": 448,
      "xMax": 594,
      "xMin": 146,
      "yMax": 714,
      "yMin": 277
    },
    {
      "advanceWidth": 240,
      "codePoint": 730,
      "height": 434,
      "leftSideBearing": 103,
      "width": 450,
      "xMax": 553,
      "xMin": 103,
      "yMax": 750,
      "yMin": 316
    },
    {
      "advanceWidth": 240,
      "codePoint": 731,
      "height": -181,
      "leftSideBearing": 1,
      "width": -222,
      "xMax": -221,
      "xMin": 1,
      "yMax": 7,
      "yMin": 188
    },
    {
      "advanceWidth": 240,
      "codePoint": 732,
      "height": 300,
      "leftSideBearing": 32,
      "width": 544,
      "xMax": 576,
      "xMin": 32,
      "yMax": 684,
      "yMin": 384
    },
    {
      "advanceWidth": 240,
      "codePoint": 733,
      "height": 259,
      "leftSideBearing": 29,
      "width": 535,
      "xMax": 564,
      "xMin": 29,
      "yMax": 708,
      "yMin": 449
    },
    {
      "advanceWidth": 678,
      "codePoint": 916,
      "height": 45,
      "leftSideBearing": 11,
      "width": -11,
      "xMax": 0,
      "xMin": 11,
      "yMax": 712,
      "yMin": 667
    },
    {
      "advanceWidth": 752,
      "codePoint": 937,
      "height": 28,
      "leftSideBearing": 46,
      "width": -46,
      "xMax": 0,
      "xMin": 46,
      "yMax": 721,
      "yMin": 693
    },
    {
      "advanceWidth": 556,
      "codePoint": 956,
      "height": -80,
      "leftSideBearing": 35,
      "width": -263,
      "xMax": -228,
      "xMin": 35,
      "yMax": 474,
      "yMin": 554
    },
    {
      "advanceWidth": 578,
      "codePoint": 960,
      "height": -71,
      "leftSideBearing": 31,
      "width": -38,
      "xMax": -7,
      "xMin": 31,
      "yMax": 474,
      "yMin": 545
    },
    {
      "advanceWidth": 500,
      "codePoint": 8211,
      "height": -257,
      "leftSideBearing": 28,
      "width": 176,
      "xMax": 204,
      "xMin": 28,
      "yMax": 282,
      "yMin": 539
    },
    {
      "advanceWidth": 1000,
      "codePoint": 8212,
      "height": -757,
      "leftSideBearing": 28,
      "width": 176,
      "xMax": 204,
      "xMin": 28,
      "yMax": 282,
      "yMin": 1039
    },
    {
      "advanceWidth": 278,
      "codePoint": 8216,
      "height": 387,
      "leftSideBearing": 120,
      "width": 342,
      "xMax": 462,
      "xMin": 120,
      "yMax": 708,
      "yMin": 321
    },
    {
      "advanceWidth": 278,
      "codePoint": 8217,
      "height": 387,
      "leftSideBearing": 120,
      "width": 342,
      "xMax": 462,
      "xMin": 120,
      "yMax": 708,
      "yMin": 321
    },
    {
      "advanceWidth": 278,
      "codePoint": 8218,
      "height": -124,
      "leftSideBearing": 37,
      "width": -169,
      "xMax": -132,
      "xMin": 37,
      "yMax": 114,
      "yMin": 238
    },
    {
      "advanceWidth": 519,
      "codePoint": 8220,
      "height": 178,
      "leftSideBearing": 152,
      "width": 310,
      "xMax": 462,
      "xMin": 152,
      "yMax": 708,
      "yMin": 530
    },
    {
      "advanceWidth": 519,
      "codePoint": 8221,
      "height": 178,
      "leftSideBearing": 152,
      "width": 310,
      "xMax": 462,
      "xMin": 152,
      "yMax": 708,
      "yMin": 530
    },
    {
      "advanceWidth": 519,
      "codePoint": 8222,
      "height": -333,
      "leftSideBearing": 69,
      "width": -201,
      "xMax": -132,
      "xMin": 69,
      "yMax": 114,
      "yMin": 447
    },
    {
      "advanceWidth": 556,
      "codePoint": 8224,
      "height": 117,
      "leftSideBearing": 95,
      "width": -221,
      "xMax": -126,
      "xMin": 95,
      "yMax": 708,
      "yMin": 591
    },
    {
      "advanceWidth": 556,
      "codePoint": 8225,
      "height": 119,
      "leftSideBearing": 50,
      "width": -176,
      "xMax": -126,
      "xMin": 50,
      "yMax": 708,
      "yMin": 589
    },
    {
      "advanceWidth": 500,
      "codePoint": 8226,
      "height": 50,
      "leftSideBearing": 117,
      "width": 60,
      "xMax": 177,
      "xMin": 117,
      "yMax": 531,
      "yMin": 481
    },
    {
      "advanceWidth": 1000,
      "codePoint": 8230,
      "height": -785,
      "leftSideBearing": 105,
      "width": -111,
      "xMax": -6,
      "xMin": 105,
      "yMax": 126,
      "yMin": 911
    },
    {
      "advanceWidth": 1056,
      "codePoint": 8240,
      "height": -321,
      "leftSideBearing": 93,
      "width": -124,
      "xMax": -31,
      "xMin": 93,
      "yMax": 740,
      "yMin": 1061
    },
    {
      "advanceWidth": 315,
      "codePoint": 8249,
      "height": 140,
      "leftSideBearing": 88,
      "width": -61,
      "xMax": 27,
      "xMin": 88,
      "yMax": 459,
      "yMin": 319
    },
    {
      "advanceWidth": 315,
      "codePoint": 8250,
      "height": 164,
      "leftSideBearing": 63,
      "width": -36,
      "xMax": 27,
      "xMin": 63,
      "yMax": 459,
      "yMin": 295
    },
    {
      "advanceWidth": 167,
      "codePoint": 8260,
      "height": 308,
      "leftSideBearing": -166,
      "width": 134,
      "xMax": -32,
      "xMin": -166,
      "yMax": 740,
      "yMin": 432
    },
    {
      "advanceWidth": 556,
      "codePoint": 8364,
      "height": 99,
      "leftSideBearing": 55,
      "width": -67,
      "xMax": -12,
      "xMin": 55,
      "yMax": 720,
      "yMin": 621
    },
    {
      "advanceWidth": 500,
      "codePoint": 8467,
      "height": 248,
      "leftSideBearing": 30,
      "width": -44,
      "xMax": -14,
      "xMin": 30,
      "yMax": 721,
      "yMin": 473
    },
    {
      "advanceWidth": 1000,
      "codePoint": 8482,
      "height": -293,
      "leftSideBearing": 124,
      "width": 172,
      "xMax": 296,
      "xMin": 124,
      "yMax": 708,
      "yMin": 1001
    },
    {
      "advanceWidth": 752,
      "codePoint": 8486,
      "height": 28,
      "leftSideBearing": 46,
      "width": -46,
      "xMax": 0,
      "xMin": 46,
      "yMax": 721,
      "yMin": 693
    },
    {
      "advanceWidth": 604,
      "codePoint": 8494,
      "height": -26,
      "leftSideBearing": 44,
      "width": -61,
      "xMax": -17,
      "xMin": 44,
      "yMax": 535,
      "yMin": 561
    },
    {
      "advanceWidth": 523,
      "codePoint": 8706,
      "height": 240,
      "leftSideBearing": 35,
      "width": -47,
      "xMax": -12,
      "xMin": 35,
      "yMax": 721,
      "yMin": 481
    },
    {
      "advanceWidth": 678,
      "codePoint": 8710,
      "height": 45,
      "leftSideBearing": 11,
      "width": -11,
      "xMax": 0,
      "xMin": 11,
      "yMax": 712,
      "yMin": 667
    },
    {
      "advanceWidth": 726,
      "codePoint": 8719,
      "height": 126,
      "leftSideBearing": 66,
      "width": -280,
      "xMax": -214,
      "xMin": 66,
      "yMax": 786,
      "yMin": 660
    },
    {
      "advanceWidth": 626,
      "codePoint": 8721,
      "height": 185,
      "leftSideBearing": 25,
      "width": -239,
      "xMax": -214,
      "xMin": 25,
      "yMax": 786,
      "yMin": 601
    },
    {
      "advanceWidth": 666,
      "codePoint": 8722,
      "height": -306,
      "leftSideBearing": 103,
      "width": 161,
      "xMax": 264,
      "xMin": 103,
      "yMax": 342,
      "yMin": 648
    },
    {
      "advanceWidth": 167,
      "codePoint": 8725,
      "height": 308,
      "leftSideBearing": -166,
      "width": 134,
      "xMax": -32,
      "xMin": -166,
      "yMax": 740,
      "yMin": 432
    },
    {
      "advanceWidth": 278,
      "codePoint": 8729,
      "height": 118,
      "leftSideBearing": 111,
      "width": 126,
      "xMax": 237,
      "xMin": 111,
      "yMax": 369,
      "yMin": 251
    },
    {
      "advanceWidth": 515,
      "codePoint": 8730,
      "height": 260,
      "leftSideBearing": -10,
      "width": -204,
      "xMax": -214,
      "xMin": -10,
      "yMax": 786,
      "yMin": 526
    },
    {
      "advanceWidth": 778,
      "codePoint": 8734,
      "height": -320,
      "leftSideBearing": 61,
      "width": 28,
      "xMax": 89,
      "xMin": 61,
      "yMax": 434,
      "yMin": 754
    },
    {
      "advanceWidth": 574,
      "codePoint": 8747,
      "height": 344,
      "leftSideBearing": 96,
      "width": -309,
      "xMax": -213,
      "xMin": 96,
      "yMax": 786,
      "yMin": 442
    },
    {
      "advanceWidth": 666,
      "codePoint": 8776,
      "height": -159,
      "leftSideBearing": 67,
      "width": 15,
      "xMax": 82,
      "xMin": 67,
      "yMax": 440,
      "yMin": 599
    },
    {
      "advanceWidth": 666,
      "codePoint": 8800,
      "height": -4,
      "leftSideBearing": 40,
      "width": -81,
      "xMax": -41,
      "xMin": 40,
      "yMax": 548,
      "yMin": 552
    },
    {
      "advanceWidth": 666,
      "codePoint": 8804,
      "height": -11,
      "leftSideBearing": 77,
      "width": -69,
      "xMax": 8,
      "xMin": 77,
      "yMax": 578,
      "yMin": 589
    },
    {
      "advanceWidth": 666,
      "codePoint": 8805,
      "height": -11,
      "leftSideBearing": 77,
      "width": -69,
      "xMax": 8,
      "xMin": 77,
      "yMax": 578,
      "yMin": 589
    },
    {
      "advanceWidth": 593,
      "codePoint": 9674,
      "height": 236,
      "leftSideBearing": 82,
      "width": -117,
      "xMax": -35,
      "xMin": 82,
      "yMax": 747,
      "yMin": 511
    },
    {
      "advanceWidth": 240,
      "codePoint": 57558,
      "height": 243,
      "leftSideBearing": -70,
      "width": -170,
      "xMax": -240,
      "xMin": -70,
      "yMax": 474,
      "yMin": 231
    },
    {
      "advanceWidth": 240,
      "codePoint": 58112,
      "height": 639,
      "leftSideBearing": 53,
      "width": 707,
      "xMax": 760,
      "xMin": 53,
      "yMax": 904,
      "yMin": 265
    },
    {
      "advanceWidth": 240,
      "codePoint": 58113,
      "height": 519,
      "leftSideBearing": 133,
      "width": 627,
      "xMax": 760,
      "xMin": 133,
      "yMax": 904,
      "yMin": 385
    },
    {
      "advanceWidth": 240,
      "codePoint": 58114,
      "height": 540,
      "leftSideBearing": 34,
      "width": 726,
      "xMax": 760,
      "xMin": 34,
      "yMax": 904,
      "yMin": 364
    },
    {
      "advanceWidth": 240,
      "codePoint": 58115,
      "height": 520,
      "leftSideBearing": 54,
      "width": 706,
      "xMax": 760,
      "xMin": 54,
      "yMax": 904,
      "yMin": 384
    },
    {
      "advanceWidth": 240,
      "codePoint": 58116,
      "height": 494,
      "leftSideBearing": 32,
      "width": 738,
      "xMax": 770,
      "xMin": 32,
      "yMax": 878,
      "yMin": 384
    },
    {
      "advanceWidth": 240,
      "codePoint": 58117,
      "height": 519,
      "leftSideBearing": 44,
      "width": 734,
      "xMax": 778,
      "xMin": 44,
      "yMax": 898,
      "yMin": 379
    },
    {
      "advanceWidth": 240,
      "codePoint": 58118,
      "height": 497,
      "leftSideBearing": 60,
      "width": 728,
      "xMax": 788,
      "xMin": 60,
      "yMax": 854,
      "yMin": 357
    },
    {
      "advanceWidth": 240,
      "codePoint": 58119,
      "height": 531,
      "leftSideBearing": 56,
      "width": 712,
      "xMax": 768,
      "xMin": 56,
      "yMax": 906,
      "yMin": 375
    },
    {
      "advanceWidth": 240,
      "codePoint": 58120,
      "height": 628,
      "leftSideBearing": 103,
      "width": 644,
      "xMax": 747,
      "xMin": 103,
      "yMax": 944,
      "yMin": 316
    },
    {
      "advanceWidth": 240,
      "codePoint": 58121,
      "height": 455,
      "leftSideBearing": 29,
      "width": 731,
      "xMax": 760,
      "xMin": 29,
      "yMax": 904,
      "yMin": 449
    },
    {
      "advanceWidth": 240,
      "codePoint": 58122,
      "height": 621,
      "leftSideBearing": 146,
      "width": 632,
      "xMax": 778,
      "xMin": 146,
      "yMax": 898,
      "yMin": 277
    },
    {
      "advanceWidth": 250,
      "codePoint": 58123,
      "height": 456,
      "leftSideBearing": 55,
      "width": 463,
      "xMax": 518,
      "xMin": 55,
      "yMax": 708,
      "yMin": 252
    },
    {
      "advanceWidth": 250,
      "codePoint": 58124,
      "height": -245,
      "leftSideBearing": 3,
      "width": -238,
      "xMax": -235,
      "xMin": 3,
      "yMax": -45,
      "yMin": 200
    },
    {
      "advanceWidth": 250,
      "codePoint": 58125,
      "height": 462,
      "leftSideBearing": 100,
      "width": 464,
      "xMax": 564,
      "xMin": 100,
      "yMax": 759,
      "yMin": 297
    },
    {
      "advanceWidth": 512,
      "codePoint": 63743,
      "height": 206,
      "leftSideBearing": 0,
      "width": 0,
      "xMax": 0,
      "xMin": 0,
      "yMax": 718,
      "yMin": 512
    },
    {
      "advanceWidth": 556,
      "codePoint": 64257,
      "height": 172,
      "leftSideBearing": 56,
      "width": -56,
      "xMax": 0,
      "xMin": 56,
      "yMax": 768,
      "yMin": 596
    },
    {
      "advanceWidth": 556,
      "codePoint": 64258,
      "height": 181,
      "leftSideBearing": 56,
      "width": -56,
      "xMax": 0,
      "xMin": 56,
      "yMax": 768,
      "yMin": 587
    }
  ],
  "descent": -366,
  "familyName": "Avenir",
  "features": [{ "name": "kern", "type": "positioning" }],
  "fullName": "Avenir Medium Oblique",
  "id": "avenir-medium-oblique",
  "lineGap": 0,
  "postScriptName": "Avenir-MediumOblique",
  "subfamilyName": "Medium Oblique",
  "typographicFamilyName": "Avenir Medium",
  "typographicSubfamilyName": "Oblique",
  "unitsPerEm": 1000,
  "variable": false,
  "wwsFamilyName": null,
  "wwsSubFamilyName": null,
  "xHeight": 474,
  "xWidthAvg": 535
}
