{
  "ascent": 672,
  "capHeight": 655,
  "codePoints": [
    {
      "advanceWidth": 245,
      "codePoint": 32,
      "height": 0,
      "leftSideBearing": 0,
      "width": 0,
      "xMax": 0,
      "xMin": 0,
      "yMax": 0,
      "yMin": 0
    },
    {
      "advanceWidth": 323,
      "codePoint": 33,
      "height": 677,
      "leftSideBearing": 74,
      "width": 287,
      "xMax": 361,
      "xMin": 74,
      "yMax": 666,
      "yMin": -11
    },
    {
      "advanceWidth": 555,
      "codePoint": 34,
      "height": 325,
      "leftSideBearing": 166,
      "width": 358,
      "xMax": 524,
      "xMin": 166,
      "yMax": 648,
      "yMin": 323
    },
    {
      "advanceWidth": 668,
      "codePoint": 35,
      "height": 702,
      "leftSideBearing": 78,
      "width": 587,
      "xMax": 665,
      "xMin": 78,
      "yMax": 680,
      "yMin": -22
    },
    {
      "advanceWidth": 490,
      "codePoint": 36,
      "height": 789,
      "leftSideBearing": 27,
      "width": 490,
      "xMax": 517,
      "xMin": 27,
      "yMax": 674,
      "yMin": -115
    },
    {
      "advanceWidth": 927,
      "codePoint": 37,
      "height": 708,
      "leftSideBearing": 151,
      "width": 685,
      "xMax": 836,
      "xMin": 151,
      "yMax": 666,
      "yMin": -42
    },
    {
      "advanceWidth": 760,
      "codePoint": 38,
      "height": 681,
      "leftSideBearing": 43,
      "width": 699,
      "xMax": 742,
      "xMin": 43,
      "yMax": 670,
      "yMin": -11
    },
    {
      "advanceWidth": 281,
      "codePoint": 39,
      "height": 325,
      "leftSideBearing": 156,
      "width": 158,
      "xMax": 314,
      "xMin": 156,
      "yMax": 648,
      "yMin": 323
    },
    {
      "advanceWidth": 375,
      "codePoint": 40,
      "height": 919,
      "leftSideBearing": 59,
      "width": 407,
      "xMax": 466,
      "xMin": 59,
      "yMax": 669,
      "yMin": -250
    },
    {
      "advanceWidth": 375,
      "codePoint": 41,
      "height": 919,
      "leftSideBearing": -65,
      "width": 407,
      "xMax": 342,
      "xMin": -65,
      "yMax": 668,
      "yMin": -251
    },
    {
      "advanceWidth": 490,
      "codePoint": 42,
      "height": 417,
      "leftSideBearing": 108,
      "width": 412,
      "xMax": 520,
      "xMin": 108,
      "yMax": 669,
      "yMin": 252
    },
    {
      "advanceWidth": 667,
      "codePoint": 43,
      "height": 538,
      "leftSideBearing": 102,
      "width": 538,
      "xMax": 640,
      "xMin": 102,
      "yMax": 597,
      "yMin": 59
    },
    {
      "advanceWidth": 271,
      "codePoint": 44,
      "height": 320,
      "leftSideBearing": 34,
      "width": 204,
      "xMax": 238,
      "xMin": 34,
      "yMax": 146,
      "yMin": -174
    },
    {
      "advanceWidth": 427,
      "codePoint": 45,
      "height": 110,
      "leftSideBearing": 89,
      "width": 241,
      "xMax": 330,
      "xMin": 89,
      "yMax": 295,
      "yMin": 185
    },
    {
      "advanceWidth": 271,
      "codePoint": 46,
      "height": 155,
      "leftSideBearing": 43,
      "width": 155,
      "xMax": 198,
      "xMin": 43,
      "yMax": 144,
      "yMin": -11
    },
    {
      "advanceWidth": 281,
      "codePoint": 47,
      "height": 714,
      "leftSideBearing": -76,
      "width": 433,
      "xMax": 357,
      "xMin": -76,
      "yMax": 665,
      "yMin": -49
    },
    {
      "advanceWidth": 490,
      "codePoint": 48,
      "height": 659,
      "leftSideBearing": 55,
      "width": 450,
      "xMax": 505,
      "xMin": 55,
      "yMax": 648,
      "yMin": -11
    },
    {
      "advanceWidth": 490,
      "codePoint": 49,
      "height": 648,
      "leftSideBearing": 37,
      "width": 389,
      "xMax": 426,
      "xMin": 37,
      "yMax": 648,
      "yMin": 0
    },
    {
      "advanceWidth": 490,
      "codePoint": 50,
      "height": 648,
      "leftSideBearing": 38,
      "width": 482,
      "xMax": 520,
      "xMin": 38,
      "yMax": 648,
      "yMin": 0
    },
    {
      "advanceWidth": 490,
      "codePoint": 51,
      "height": 659,
      "leftSideBearing": 38,
      "width": 471,
      "xMax": 509,
      "xMin": 38,
      "yMax": 648,
      "yMin": -11
    },
    {
      "advanceWidth": 490,
      "codePoint": 52,
      "height": 648,
      "leftSideBearing": 37,
      "width": 457,
      "xMax": 494,
      "xMin": 37,
      "yMax": 648,
      "yMin": 0
    },
    {
      "advanceWidth": 490,
      "codePoint": 53,
      "height": 686,
      "leftSideBearing": 37,
      "width": 497,
      "xMax": 534,
      "xMin": 37,
      "yMax": 675,
      "yMin": -11
    },
    {
      "advanceWidth": 490,
      "codePoint": 54,
      "height": 659,
      "leftSideBearing": 43,
      "width": 450,
      "xMax": 493,
      "xMin": 43,
      "yMax": 648,
      "yMin": -11
    },
    {
      "advanceWidth": 490,
      "codePoint": 55,
      "height": 645,
      "leftSideBearing": 96,
      "width": 454,
      "xMax": 550,
      "xMin": 96,
      "yMax": 634,
      "yMin": -11
    },
    {
      "advanceWidth": 490,
      "codePoint": 56,
      "height": 659,
      "leftSideBearing": 34,
      "width": 484,
      "xMax": 518,
      "xMin": 34,
      "yMax": 648,
      "yMin": -11
    },
    {
      "advanceWidth": 490,
      "codePoint": 57,
      "height": 659,
      "leftSideBearing": 60,
      "width": 447,
      "xMax": 507,
      "xMin": 60,
      "yMax": 648,
      "yMin": -11
    },
    {
      "advanceWidth": 271,
      "codePoint": 58,
      "height": 406,
      "leftSideBearing": 43,
      "width": 212,
      "xMax": 255,
      "xMin": 43,
      "yMax": 395,
      "yMin": -11
    },
    {
      "advanceWidth": 323,
      "codePoint": 59,
      "height": 568,
      "leftSideBearing": 18,
      "width": 262,
      "xMax": 280,
      "xMin": 18,
      "yMax": 379,
      "yMin": -189
    },
    {
      "advanceWidth": 667,
      "codePoint": 60,
      "height": 532,
      "leftSideBearing": 64,
      "width": 539,
      "xMax": 603,
      "xMin": 64,
      "yMax": 594,
      "yMin": 62
    },
    {
      "advanceWidth": 667,
      "codePoint": 61,
      "height": 322,
      "leftSideBearing": 102,
      "width": 538,
      "xMax": 640,
      "xMin": 102,
      "yMax": 490,
      "yMin": 168
    },
    {
      "advanceWidth": 667,
      "codePoint": 62,
      "height": 532,
      "leftSideBearing": 64,
      "width": 539,
      "xMax": 603,
      "xMin": 64,
      "yMax": 594,
      "yMin": 62
    },
    {
      "advanceWidth": 438,
      "codePoint": 63,
      "height": 676,
      "leftSideBearing": 92,
      "width": 368,
      "xMax": 460,
      "xMin": 92,
      "yMax": 666,
      "yMin": -10
    },
    {
      "advanceWidth": 832,
      "codePoint": 64,
      "height": 861,
      "leftSideBearing": 34,
      "width": 833,
      "xMax": 867,
      "xMin": 34,
      "yMax": 653,
      "yMin": -208
    },
    {
      "advanceWidth": 729,
      "codePoint": 65,
      "height": 663,
      "leftSideBearing": -15,
      "width": 692,
      "xMax": 677,
      "xMin": -15,
      "yMax": 663,
      "yMin": 0
    },
    {
      "advanceWidth": 760,
      "codePoint": 66,
      "height": 655,
      "leftSideBearing": 30,
      "width": 702,
      "xMax": 732,
      "xMin": 30,
      "yMax": 655,
      "yMin": 0
    },
    {
      "advanceWidth": 760,
      "codePoint": 67,
      "height": 681,
      "leftSideBearing": 104,
      "width": 660,
      "xMax": 764,
      "xMin": 104,
      "yMax": 670,
      "yMin": -11
    },
    {
      "advanceWidth": 813,
      "codePoint": 68,
      "height": 655,
      "leftSideBearing": 45,
      "width": 744,
      "xMax": 789,
      "xMin": 45,
      "yMax": 655,
      "yMin": 0
    },
    {
      "advanceWidth": 698,
      "codePoint": 69,
      "height": 655,
      "leftSideBearing": 19,
      "width": 703,
      "xMax": 722,
      "xMin": 19,
      "yMax": 655,
      "yMin": 0
    },
    {
      "advanceWidth": 646,
      "codePoint": 70,
      "height": 655,
      "leftSideBearing": 20,
      "width": 700,
      "xMax": 720,
      "xMin": 20,
      "yMax": 655,
      "yMin": 0
    },
    {
      "advanceWidth": 813,
      "codePoint": 71,
      "height": 681,
      "leftSideBearing": 96,
      "width": 700,
      "xMax": 796,
      "xMin": 96,
      "yMax": 670,
      "yMin": -11
    },
    {
      "advanceWidth": 813,
      "codePoint": 72,
      "height": 655,
      "leftSideBearing": 22,
      "width": 848,
      "xMax": 870,
      "xMin": 22,
      "yMax": 655,
      "yMin": 0
    },
    {
      "advanceWidth": 375,
      "codePoint": 73,
      "height": 655,
      "leftSideBearing": 15,
      "width": 423,
      "xMax": 438,
      "xMin": 15,
      "yMax": 655,
      "yMin": 0
    },
    {
      "advanceWidth": 542,
      "codePoint": 74,
      "height": 767,
      "leftSideBearing": 19,
      "width": 575,
      "xMax": 594,
      "xMin": 19,
      "yMax": 655,
      "yMin": -112
    },
    {
      "advanceWidth": 760,
      "codePoint": 75,
      "height": 655,
      "leftSideBearing": 18,
      "width": 764,
      "xMax": 782,
      "xMin": 18,
      "yMax": 655,
      "yMin": 0
    },
    {
      "advanceWidth": 646,
      "codePoint": 76,
      "height": 655,
      "leftSideBearing": 22,
      "width": 603,
      "xMax": 625,
      "xMin": 22,
      "yMax": 655,
      "yMin": 0
    },
    {
      "advanceWidth": 969,
      "codePoint": 77,
      "height": 655,
      "leftSideBearing": 24,
      "width": 989,
      "xMax": 1013,
      "xMin": 24,
      "yMax": 655,
      "yMin": 0
    },
    {
      "advanceWidth": 760,
      "codePoint": 78,
      "height": 660,
      "leftSideBearing": 19,
      "width": 791,
      "xMax": 810,
      "xMin": 19,
      "yMax": 655,
      "yMin": -5
    },
    {
      "advanceWidth": 813,
      "codePoint": 79,
      "height": 681,
      "leftSideBearing": 104,
      "width": 689,
      "xMax": 793,
      "xMin": 104,
      "yMax": 670,
      "yMin": -11
    },
    {
      "advanceWidth": 698,
      "codePoint": 80,
      "height": 655,
      "leftSideBearing": 27,
      "width": 707,
      "xMax": 734,
      "xMin": 27,
      "yMax": 655,
      "yMin": 0
    },
    {
      "advanceWidth": 813,
      "codePoint": 81,
      "height": 877,
      "leftSideBearing": 105,
      "width": 689,
      "xMax": 794,
      "xMin": 105,
      "yMax": 670,
      "yMin": -207
    },
    {
      "advanceWidth": 760,
      "codePoint": 82,
      "height": 660,
      "leftSideBearing": 22,
      "width": 722,
      "xMax": 744,
      "xMin": 22,
      "yMax": 655,
      "yMin": -5
    },
    {
      "advanceWidth": 646,
      "codePoint": 83,
      "height": 681,
      "leftSideBearing": 71,
      "width": 571,
      "xMax": 642,
      "xMin": 71,
      "yMax": 670,
      "yMin": -11
    },
    {
      "advanceWidth": 698,
      "codePoint": 84,
      "height": 655,
      "leftSideBearing": 91,
      "width": 677,
      "xMax": 768,
      "xMin": 91,
      "yMax": 655,
      "yMin": 0
    },
    {
      "advanceWidth": 813,
      "codePoint": 85,
      "height": 666,
      "leftSideBearing": 144,
      "width": 719,
      "xMax": 863,
      "xMin": 144,
      "yMax": 655,
      "yMin": -11
    },
    {
      "advanceWidth": 698,
      "codePoint": 86,
      "height": 669,
      "leftSideBearing": 128,
      "width": 646,
      "xMax": 774,
      "xMin": 128,
      "yMax": 655,
      "yMin": -14
    },
    {
      "advanceWidth": 969,
      "codePoint": 87,
      "height": 666,
      "leftSideBearing": 129,
      "width": 916,
      "xMax": 1045,
      "xMin": 129,
      "yMax": 655,
      "yMin": -11
    },
    {
      "advanceWidth": 760,
      "codePoint": 88,
      "height": 655,
      "leftSideBearing": 31,
      "width": 738,
      "xMax": 769,
      "xMin": 31,
      "yMax": 655,
      "yMin": 0
    },
    {
      "advanceWidth": 698,
      "codePoint": 89,
      "height": 655,
      "leftSideBearing": 121,
      "width": 634,
      "xMax": 755,
      "xMin": 121,
      "yMax": 655,
      "yMin": 0
    },
    {
      "advanceWidth": 646,
      "codePoint": 90,
      "height": 655,
      "leftSideBearing": 25,
      "width": 646,
      "xMax": 671,
      "xMin": 25,
      "yMax": 655,
      "yMin": 0
    },
    {
      "advanceWidth": 385,
      "codePoint": 91,
      "height": 893,
      "leftSideBearing": 33,
      "width": 454,
      "xMax": 487,
      "xMin": 33,
      "yMax": 654,
      "yMin": -239
    },
    {
      "advanceWidth": 281,
      "codePoint": 92,
      "height": 714,
      "leftSideBearing": -47,
      "width": 435,
      "xMax": 388,
      "xMin": -47,
      "yMax": 665,
      "yMin": -49
    },
    {
      "advanceWidth": 385,
      "codePoint": 93,
      "height": 893,
      "leftSideBearing": -67,
      "width": 454,
      "xMax": 387,
      "xMin": -67,
      "yMax": 654,
      "yMin": -239
    },
    {
      "advanceWidth": 570,
      "codePoint": 94,
      "height": 351,
      "leftSideBearing": 97,
      "width": 446,
      "xMax": 543,
      "xMin": 97,
      "yMax": 665,
      "yMin": 314
    },
    {
      "advanceWidth": 500,
      "codePoint": 95,
      "height": 50,
      "leftSideBearing": -6,
      "width": 512,
      "xMax": 506,
      "xMin": -6,
      "yMax": -75,
      "yMin": -125
    },
    {
      "advanceWidth": 333,
      "codePoint": 96,
      "height": 163,
      "leftSideBearing": 80,
      "width": 234,
      "xMax": 314,
      "xMin": 80,
      "yMax": 636,
      "yMin": 473
    },
    {
      "advanceWidth": 542,
      "codePoint": 97,
      "height": 406,
      "leftSideBearing": 25,
      "width": 503,
      "xMax": 528,
      "xMin": 25,
      "yMax": 395,
      "yMin": -11
    },
    {
      "advanceWidth": 594,
      "codePoint": 98,
      "height": 676,
      "leftSideBearing": 74,
      "width": 482,
      "xMax": 556,
      "xMin": 74,
      "yMax": 665,
      "yMin": -11
    },
    {
      "advanceWidth": 490,
      "codePoint": 99,
      "height": 406,
      "leftSideBearing": 40,
      "width": 432,
      "xMax": 472,
      "xMin": 40,
      "yMax": 395,
      "yMin": -11
    },
    {
      "advanceWidth": 594,
      "codePoint": 100,
      "height": 674,
      "leftSideBearing": 34,
      "width": 577,
      "xMax": 611,
      "xMin": 34,
      "yMax": 663,
      "yMin": -11
    },
    {
      "advanceWidth": 490,
      "codePoint": 101,
      "height": 406,
      "leftSideBearing": 34,
      "width": 421,
      "xMax": 455,
      "xMin": 34,
      "yMax": 395,
      "yMin": -11
    },
    {
      "advanceWidth": 375,
      "codePoint": 102,
      "height": 923,
      "leftSideBearing": -145,
      "width": 674,
      "xMax": 529,
      "xMin": -145,
      "yMax": 667,
      "yMin": -256
    },
    {
      "advanceWidth": 542,
      "codePoint": 103,
      "height": 665,
      "leftSideBearing": -34,
      "width": 577,
      "xMax": 543,
      "xMin": -34,
      "yMax": 409,
      "yMin": -256
    },
    {
      "advanceWidth": 594,
      "codePoint": 104,
      "height": 674,
      "leftSideBearing": 44,
      "width": 539,
      "xMax": 583,
      "xMin": 44,
      "yMax": 663,
      "yMin": -11
    },
    {
      "advanceWidth": 323,
      "codePoint": 105,
      "height": 637,
      "leftSideBearing": 56,
      "width": 248,
      "xMax": 304,
      "xMin": 56,
      "yMax": 626,
      "yMin": -11
    },
    {
      "advanceWidth": 323,
      "codePoint": 106,
      "height": 884,
      "leftSideBearing": -128,
      "width": 461,
      "xMax": 333,
      "xMin": -128,
      "yMax": 628,
      "yMin": -256
    },
    {
      "advanceWidth": 542,
      "codePoint": 107,
      "height": 674,
      "leftSideBearing": 43,
      "width": 483,
      "xMax": 526,
      "xMin": 43,
      "yMax": 665,
      "yMin": -9
    },
    {
      "advanceWidth": 323,
      "codePoint": 108,
      "height": 676,
      "leftSideBearing": 52,
      "width": 288,
      "xMax": 340,
      "xMin": 52,
      "yMax": 665,
      "yMin": -11
    },
    {
      "advanceWidth": 969,
      "codePoint": 109,
      "height": 406,
      "leftSideBearing": 54,
      "width": 907,
      "xMax": 961,
      "xMin": 54,
      "yMax": 395,
      "yMin": -11
    },
    {
      "advanceWidth": 594,
      "codePoint": 110,
      "height": 406,
      "leftSideBearing": 44,
      "width": 535,
      "xMax": 579,
      "xMin": 44,
      "yMax": 395,
      "yMin": -11
    },
    {
      "advanceWidth": 542,
      "codePoint": 111,
      "height": 406,
      "leftSideBearing": 34,
      "width": 474,
      "xMax": 508,
      "xMin": 34,
      "yMax": 395,
      "yMin": -11
    },
    {
      "advanceWidth": 594,
      "codePoint": 112,
      "height": 642,
      "leftSideBearing": -80,
      "width": 627,
      "xMax": 547,
      "xMin": -80,
      "yMax": 395,
      "yMin": -247
    },
    {
      "advanceWidth": 594,
      "codePoint": 113,
      "height": 642,
      "leftSideBearing": 40,
      "width": 521,
      "xMax": 561,
      "xMin": 40,
      "yMax": 395,
      "yMin": -247
    },
    {
      "advanceWidth": 479,
      "codePoint": 114,
      "height": 395,
      "leftSideBearing": 51,
      "width": 418,
      "xMax": 469,
      "xMin": 51,
      "yMax": 395,
      "yMin": 0
    },
    {
      "advanceWidth": 427,
      "codePoint": 115,
      "height": 406,
      "leftSideBearing": 22,
      "width": 386,
      "xMax": 408,
      "xMin": 22,
      "yMax": 395,
      "yMin": -11
    },
    {
      "advanceWidth": 375,
      "codePoint": 116,
      "height": 506,
      "leftSideBearing": 63,
      "width": 312,
      "xMax": 375,
      "xMin": 63,
      "yMax": 501,
      "yMin": -5
    },
    {
      "advanceWidth": 594,
      "codePoint": 117,
      "height": 404,
      "leftSideBearing": 59,
      "width": 517,
      "xMax": 576,
      "xMin": 59,
      "yMax": 393,
      "yMin": -11
    },
    {
      "advanceWidth": 542,
      "codePoint": 118,
      "height": 406,
      "leftSideBearing": 26,
      "width": 473,
      "xMax": 499,
      "xMin": 26,
      "yMax": 395,
      "yMin": -11
    },
    {
      "advanceWidth": 760,
      "codePoint": 119,
      "height": 406,
      "leftSideBearing": 25,
      "width": 696,
      "xMax": 721,
      "xMin": 25,
      "yMax": 395,
      "yMin": -11
    },
    {
      "advanceWidth": 542,
      "codePoint": 120,
      "height": 406,
      "leftSideBearing": 24,
      "width": 494,
      "xMax": 518,
      "xMin": 24,
      "yMax": 395,
      "yMin": -11
    },
    {
      "advanceWidth": 542,
      "codePoint": 121,
      "height": 651,
      "leftSideBearing": -48,
      "width": 573,
      "xMax": 525,
      "xMin": -48,
      "yMax": 395,
      "yMin": -256
    },
    {
      "advanceWidth": 490,
      "codePoint": 122,
      "height": 406,
      "leftSideBearing": 19,
      "width": 452,
      "xMax": 471,
      "xMin": 19,
      "yMax": 395,
      "yMin": -11
    },
    {
      "advanceWidth": 394,
      "codePoint": 123,
      "height": 879.0271548742576,
      "leftSideBearing": 98,
      "width": 270,
      "xMax": 368,
      "xMin": 98,
      "yMax": 677,
      "yMin": -202.02715487425755
    },
    {
      "advanceWidth": 566,
      "codePoint": 124,
      "height": 921,
      "leftSideBearing": 237,
      "width": 91,
      "xMax": 328,
      "xMin": 237,
      "yMax": 664,
      "yMin": -257
    },
    {
      "advanceWidth": 394,
      "codePoint": 125,
      "height": 879.0271548742576,
      "leftSideBearing": 91,
      "width": 270,
      "xMax": 361,
      "xMin": 91,
      "yMax": 678.0271548742576,
      "yMin": -201
    },
    {
      "advanceWidth": 667,
      "codePoint": 126,
      "height": 178,
      "leftSideBearing": 100,
      "width": 543,
      "xMax": 643,
      "xMin": 100,
      "yMax": 412,
      "yMin": 234
    },
    {
      "advanceWidth": 245,
      "codePoint": 160,
      "height": 0,
      "leftSideBearing": 0,
      "width": 0,
      "xMax": 0,
      "xMin": 0,
      "yMax": 0,
      "yMin": 0
    },
    {
      "advanceWidth": 323,
      "codePoint": 161,
      "height": 677,
      "leftSideBearing": 15,
      "width": 287,
      "xMax": 302,
      "xMin": 15,
      "yMax": 395,
      "yMin": -282
    },
    {
      "advanceWidth": 490,
      "codePoint": 162,
      "height": 776,
      "leftSideBearing": 39,
      "width": 432,
      "xMax": 471,
      "xMin": 39,
      "yMax": 595,
      "yMin": -181
    },
    {
      "advanceWidth": 490,
      "codePoint": 163,
      "height": 659,
      "leftSideBearing": 14,
      "width": 494,
      "xMax": 508,
      "xMin": 14,
      "yMax": 648,
      "yMin": -11
    },
    {
      "advanceWidth": 472,
      "codePoint": 164,
      "height": 445,
      "leftSideBearing": 9,
      "width": 452,
      "xMax": 461,
      "xMin": 9,
      "yMax": 577,
      "yMin": 132
    },
    {
      "advanceWidth": 698,
      "codePoint": 165,
      "height": 655,
      "leftSideBearing": 82,
      "width": 673,
      "xMax": 755,
      "xMin": 82,
      "yMax": 655,
      "yMin": 0
    },
    {
      "advanceWidth": 566,
      "codePoint": 166,
      "height": 921,
      "leftSideBearing": 237,
      "width": 91,
      "xMax": 328,
      "xMin": 237,
      "yMax": 664,
      "yMin": -257
    },
    {
      "advanceWidth": 542,
      "codePoint": 167,
      "height": 875,
      "leftSideBearing": 29,
      "width": 485,
      "xMax": 514,
      "xMin": 29,
      "yMax": 645,
      "yMin": -230
    },
    {
      "advanceWidth": 333,
      "codePoint": 168,
      "height": 124,
      "leftSideBearing": 77,
      "width": 334,
      "xMax": 411,
      "xMin": 77,
      "yMax": 617,
      "yMin": 493
    },
    {
      "advanceWidth": 747,
      "codePoint": 169,
      "height": 692,
      "leftSideBearing": 60,
      "width": 692,
      "xMax": 752,
      "xMin": 60,
      "yMax": 677,
      "yMin": -15
    },
    {
      "advanceWidth": 354,
      "codePoint": 170,
      "height": 243,
      "leftSideBearing": 103,
      "width": 327,
      "xMax": 430,
      "xMin": 103,
      "yMax": 670,
      "yMin": 427
    },
    {
      "advanceWidth": 490,
      "codePoint": 171,
      "height": 353,
      "leftSideBearing": 12,
      "width": 462,
      "xMax": 474,
      "xMin": 12,
      "yMax": 384,
      "yMin": 31
    },
    {
      "advanceWidth": 667,
      "codePoint": 172,
      "height": 322,
      "leftSideBearing": 102,
      "width": 538,
      "xMax": 640,
      "xMin": 102,
      "yMax": 490,
      "yMin": 168
    },
    {
      "advanceWidth": 427,
      "codePoint": 173,
      "height": 110,
      "leftSideBearing": 89,
      "width": 241,
      "xMax": 330,
      "xMin": 89,
      "yMax": 295,
      "yMin": 185
    },
    {
      "advanceWidth": 747,
      "codePoint": 174,
      "height": 692,
      "leftSideBearing": 60,
      "width": 692,
      "xMax": 752,
      "xMin": 60,
      "yMax": 677,
      "yMin": -15
    },
    {
      "advanceWidth": 333,
      "codePoint": 175,
      "height": 93,
      "leftSideBearing": 86,
      "width": 295,
      "xMax": 381,
      "xMin": 86,
      "yMax": 604,
      "yMin": 511
    },
    {
      "advanceWidth": 400,
      "codePoint": 176,
      "height": 346,
      "leftSideBearing": 96,
      "width": 346,
      "xMax": 442,
      "xMin": 96,
      "yMax": 665,
      "yMin": 319
    },
    {
      "advanceWidth": 668,
      "codePoint": 177,
      "height": 708,
      "leftSideBearing": 103,
      "width": 538,
      "xMax": 641,
      "xMin": 103,
      "yMax": 708,
      "yMin": 0
    },
    {
      "advanceWidth": 323,
      "codePoint": 178,
      "height": 324,
      "leftSideBearing": 81,
      "width": 313,
      "xMax": 394,
      "xMin": 81,
      "yMax": 648,
      "yMin": 324
    },
    {
      "advanceWidth": 323,
      "codePoint": 179,
      "height": 329,
      "leftSideBearing": 80,
      "width": 306,
      "xMax": 386,
      "xMin": 80,
      "yMax": 648,
      "yMin": 319
    },
    {
      "advanceWidth": 333,
      "codePoint": 180,
      "height": 163,
      "leftSideBearing": 159,
      "width": 234,
      "xMax": 393,
      "xMin": 159,
      "yMax": 636,
      "yMin": 473
    },
    {
      "advanceWidth": 576,
      "codePoint": 181,
      "height": 602,
      "leftSideBearing": -47,
      "width": 596,
      "xMax": 549,
      "xMin": -47,
      "yMax": 386,
      "yMin": -216
    },
    {
      "advanceWidth": 542,
      "codePoint": 182,
      "height": 902,
      "leftSideBearing": 67,
      "width": 549,
      "xMax": 616,
      "xMin": 67,
      "yMax": 655,
      "yMin": -247
    },
    {
      "advanceWidth": 271,
      "codePoint": 183,
      "height": 157,
      "leftSideBearing": 88,
      "width": 157,
      "xMax": 245,
      "xMin": 88,
      "yMax": 399,
      "yMin": 242
    },
    {
      "advanceWidth": 333,
      "codePoint": 184,
      "height": 197,
      "leftSideBearing": 25,
      "width": 166,
      "xMax": 191,
      "xMin": 25,
      "yMax": 7,
      "yMin": -190
    },
    {
      "advanceWidth": 323,
      "codePoint": 185,
      "height": 324,
      "leftSideBearing": 79,
      "width": 253,
      "xMax": 332,
      "xMin": 79,
      "yMax": 648,
      "yMin": 324
    },
    {
      "advanceWidth": 354,
      "codePoint": 186,
      "height": 243,
      "leftSideBearing": 108,
      "width": 308,
      "xMax": 416,
      "xMin": 108,
      "yMax": 670,
      "yMin": 427
    },
    {
      "advanceWidth": 490,
      "codePoint": 187,
      "height": 353,
      "leftSideBearing": 16,
      "width": 462,
      "xMax": 478,
      "xMin": 16,
      "yMax": 384,
      "yMin": 31
    },
    {
      "advanceWidth": 927,
      "codePoint": 188,
      "height": 682,
      "leftSideBearing": 173,
      "width": 662,
      "xMax": 835,
      "xMin": 173,
      "yMax": 648,
      "yMin": -34
    },
    {
      "advanceWidth": 927,
      "codePoint": 189,
      "height": 682,
      "leftSideBearing": 177,
      "width": 652,
      "xMax": 829,
      "xMin": 177,
      "yMax": 648,
      "yMin": -34
    },
    {
      "advanceWidth": 927,
      "codePoint": 190,
      "height": 682,
      "leftSideBearing": 174,
      "width": 667,
      "xMax": 841,
      "xMin": 174,
      "yMax": 648,
      "yMin": -34
    },
    {
      "advanceWidth": 438,
      "codePoint": 191,
      "height": 676,
      "leftSideBearing": 10,
      "width": 368,
      "xMax": 378,
      "xMin": 10,
      "yMax": 395,
      "yMin": -281
    },
    {
      "advanceWidth": 729,
      "codePoint": 192,
      "height": 876,
      "leftSideBearing": -15,
      "width": 692,
      "xMax": 677,
      "xMin": -15,
      "yMax": 876,
      "yMin": 0
    },
    {
      "advanceWidth": 729,
      "codePoint": 193,
      "height": 876,
      "leftSideBearing": -15,
      "width": 726,
      "xMax": 711,
      "xMin": -15,
      "yMax": 876,
      "yMin": 0
    },
    {
      "advanceWidth": 729,
      "codePoint": 194,
      "height": 883,
      "leftSideBearing": -15,
      "width": 692,
      "xMax": 677,
      "xMin": -15,
      "yMax": 883,
      "yMin": 0
    },
    {
      "advanceWidth": 729,
      "codePoint": 195,
      "height": 857,
      "leftSideBearing": -15,
      "width": 746,
      "xMax": 731,
      "xMin": -15,
      "yMax": 857,
      "yMin": 0
    },
    {
      "advanceWidth": 729,
      "codePoint": 196,
      "height": 857,
      "leftSideBearing": -15,
      "width": 744,
      "xMax": 729,
      "xMin": -15,
      "yMax": 857,
      "yMin": 0
    },
    {
      "advanceWidth": 729,
      "codePoint": 197,
      "height": 881,
      "leftSideBearing": -15,
      "width": 692,
      "xMax": 677,
      "xMin": -15,
      "yMax": 881,
      "yMin": 0
    },
    {
      "advanceWidth": 969,
      "codePoint": 198,
      "height": 655,
      "leftSideBearing": 15,
      "width": 973,
      "xMax": 988,
      "xMin": 15,
      "yMax": 655,
      "yMin": 0
    },
    {
      "advanceWidth": 760,
      "codePoint": 199,
      "height": 881,
      "leftSideBearing": 104,
      "width": 660,
      "xMax": 764,
      "xMin": 104,
      "yMax": 670,
      "yMin": -211
    },
    {
      "advanceWidth": 698,
      "codePoint": 200,
      "height": 876,
      "leftSideBearing": 19,
      "width": 703,
      "xMax": 722,
      "xMin": 19,
      "yMax": 876,
      "yMin": 0
    },
    {
      "advanceWidth": 698,
      "codePoint": 201,
      "height": 876,
      "leftSideBearing": 19,
      "width": 703,
      "xMax": 722,
      "xMin": 19,
      "yMax": 876,
      "yMin": 0
    },
    {
      "advanceWidth": 698,
      "codePoint": 202,
      "height": 883,
      "leftSideBearing": 19,
      "width": 703,
      "xMax": 722,
      "xMin": 19,
      "yMax": 883,
      "yMin": 0
    },
    {
      "advanceWidth": 698,
      "codePoint": 203,
      "height": 857,
      "leftSideBearing": 19,
      "width": 703,
      "xMax": 722,
      "xMin": 19,
      "yMax": 857,
      "yMin": 0
    },
    {
      "advanceWidth": 375,
      "codePoint": 204,
      "height": 876,
      "leftSideBearing": 15,
      "width": 423,
      "xMax": 438,
      "xMin": 15,
      "yMax": 876,
      "yMin": 0
    },
    {
      "advanceWidth": 375,
      "codePoint": 205,
      "height": 876,
      "leftSideBearing": 15,
      "width": 429,
      "xMax": 444,
      "xMin": 15,
      "yMax": 876,
      "yMin": 0
    },
    {
      "advanceWidth": 375,
      "codePoint": 206,
      "height": 883,
      "leftSideBearing": 15,
      "width": 435,
      "xMax": 450,
      "xMin": 15,
      "yMax": 883,
      "yMin": 0
    },
    {
      "advanceWidth": 375,
      "codePoint": 207,
      "height": 857,
      "leftSideBearing": 15,
      "width": 467,
      "xMax": 482,
      "xMin": 15,
      "yMax": 857,
      "yMin": 0
    },
    {
      "advanceWidth": 813,
      "codePoint": 208,
      "height": 655,
      "leftSideBearing": 45,
      "width": 743,
      "xMax": 788,
      "xMin": 45,
      "yMax": 655,
      "yMin": 0
    },
    {
      "advanceWidth": 760,
      "codePoint": 209,
      "height": 862,
      "leftSideBearing": 19,
      "width": 791,
      "xMax": 810,
      "xMin": 19,
      "yMax": 857,
      "yMin": -5
    },
    {
      "advanceWidth": 813,
      "codePoint": 210,
      "height": 887,
      "leftSideBearing": 104,
      "width": 689,
      "xMax": 793,
      "xMin": 104,
      "yMax": 876,
      "yMin": -11
    },
    {
      "advanceWidth": 813,
      "codePoint": 211,
      "height": 887,
      "leftSideBearing": 104,
      "width": 689,
      "xMax": 793,
      "xMin": 104,
      "yMax": 876,
      "yMin": -11
    },
    {
      "advanceWidth": 813,
      "codePoint": 212,
      "height": 894,
      "leftSideBearing": 104,
      "width": 689,
      "xMax": 793,
      "xMin": 104,
      "yMax": 883,
      "yMin": -11
    },
    {
      "advanceWidth": 813,
      "codePoint": 213,
      "height": 868,
      "leftSideBearing": 104,
      "width": 689,
      "xMax": 793,
      "xMin": 104,
      "yMax": 857,
      "yMin": -11
    },
    {
      "advanceWidth": 813,
      "codePoint": 214,
      "height": 868,
      "leftSideBearing": 104,
      "width": 689,
      "xMax": 793,
      "xMin": 104,
      "yMax": 857,
      "yMin": -11
    },
    {
      "advanceWidth": 667,
      "codePoint": 215,
      "height": 503,
      "leftSideBearing": 120,
      "width": 504,
      "xMax": 624,
      "xMin": 120,
      "yMax": 579,
      "yMin": 76
    },
    {
      "advanceWidth": 813,
      "codePoint": 216,
      "height": 683,
      "leftSideBearing": 98,
      "width": 700,
      "xMax": 798,
      "xMin": 98,
      "yMax": 670,
      "yMin": -13
    },
    {
      "advanceWidth": 813,
      "codePoint": 217,
      "height": 887,
      "leftSideBearing": 144,
      "width": 719,
      "xMax": 863,
      "xMin": 144,
      "yMax": 876,
      "yMin": -11
    },
    {
      "advanceWidth": 813,
      "codePoint": 218,
      "height": 887,
      "leftSideBearing": 144,
      "width": 719,
      "xMax": 863,
      "xMin": 144,
      "yMax": 876,
      "yMin": -11
    },
    {
      "advanceWidth": 813,
      "codePoint": 219,
      "height": 894,
      "leftSideBearing": 144,
      "width": 719,
      "xMax": 863,
      "xMin": 144,
      "yMax": 883,
      "yMin": -11
    },
    {
      "advanceWidth": 813,
      "codePoint": 220,
      "height": 868,
      "leftSideBearing": 144,
      "width": 719,
      "xMax": 863,
      "xMin": 144,
      "yMax": 857,
      "yMin": -11
    },
    {
      "advanceWidth": 698,
      "codePoint": 221,
      "height": 876,
      "leftSideBearing": 121,
      "width": 634,
      "xMax": 755,
      "xMin": 121,
      "yMax": 876,
      "yMin": 0
    },
    {
      "advanceWidth": 698,
      "codePoint": 222,
      "height": 655,
      "leftSideBearing": 27,
      "width": 679,
      "xMax": 706,
      "xMin": 27,
      "yMax": 655,
      "yMin": 0
    },
    {
      "advanceWidth": 594,
      "codePoint": 223,
      "height": 923,
      "leftSideBearing": -144,
      "width": 755,
      "xMax": 611,
      "xMin": -144,
      "yMax": 671,
      "yMin": -252
    },
    {
      "advanceWidth": 542,
      "codePoint": 224,
      "height": 647,
      "leftSideBearing": 25,
      "width": 503,
      "xMax": 528,
      "xMin": 25,
      "yMax": 636,
      "yMin": -11
    },
    {
      "advanceWidth": 542,
      "codePoint": 225,
      "height": 647,
      "leftSideBearing": 25,
      "width": 503,
      "xMax": 528,
      "xMin": 25,
      "yMax": 636,
      "yMin": -11
    },
    {
      "advanceWidth": 542,
      "codePoint": 226,
      "height": 654,
      "leftSideBearing": 25,
      "width": 503,
      "xMax": 528,
      "xMin": 25,
      "yMax": 643,
      "yMin": -11
    },
    {
      "advanceWidth": 542,
      "codePoint": 227,
      "height": 628,
      "leftSideBearing": 25,
      "width": 503,
      "xMax": 528,
      "xMin": 25,
      "yMax": 617,
      "yMin": -11
    },
    {
      "advanceWidth": 542,
      "codePoint": 228,
      "height": 628,
      "leftSideBearing": 25,
      "width": 503,
      "xMax": 528,
      "xMin": 25,
      "yMax": 617,
      "yMin": -11
    },
    {
      "advanceWidth": 542,
      "codePoint": 229,
      "height": 652,
      "leftSideBearing": 25,
      "width": 503,
      "xMax": 528,
      "xMin": 25,
      "yMax": 641,
      "yMin": -11
    },
    {
      "advanceWidth": 813,
      "codePoint": 230,
      "height": 406,
      "leftSideBearing": 90,
      "width": 692,
      "xMax": 782,
      "xMin": 90,
      "yMax": 395,
      "yMin": -11
    },
    {
      "advanceWidth": 490,
      "codePoint": 231,
      "height": 606,
      "leftSideBearing": 40,
      "width": 432,
      "xMax": 472,
      "xMin": 40,
      "yMax": 395,
      "yMin": -211
    },
    {
      "advanceWidth": 490,
      "codePoint": 232,
      "height": 647,
      "leftSideBearing": 34,
      "width": 421,
      "xMax": 455,
      "xMin": 34,
      "yMax": 636,
      "yMin": -11
    },
    {
      "advanceWidth": 490,
      "codePoint": 233,
      "height": 647,
      "leftSideBearing": 34,
      "width": 438,
      "xMax": 472,
      "xMin": 34,
      "yMax": 636,
      "yMin": -11
    },
    {
      "advanceWidth": 490,
      "codePoint": 234,
      "height": 654,
      "leftSideBearing": 34,
      "width": 421,
      "xMax": 455,
      "xMin": 34,
      "yMax": 643,
      "yMin": -11
    },
    {
      "advanceWidth": 490,
      "codePoint": 235,
      "height": 628,
      "leftSideBearing": 34,
      "width": 456,
      "xMax": 490,
      "xMin": 34,
      "yMax": 617,
      "yMin": -11
    },
    {
      "advanceWidth": 323,
      "codePoint": 236,
      "height": 647,
      "leftSideBearing": 56,
      "width": 253,
      "xMax": 309,
      "xMin": 56,
      "yMax": 636,
      "yMin": -11
    },
    {
      "advanceWidth": 323,
      "codePoint": 237,
      "height": 647,
      "leftSideBearing": 56,
      "width": 332,
      "xMax": 388,
      "xMin": 56,
      "yMax": 636,
      "yMin": -11
    },
    {
      "advanceWidth": 323,
      "codePoint": 238,
      "height": 654,
      "leftSideBearing": 20,
      "width": 324,
      "xMax": 344,
      "xMin": 20,
      "yMax": 643,
      "yMin": -11
    },
    {
      "advanceWidth": 323,
      "codePoint": 239,
      "height": 628,
      "leftSideBearing": 56,
      "width": 350,
      "xMax": 406,
      "xMin": 56,
      "yMax": 617,
      "yMin": -11
    },
    {
      "advanceWidth": 500,
      "codePoint": 240,
      "height": 669,
      "leftSideBearing": 13,
      "width": 488,
      "xMax": 501,
      "xMin": 13,
      "yMax": 658,
      "yMin": -11
    },
    {
      "advanceWidth": 594,
      "codePoint": 241,
      "height": 628,
      "leftSideBearing": 44,
      "width": 535,
      "xMax": 579,
      "xMin": 44,
      "yMax": 617,
      "yMin": -11
    },
    {
      "advanceWidth": 542,
      "codePoint": 242,
      "height": 647,
      "leftSideBearing": 34,
      "width": 474,
      "xMax": 508,
      "xMin": 34,
      "yMax": 636,
      "yMin": -11
    },
    {
      "advanceWidth": 542,
      "codePoint": 243,
      "height": 647,
      "leftSideBearing": 34,
      "width": 474,
      "xMax": 508,
      "xMin": 34,
      "yMax": 636,
      "yMin": -11
    },
    {
      "advanceWidth": 542,
      "codePoint": 244,
      "height": 654,
      "leftSideBearing": 34,
      "width": 474,
      "xMax": 508,
      "xMin": 34,
      "yMax": 643,
      "yMin": -11
    },
    {
      "advanceWidth": 542,
      "codePoint": 245,
      "height": 628,
      "leftSideBearing": 34,
      "width": 494,
      "xMax": 528,
      "xMin": 34,
      "yMax": 617,
      "yMin": -11
    },
    {
      "advanceWidth": 542,
      "codePoint": 246,
      "height": 628,
      "leftSideBearing": 34,
      "width": 482,
      "xMax": 516,
      "xMin": 34,
      "yMax": 617,
      "yMin": -11
    },
    {
      "advanceWidth": 668,
      "codePoint": 247,
      "height": 514,
      "leftSideBearing": 102,
      "width": 538,
      "xMax": 640,
      "xMin": 102,
      "yMax": 584,
      "yMin": 70
    },
    {
      "advanceWidth": 542,
      "codePoint": 248,
      "height": 451,
      "leftSideBearing": 34,
      "width": 474,
      "xMax": 508,
      "xMin": 34,
      "yMax": 425,
      "yMin": -26
    },
    {
      "advanceWidth": 594,
      "codePoint": 249,
      "height": 647,
      "leftSideBearing": 59,
      "width": 517,
      "xMax": 576,
      "xMin": 59,
      "yMax": 636,
      "yMin": -11
    },
    {
      "advanceWidth": 594,
      "codePoint": 250,
      "height": 647,
      "leftSideBearing": 59,
      "width": 517,
      "xMax": 576,
      "xMin": 59,
      "yMax": 636,
      "yMin": -11
    },
    {
      "advanceWidth": 594,
      "codePoint": 251,
      "height": 654,
      "leftSideBearing": 59,
      "width": 517,
      "xMax": 576,
      "xMin": 59,
      "yMax": 643,
      "yMin": -11
    },
    {
      "advanceWidth": 594,
      "codePoint": 252,
      "height": 628,
      "leftSideBearing": 59,
      "width": 517,
      "xMax": 576,
      "xMin": 59,
      "yMax": 617,
      "yMin": -11
    },
    {
      "advanceWidth": 542,
      "codePoint": 253,
      "height": 892,
      "leftSideBearing": -48,
      "width": 573,
      "xMax": 525,
      "xMin": -48,
      "yMax": 636,
      "yMin": -256
    },
    {
      "advanceWidth": 594,
      "codePoint": 254,
      "height": 912,
      "leftSideBearing": -80,
      "width": 627,
      "xMax": 547,
      "xMin": -80,
      "yMax": 665,
      "yMin": -247
    },
    {
      "advanceWidth": 542,
      "codePoint": 255,
      "height": 873,
      "leftSideBearing": -48,
      "width": 573,
      "xMax": 525,
      "xMin": -48,
      "yMax": 617,
      "yMin": -256
    },
    {
      "advanceWidth": 323,
      "codePoint": 305,
      "height": 404,
      "leftSideBearing": 56,
      "width": 248,
      "xMax": 304,
      "xMin": 56,
      "yMax": 393,
      "yMin": -11
    },
    {
      "advanceWidth": 646,
      "codePoint": 321,
      "height": 655,
      "leftSideBearing": 22,
      "width": 603,
      "xMax": 625,
      "xMin": 22,
      "yMax": 655,
      "yMin": 0
    },
    {
      "advanceWidth": 323,
      "codePoint": 322,
      "height": 676,
      "leftSideBearing": 18,
      "width": 353,
      "xMax": 371,
      "xMin": 18,
      "yMax": 665,
      "yMin": -11
    },
    {
      "advanceWidth": 969,
      "codePoint": 338,
      "height": 663,
      "leftSideBearing": 43,
      "width": 952,
      "xMax": 995,
      "xMin": 43,
      "yMax": 660,
      "yMin": -3
    },
    {
      "advanceWidth": 813,
      "codePoint": 339,
      "height": 406,
      "leftSideBearing": 42,
      "width": 733,
      "xMax": 775,
      "xMin": 42,
      "yMax": 395,
      "yMin": -11
    },
    {
      "advanceWidth": 646,
      "codePoint": 352,
      "height": 894,
      "leftSideBearing": 71,
      "width": 584,
      "xMax": 655,
      "xMin": 71,
      "yMax": 883,
      "yMin": -11
    },
    {
      "advanceWidth": 427,
      "codePoint": 353,
      "height": 654,
      "leftSideBearing": 22,
      "width": 483,
      "xMax": 505,
      "xMin": 22,
      "yMax": 643,
      "yMin": -11
    },
    {
      "advanceWidth": 698,
      "codePoint": 376,
      "height": 857,
      "leftSideBearing": 121,
      "width": 634,
      "xMax": 755,
      "xMin": 121,
      "yMax": 857,
      "yMin": 0
    },
    {
      "advanceWidth": 646,
      "codePoint": 381,
      "height": 883,
      "leftSideBearing": 25,
      "width": 646,
      "xMax": 671,
      "xMin": 25,
      "yMax": 883,
      "yMin": 0
    },
    {
      "advanceWidth": 490,
      "codePoint": 382,
      "height": 654,
      "leftSideBearing": 19,
      "width": 518,
      "xMax": 537,
      "xMin": 19,
      "yMax": 643,
      "yMin": -11
    },
    {
      "advanceWidth": 677,
      "codePoint": 402,
      "height": 923,
      "leftSideBearing": 2,
      "width": 673,
      "xMax": 675,
      "xMin": 2,
      "yMax": 667,
      "yMin": -256
    },
    {
      "advanceWidth": 333,
      "codePoint": 710,
      "height": 176,
      "leftSideBearing": 25,
      "width": 324,
      "xMax": 349,
      "xMin": 25,
      "yMax": 643,
      "yMin": 467
    },
    {
      "advanceWidth": 333,
      "codePoint": 711,
      "height": 176,
      "leftSideBearing": 134,
      "width": 324,
      "xMax": 458,
      "xMin": 134,
      "yMax": 643,
      "yMin": 467
    },
    {
      "advanceWidth": 333,
      "codePoint": 713,
      "height": 93,
      "leftSideBearing": 86,
      "width": 295,
      "xMax": 381,
      "xMin": 86,
      "yMax": 604,
      "yMin": 511
    },
    {
      "advanceWidth": 333,
      "codePoint": 728,
      "height": 170,
      "leftSideBearing": 140,
      "width": 266,
      "xMax": 406,
      "xMin": 140,
      "yMax": 638,
      "yMin": 468
    },
    {
      "advanceWidth": 333,
      "codePoint": 729,
      "height": 124,
      "leftSideBearing": 182,
      "width": 124,
      "xMax": 306,
      "xMin": 182,
      "yMax": 617,
      "yMin": 493
    },
    {
      "advanceWidth": 333,
      "codePoint": 730,
      "height": 180,
      "leftSideBearing": 168,
      "width": 180,
      "xMax": 348,
      "xMin": 168,
      "yMax": 641,
      "yMin": 461
    },
    {
      "advanceWidth": 333,
      "codePoint": 731,
      "height": 207,
      "leftSideBearing": 152,
      "width": 221,
      "xMax": 373,
      "xMin": 152,
      "yMax": 7,
      "yMin": -200
    },
    {
      "advanceWidth": 333,
      "codePoint": 732,
      "height": 126,
      "leftSideBearing": 94,
      "width": 329,
      "xMax": 423,
      "xMin": 94,
      "yMax": 617,
      "yMin": 491
    },
    {
      "advanceWidth": 333,
      "codePoint": 733,
      "height": 163,
      "leftSideBearing": 82,
      "width": 362,
      "xMax": 444,
      "xMin": 82,
      "yMax": 636,
      "yMin": 473
    },
    {
      "advanceWidth": 655,
      "codePoint": 937,
      "height": 712,
      "leftSideBearing": 40,
      "width": 575,
      "xMax": 615,
      "xMin": 40,
      "yMax": 712,
      "yMin": 0
    },
    {
      "advanceWidth": 576,
      "codePoint": 956,
      "height": 602,
      "leftSideBearing": -47,
      "width": 596,
      "xMax": 549,
      "xMin": -47,
      "yMax": 386,
      "yMin": -216
    },
    {
      "advanceWidth": 400,
      "codePoint": 960,
      "height": 494,
      "leftSideBearing": 25,
      "width": 350,
      "xMax": 375,
      "xMin": 25,
      "yMax": 482,
      "yMin": -12
    },
    {
      "advanceWidth": 500,
      "codePoint": 8211,
      "height": 90,
      "leftSideBearing": 21,
      "width": 512,
      "xMax": 533,
      "xMin": 21,
      "yMax": 295,
      "yMin": 205
    },
    {
      "advanceWidth": 1000,
      "codePoint": 8212,
      "height": 90,
      "leftSideBearing": 21,
      "width": 1012,
      "xMax": 1033,
      "xMin": 21,
      "yMax": 295,
      "yMin": 205
    },
    {
      "advanceWidth": 271,
      "codePoint": 8216,
      "height": 293,
      "leftSideBearing": 103,
      "width": 198,
      "xMax": 301,
      "xMin": 103,
      "yMax": 665,
      "yMin": 372
    },
    {
      "advanceWidth": 271,
      "codePoint": 8217,
      "height": 293,
      "leftSideBearing": 97,
      "width": 198,
      "xMax": 295,
      "xMin": 97,
      "yMax": 667,
      "yMin": 374
    },
    {
      "advanceWidth": 271,
      "codePoint": 8218,
      "height": 293,
      "leftSideBearing": 39,
      "width": 198,
      "xMax": 237,
      "xMin": 39,
      "yMax": 152,
      "yMin": -141
    },
    {
      "advanceWidth": 490,
      "codePoint": 8220,
      "height": 293,
      "leftSideBearing": 98,
      "width": 426,
      "xMax": 524,
      "xMin": 98,
      "yMax": 665,
      "yMin": 372
    },
    {
      "advanceWidth": 490,
      "codePoint": 8221,
      "height": 293,
      "leftSideBearing": 104,
      "width": 426,
      "xMax": 530,
      "xMin": 104,
      "yMax": 667,
      "yMin": 374
    },
    {
      "advanceWidth": 490,
      "codePoint": 8222,
      "height": 293,
      "leftSideBearing": 34,
      "width": 426,
      "xMax": 460,
      "xMin": 34,
      "yMax": 152,
      "yMin": -141
    },
    {
      "advanceWidth": 490,
      "codePoint": 8224,
      "height": 922,
      "leftSideBearing": 73,
      "width": 449,
      "xMax": 522,
      "xMin": 73,
      "yMax": 669,
      "yMin": -253
    },
    {
      "advanceWidth": 490,
      "codePoint": 8225,
      "height": 922,
      "leftSideBearing": 25,
      "width": 461,
      "xMax": 486,
      "xMin": 25,
      "yMax": 669,
      "yMin": -253
    },
    {
      "advanceWidth": 354,
      "codePoint": 8226,
      "height": 278,
      "leftSideBearing": 69,
      "width": 279,
      "xMax": 348,
      "xMin": 69,
      "yMax": 469,
      "yMin": 191
    },
    {
      "advanceWidth": 1000,
      "codePoint": 8230,
      "height": 155,
      "leftSideBearing": 89,
      "width": 821,
      "xMax": 910,
      "xMin": 89,
      "yMax": 144,
      "yMin": -11
    },
    {
      "advanceWidth": 969,
      "codePoint": 8240,
      "height": 707,
      "leftSideBearing": 70,
      "width": 905,
      "xMax": 975,
      "xMin": 70,
      "yMax": 664,
      "yMin": -43
    },
    {
      "advanceWidth": 281,
      "codePoint": 8249,
      "height": 353,
      "leftSideBearing": 8,
      "width": 262,
      "xMax": 270,
      "xMin": 8,
      "yMax": 384,
      "yMin": 31
    },
    {
      "advanceWidth": 281,
      "codePoint": 8250,
      "height": 353,
      "leftSideBearing": 13,
      "width": 259,
      "xMax": 272,
      "xMin": 13,
      "yMax": 384,
      "yMin": 31
    },
    {
      "advanceWidth": 281,
      "codePoint": 8260,
      "height": 682,
      "leftSideBearing": -138,
      "width": 634,
      "xMax": 496,
      "xMin": -138,
      "yMax": 648,
      "yMin": -34
    },
    {
      "advanceWidth": 490,
      "codePoint": 8364,
      "height": 659,
      "leftSideBearing": 12,
      "width": 518,
      "xMax": 530,
      "xMin": 12,
      "yMax": 648,
      "yMin": -11
    },
    {
      "advanceWidth": 326,
      "codePoint": 8467,
      "height": 724,
      "leftSideBearing": 0,
      "width": 316,
      "xMax": 316,
      "xMin": 0,
      "yMax": 712,
      "yMin": -12
    },
    {
      "advanceWidth": 1000,
      "codePoint": 8482,
      "height": 394,
      "leftSideBearing": 29,
      "width": 1006,
      "xMax": 1035,
      "xMin": 29,
      "yMax": 655,
      "yMin": 261
    },
    {
      "advanceWidth": 655,
      "codePoint": 8486,
      "height": 712,
      "leftSideBearing": 40,
      "width": 575,
      "xMax": 615,
      "xMin": 40,
      "yMax": 712,
      "yMin": 0
    },
    {
      "advanceWidth": 569,
      "codePoint": 8494,
      "height": 518,
      "leftSideBearing": 41,
      "width": 488,
      "xMax": 529,
      "xMin": 41,
      "yMax": 506,
      "yMin": -12
    },
    {
      "advanceWidth": 446,
      "codePoint": 8706,
      "height": 739,
      "leftSideBearing": 18,
      "width": 403,
      "xMax": 421,
      "xMin": 18,
      "yMax": 727,
      "yMin": -12
    },
    {
      "advanceWidth": 485,
      "codePoint": 8710,
      "height": 712,
      "leftSideBearing": 25,
      "width": 439,
      "xMax": 464,
      "xMin": 25,
      "yMax": 712,
      "yMin": 0
    },
    {
      "advanceWidth": 584,
      "codePoint": 8719,
      "height": 831,
      "leftSideBearing": 30,
      "width": 524,
      "xMax": 554,
      "xMin": 30,
      "yMax": 700,
      "yMin": -131
    },
    {
      "advanceWidth": 408,
      "codePoint": 8721,
      "height": 831,
      "leftSideBearing": 13,
      "width": 387,
      "xMax": 400,
      "xMin": 13,
      "yMax": 700,
      "yMin": -131
    },
    {
      "advanceWidth": 667,
      "codePoint": 8722,
      "height": 90,
      "leftSideBearing": 102,
      "width": 538,
      "xMax": 640,
      "xMin": 102,
      "yMax": 373,
      "yMin": 283
    },
    {
      "advanceWidth": 281,
      "codePoint": 8725,
      "height": 682,
      "leftSideBearing": -138,
      "width": 634,
      "xMax": 496,
      "xMin": -138,
      "yMax": 648,
      "yMin": -34
    },
    {
      "advanceWidth": 271,
      "codePoint": 8729,
      "height": 157,
      "leftSideBearing": 88,
      "width": 157,
      "xMax": 245,
      "xMin": 88,
      "yMax": 399,
      "yMin": 242
    },
    {
      "advanceWidth": 262,
      "codePoint": 8730,
      "height": 740,
      "leftSideBearing": -20,
      "width": 271,
      "xMax": 251,
      "xMin": -20,
      "yMax": 728,
      "yMin": -12
    },
    {
      "advanceWidth": 568,
      "codePoint": 8734,
      "height": 255,
      "leftSideBearing": 37,
      "width": 491,
      "xMax": 528,
      "xMin": 37,
      "yMax": 407,
      "yMin": 152
    },
    {
      "advanceWidth": 251,
      "codePoint": 8747,
      "height": 958,
      "leftSideBearing": 10,
      "width": 231,
      "xMax": 241,
      "xMin": 10,
      "yMax": 747,
      "yMin": -211
    },
    {
      "advanceWidth": 667,
      "codePoint": 8776,
      "height": 393,
      "leftSideBearing": 8,
      "width": 651,
      "xMax": 659,
      "xMin": 8,
      "yMax": 520,
      "yMin": 127
    },
    {
      "advanceWidth": 668,
      "codePoint": 8800,
      "height": 550,
      "leftSideBearing": 52,
      "width": 563,
      "xMax": 615,
      "xMin": 52,
      "yMax": 594,
      "yMin": 44
    },
    {
      "advanceWidth": 667,
      "codePoint": 8804,
      "height": 629,
      "leftSideBearing": 52,
      "width": 563,
      "xMax": 615,
      "xMin": 52,
      "yMax": 629,
      "yMin": 0
    },
    {
      "advanceWidth": 667,
      "codePoint": 8805,
      "height": 627,
      "leftSideBearing": 52,
      "width": 563,
      "xMax": 615,
      "xMin": 52,
      "yMax": 627,
      "yMin": 0
    },
    {
      "advanceWidth": 287,
      "codePoint": 9674,
      "height": 724,
      "leftSideBearing": 0,
      "width": 287,
      "xMax": 287,
      "xMin": 0,
      "yMax": 712,
      "yMin": -12
    },
    {
      "advanceWidth": 646,
      "codePoint": 64257,
      "height": 922,
      "leftSideBearing": -146,
      "width": 775,
      "xMax": 629,
      "xMin": -146,
      "yMax": 666,
      "yMin": -256
    },
    {
      "advanceWidth": 646,
      "codePoint": 64258,
      "height": 922,
      "leftSideBearing": -146,
      "width": 808,
      "xMax": 662,
      "xMin": -146,
      "yMax": 666,
      "yMin": -256
    }
  ],
  "descent": -328,
  "familyName": "Bodoni MT Std",
  "features": [
    { "name": "aalt", "type": "substitution" },
    { "name": "frac", "type": "substitution" },
    { "name": "liga", "type": "substitution" },
    { "name": "ordn", "type": "substitution" },
    { "name": "sups", "type": "substitution" },
    { "name": "kern", "type": "positioning" }
  ],
  "fullName": "BodoniMTStd-BoldItalic",
  "id": "bodoni-mt-std-bold-italic",
  "lineGap": 200,
  "postScriptName": "BodoniMTStd-BoldItalic",
  "subfamilyName": "Bold Italic",
  "typographicFamilyName": "Bodoni MT Std",
  "typographicSubfamilyName": "Bold Italic",
  "unitsPerEm": 1000,
  "variable": false,
  "wwsFamilyName": null,
  "wwsSubFamilyName": null,
  "xHeight": 395,
  "xWidthAvg": 555
}
