{
  "ascent": 2014,
  "capHeight": 1554,
  "codePoints": [
    {
      "advanceWidth": 0,
      "codePoint": 0,
      "height": 0,
      "leftSideBearing": 0,
      "width": 0,
      "xMax": 0,
      "xMin": 0,
      "yMax": 0,
      "yMin": 0
    },
    {
      "advanceWidth": 0,
      "codePoint": 8,
      "height": 0,
      "leftSideBearing": 0,
      "width": 0,
      "xMax": 0,
      "xMin": 0,
      "yMax": 0,
      "yMin": 0
    },
    {
      "advanceWidth": 424,
      "codePoint": 9,
      "height": 0,
      "leftSideBearing": 0,
      "width": 0,
      "xMax": 0,
      "xMin": 0,
      "yMax": 0,
      "yMin": 0
    },
    {
      "advanceWidth": 1024,
      "codePoint": 13,
      "height": 0,
      "leftSideBearing": 0,
      "width": 0,
      "xMax": 0,
      "xMin": 0,
      "yMax": 0,
      "yMin": 0
    },
    {
      "advanceWidth": 0,
      "codePoint": 29,
      "height": 0,
      "leftSideBearing": 0,
      "width": 0,
      "xMax": 0,
      "xMin": 0,
      "yMax": 0,
      "yMin": 0
    },
    {
      "advanceWidth": 424,
      "codePoint": 32,
      "height": 0,
      "leftSideBearing": 0,
      "width": 0,
      "xMax": 0,
      "xMin": 0,
      "yMax": 0,
      "yMin": 0
    },
    {
      "advanceWidth": 571,
      "codePoint": 33,
      "height": 1135,
      "leftSideBearing": 162,
      "width": -176,
      "xMax": -14,
      "xMin": 162,
      "yMax": 1544,
      "yMin": 409
    },
    {
      "advanceWidth": 773,
      "codePoint": 34,
      "height": 863,
      "leftSideBearing": 93,
      "width": 846,
      "xMax": 939,
      "xMin": 93,
      "yMax": 1544,
      "yMin": 681
    },
    {
      "advanceWidth": 848,
      "codePoint": 35,
      "height": 701,
      "leftSideBearing": 4,
      "width": -4,
      "xMax": 0,
      "xMin": 4,
      "yMax": 1544,
      "yMin": 843
    },
    {
      "advanceWidth": 848,
      "codePoint": 36,
      "height": 916,
      "leftSideBearing": 64,
      "width": -216,
      "xMax": -152,
      "xMin": 64,
      "yMax": 1700,
      "yMin": 784
    },
    {
      "advanceWidth": 1187,
      "codePoint": 37,
      "height": 436,
      "leftSideBearing": 74,
      "width": -96,
      "xMax": -22,
      "xMin": 74,
      "yMax": 1549,
      "yMin": 1113
    },
    {
      "advanceWidth": 1051,
      "codePoint": 38,
      "height": 430,
      "leftSideBearing": 93,
      "width": -102,
      "xMax": -9,
      "xMin": 93,
      "yMax": 1436,
      "yMin": 1006
    },
    {
      "advanceWidth": 418,
      "codePoint": 39,
      "height": 1218,
      "leftSideBearing": 93,
      "width": 846,
      "xMax": 939,
      "xMin": 93,
      "yMax": 1544,
      "yMin": 326
    },
    {
      "advanceWidth": 601,
      "codePoint": 40,
      "height": 1214,
      "leftSideBearing": 116,
      "width": -564,
      "xMax": -448,
      "xMin": 116,
      "yMax": 1723,
      "yMin": 509
    },
    {
      "advanceWidth": 601,
      "codePoint": 41,
      "height": 1237,
      "leftSideBearing": 93,
      "width": -541,
      "xMax": -448,
      "xMin": 93,
      "yMax": 1723,
      "yMin": 486
    },
    {
      "advanceWidth": 848,
      "codePoint": 42,
      "height": 946,
      "leftSideBearing": 96,
      "width": 977,
      "xMax": 1073,
      "xMin": 96,
      "yMax": 1699,
      "yMin": 753
    },
    {
      "advanceWidth": 848,
      "codePoint": 43,
      "height": 361,
      "leftSideBearing": 63,
      "width": 368,
      "xMax": 431,
      "xMin": 63,
      "yMax": 1146,
      "yMin": 785
    },
    {
      "advanceWidth": 424,
      "codePoint": 44,
      "height": -116,
      "leftSideBearing": 29,
      "width": -405,
      "xMax": -376,
      "xMin": 29,
      "yMax": 216,
      "yMin": 332
    },
    {
      "advanceWidth": 364,
      "codePoint": 45,
      "height": 244,
      "leftSideBearing": 0,
      "width": 452,
      "xMax": 452,
      "xMin": 0,
      "yMax": 608,
      "yMin": 364
    },
    {
      "advanceWidth": 424,
      "codePoint": 46,
      "height": -104,
      "leftSideBearing": 89,
      "width": -103,
      "xMax": -14,
      "xMin": 89,
      "yMax": 232,
      "yMin": 336
    },
    {
      "advanceWidth": 923,
      "codePoint": 47,
      "height": 715,
      "leftSideBearing": -99,
      "width": -325,
      "xMax": -424,
      "xMin": -99,
      "yMax": 1699,
      "yMin": 984
    },
    {
      "advanceWidth": 848,
      "codePoint": 48,
      "height": 790,
      "leftSideBearing": 75,
      "width": -93,
      "xMax": -18,
      "xMin": 75,
      "yMax": 1563,
      "yMin": 773
    },
    {
      "advanceWidth": 848,
      "codePoint": 49,
      "height": 1009,
      "leftSideBearing": 183,
      "width": -183,
      "xMax": 0,
      "xMin": 183,
      "yMax": 1544,
      "yMin": 535
    },
    {
      "advanceWidth": 848,
      "codePoint": 50,
      "height": 792,
      "leftSideBearing": 77,
      "width": -77,
      "xMax": 0,
      "xMin": 77,
      "yMax": 1563,
      "yMin": 771
    },
    {
      "advanceWidth": 848,
      "codePoint": 51,
      "height": 799,
      "leftSideBearing": 84,
      "width": -102,
      "xMax": -18,
      "xMin": 84,
      "yMax": 1563,
      "yMin": 764
    },
    {
      "advanceWidth": 848,
      "codePoint": 52,
      "height": 769,
      "leftSideBearing": 60,
      "width": -60,
      "xMax": 0,
      "xMin": 60,
      "yMax": 1544,
      "yMin": 775
    },
    {
      "advanceWidth": 848,
      "codePoint": 53,
      "height": 784,
      "leftSideBearing": 88,
      "width": -106,
      "xMax": -18,
      "xMin": 88,
      "yMax": 1544,
      "yMin": 760
    },
    {
      "advanceWidth": 848,
      "codePoint": 54,
      "height": 788,
      "leftSideBearing": 92,
      "width": -110,
      "xMax": -18,
      "xMin": 92,
      "yMax": 1544,
      "yMin": 756
    },
    {
      "advanceWidth": 848,
      "codePoint": 55,
      "height": 755,
      "leftSideBearing": 99,
      "width": -99,
      "xMax": 0,
      "xMin": 99,
      "yMax": 1544,
      "yMin": 789
    },
    {
      "advanceWidth": 848,
      "codePoint": 56,
      "height": 805,
      "leftSideBearing": 91,
      "width": -109,
      "xMax": -18,
      "xMin": 91,
      "yMax": 1563,
      "yMin": 758
    },
    {
      "advanceWidth": 848,
      "codePoint": 57,
      "height": 807,
      "leftSideBearing": 94,
      "width": -94,
      "xMax": 0,
      "xMin": 94,
      "yMax": 1563,
      "yMin": 756
    },
    {
      "advanceWidth": 424,
      "codePoint": 58,
      "height": 714,
      "leftSideBearing": 89,
      "width": -103,
      "xMax": -14,
      "xMin": 89,
      "yMax": 1050,
      "yMin": 336
    },
    {
      "advanceWidth": 424,
      "codePoint": 59,
      "height": 708,
      "leftSideBearing": 29,
      "width": -405,
      "xMax": -376,
      "xMin": 29,
      "yMax": 1050,
      "yMin": 342
    },
    {
      "advanceWidth": 1158,
      "codePoint": 60,
      "height": 267,
      "leftSideBearing": 77,
      "width": 139,
      "xMax": 216,
      "xMin": 77,
      "yMax": 1348,
      "yMin": 1081
    },
    {
      "advanceWidth": 848,
      "codePoint": 61,
      "height": 210,
      "leftSideBearing": 63,
      "width": 521,
      "xMax": 584,
      "xMin": 63,
      "yMax": 995,
      "yMin": 785
    },
    {
      "advanceWidth": 1158,
      "codePoint": 62,
      "height": 266,
      "leftSideBearing": 78,
      "width": 137,
      "xMax": 215,
      "xMin": 78,
      "yMax": 1347,
      "yMin": 1081
    },
    {
      "advanceWidth": 761,
      "codePoint": 63,
      "height": 891,
      "leftSideBearing": 93,
      "width": -107,
      "xMax": -14,
      "xMin": 93,
      "yMax": 1560,
      "yMin": 669
    },
    {
      "advanceWidth": 1518,
      "codePoint": 64,
      "height": 109,
      "leftSideBearing": 62,
      "width": -81,
      "xMax": -19,
      "xMin": 62,
      "yMax": 1564,
      "yMin": 1455
    },
    {
      "advanceWidth": 835,
      "codePoint": 65,
      "height": 712,
      "leftSideBearing": 3,
      "width": -3,
      "xMax": 0,
      "xMin": 3,
      "yMax": 1544,
      "yMin": 832
    },
    {
      "advanceWidth": 843,
      "codePoint": 66,
      "height": 789,
      "leftSideBearing": 119,
      "width": -119,
      "xMax": 0,
      "xMin": 119,
      "yMax": 1544,
      "yMin": 755
    },
    {
      "advanceWidth": 781,
      "codePoint": 67,
      "height": 840,
      "leftSideBearing": 88,
      "width": -107,
      "xMax": -19,
      "xMin": 88,
      "yMax": 1565,
      "yMin": 725
    },
    {
      "advanceWidth": 953,
      "codePoint": 68,
      "height": 679,
      "leftSideBearing": 119,
      "width": -119,
      "xMax": 0,
      "xMin": 119,
      "yMax": 1544,
      "yMin": 865
    },
    {
      "advanceWidth": 744,
      "codePoint": 69,
      "height": 872,
      "leftSideBearing": 119,
      "width": -119,
      "xMax": 0,
      "xMin": 119,
      "yMax": 1544,
      "yMin": 672
    },
    {
      "advanceWidth": 716,
      "codePoint": 70,
      "height": 869,
      "leftSideBearing": 119,
      "width": -119,
      "xMax": 0,
      "xMin": 119,
      "yMax": 1544,
      "yMin": 675
    },
    {
      "advanceWidth": 955,
      "codePoint": 71,
      "height": 697,
      "leftSideBearing": 88,
      "width": -107,
      "xMax": -19,
      "xMin": 88,
      "yMax": 1564,
      "yMin": 867
    },
    {
      "advanceWidth": 959,
      "codePoint": 72,
      "height": 704,
      "leftSideBearing": 119,
      "width": -119,
      "xMax": 0,
      "xMin": 119,
      "yMax": 1544,
      "yMin": 840
    },
    {
      "advanceWidth": 446,
      "codePoint": 73,
      "height": 1217,
      "leftSideBearing": 119,
      "width": -119,
      "xMax": 0,
      "xMin": 119,
      "yMax": 1544,
      "yMin": 327
    },
    {
      "advanceWidth": 599,
      "codePoint": 74,
      "height": 1064,
      "leftSideBearing": -4,
      "width": -15,
      "xMax": -19,
      "xMin": -4,
      "yMax": 1544,
      "yMin": 480
    },
    {
      "advanceWidth": 862,
      "codePoint": 75,
      "height": 693,
      "leftSideBearing": 119,
      "width": -119,
      "xMax": 0,
      "xMin": 119,
      "yMax": 1544,
      "yMin": 851
    },
    {
      "advanceWidth": 678,
      "codePoint": 76,
      "height": 877,
      "leftSideBearing": 119,
      "width": -119,
      "xMax": 0,
      "xMin": 119,
      "yMax": 1544,
      "yMin": 667
    },
    {
      "advanceWidth": 1168,
      "codePoint": 77,
      "height": 429,
      "leftSideBearing": 65,
      "width": -65,
      "xMax": 0,
      "xMin": 65,
      "yMax": 1544,
      "yMin": 1115
    },
    {
      "advanceWidth": 958,
      "codePoint": 78,
      "height": 705,
      "leftSideBearing": 119,
      "width": -119,
      "xMax": 0,
      "xMin": 119,
      "yMax": 1544,
      "yMin": 839
    },
    {
      "advanceWidth": 979,
      "codePoint": 79,
      "height": 672,
      "leftSideBearing": 88,
      "width": -107,
      "xMax": -19,
      "xMin": 88,
      "yMax": 1564,
      "yMin": 892
    },
    {
      "advanceWidth": 812,
      "codePoint": 80,
      "height": 773,
      "leftSideBearing": 119,
      "width": -119,
      "xMax": 0,
      "xMin": 119,
      "yMax": 1544,
      "yMin": 771
    },
    {
      "advanceWidth": 979,
      "codePoint": 81,
      "height": 628,
      "leftSideBearing": 88,
      "width": -205,
      "xMax": -117,
      "xMin": 88,
      "yMax": 1564,
      "yMin": 936
    },
    {
      "advanceWidth": 863,
      "codePoint": 82,
      "height": 723,
      "leftSideBearing": 119,
      "width": -119,
      "xMax": 0,
      "xMin": 119,
      "yMax": 1544,
      "yMin": 821
    },
    {
      "advanceWidth": 764,
      "codePoint": 83,
      "height": 857,
      "leftSideBearing": 73,
      "width": -92,
      "xMax": -19,
      "xMin": 73,
      "yMax": 1565,
      "yMin": 708
    },
    {
      "advanceWidth": 669,
      "codePoint": 84,
      "height": 871,
      "leftSideBearing": -4,
      "width": 4,
      "xMax": 0,
      "xMin": -4,
      "yMax": 1544,
      "yMin": 673
    },
    {
      "advanceWidth": 948,
      "codePoint": 85,
      "height": 715,
      "leftSideBearing": 119,
      "width": -138,
      "xMax": -19,
      "xMin": 119,
      "yMax": 1544,
      "yMin": 829
    },
    {
      "advanceWidth": 757,
      "codePoint": 86,
      "height": 782,
      "leftSideBearing": -4,
      "width": 4,
      "xMax": 0,
      "xMin": -4,
      "yMax": 1544,
      "yMin": 762
    },
    {
      "advanceWidth": 1214,
      "codePoint": 87,
      "height": 333,
      "leftSideBearing": 3,
      "width": -3,
      "xMax": 0,
      "xMin": 3,
      "yMax": 1544,
      "yMin": 1211
    },
    {
      "advanceWidth": 769,
      "codePoint": 88,
      "height": 770,
      "leftSideBearing": -4,
      "width": 4,
      "xMax": 0,
      "xMin": -4,
      "yMax": 1544,
      "yMin": 774
    },
    {
      "advanceWidth": 791,
      "codePoint": 89,
      "height": 749,
      "leftSideBearing": -4,
      "width": 4,
      "xMax": 0,
      "xMin": -4,
      "yMax": 1544,
      "yMin": 795
    },
    {
      "advanceWidth": 773,
      "codePoint": 90,
      "height": 783,
      "leftSideBearing": 26,
      "width": -26,
      "xMax": 0,
      "xMin": 26,
      "yMax": 1544,
      "yMin": 761
    },
    {
      "advanceWidth": 723,
      "codePoint": 91,
      "height": 1054,
      "leftSideBearing": 154,
      "width": -578,
      "xMax": -424,
      "xMin": 154,
      "yMax": 1699,
      "yMin": 645
    },
    {
      "advanceWidth": 923,
      "codePoint": 92,
      "height": 668,
      "leftSideBearing": -52,
      "width": -372,
      "xMax": -424,
      "xMin": -52,
      "yMax": 1699,
      "yMin": 1031
    },
    {
      "advanceWidth": 723,
      "codePoint": 93,
      "height": 1131,
      "leftSideBearing": 77,
      "width": -501,
      "xMax": -424,
      "xMin": 77,
      "yMax": 1699,
      "yMin": 568
    },
    {
      "advanceWidth": 1158,
      "codePoint": 94,
      "height": 438,
      "leftSideBearing": 47,
      "width": 781,
      "xMax": 828,
      "xMin": 47,
      "yMax": 1550,
      "yMin": 1112
    },
    {
      "advanceWidth": 1158,
      "codePoint": 95,
      "height": -1297,
      "leftSideBearing": 0,
      "width": -322,
      "xMax": -322,
      "xMin": 0,
      "yMax": -139,
      "yMin": 1158
    },
    {
      "advanceWidth": 1158,
      "codePoint": 96,
      "height": 929,
      "leftSideBearing": 318,
      "width": 871,
      "xMax": 1189,
      "xMin": 318,
      "yMax": 1553,
      "yMin": 624
    },
    {
      "advanceWidth": 808,
      "codePoint": 97,
      "height": 353,
      "leftSideBearing": 69,
      "width": -85,
      "xMax": -16,
      "xMin": 69,
      "yMax": 1052,
      "yMin": 699
    },
    {
      "advanceWidth": 808,
      "codePoint": 98,
      "height": 961,
      "leftSideBearing": 108,
      "width": -124,
      "xMax": -16,
      "xMin": 108,
      "yMax": 1699,
      "yMin": 738
    },
    {
      "advanceWidth": 585,
      "codePoint": 99,
      "height": 521,
      "leftSideBearing": 69,
      "width": -85,
      "xMax": -16,
      "xMin": 69,
      "yMax": 1052,
      "yMin": 531
    },
    {
      "advanceWidth": 808,
      "codePoint": 100,
      "height": 1000,
      "leftSideBearing": 69,
      "width": -85,
      "xMax": -16,
      "xMin": 69,
      "yMax": 1699,
      "yMin": 699
    },
    {
      "advanceWidth": 755,
      "codePoint": 101,
      "height": 359,
      "leftSideBearing": 69,
      "width": -85,
      "xMax": -16,
      "xMin": 69,
      "yMax": 1052,
      "yMin": 693
    },
    {
      "advanceWidth": 502,
      "codePoint": 102,
      "height": 1225,
      "leftSideBearing": 35,
      "width": -35,
      "xMax": 0,
      "xMin": 35,
      "yMax": 1719,
      "yMin": 494
    },
    {
      "advanceWidth": 809,
      "codePoint": 103,
      "height": 351,
      "leftSideBearing": 69,
      "width": -504,
      "xMax": -435,
      "xMin": 69,
      "yMax": 1052,
      "yMin": 701
    },
    {
      "advanceWidth": 829,
      "codePoint": 104,
      "height": 978,
      "leftSideBearing": 108,
      "width": -108,
      "xMax": 0,
      "xMin": 108,
      "yMax": 1699,
      "yMin": 721
    },
    {
      "advanceWidth": 407,
      "codePoint": 105,
      "height": 1149,
      "leftSideBearing": 67,
      "width": -67,
      "xMax": 0,
      "xMin": 67,
      "yMax": 1475,
      "yMin": 326
    },
    {
      "advanceWidth": 407,
      "codePoint": 106,
      "height": 1149,
      "leftSideBearing": 67,
      "width": -491,
      "xMax": -424,
      "xMin": 67,
      "yMax": 1475,
      "yMin": 326
    },
    {
      "advanceWidth": 801,
      "codePoint": 107,
      "height": 906,
      "leftSideBearing": 108,
      "width": -108,
      "xMax": 0,
      "xMin": 108,
      "yMax": 1699,
      "yMin": 793
    },
    {
      "advanceWidth": 408,
      "codePoint": 108,
      "height": 1400,
      "leftSideBearing": 108,
      "width": -108,
      "xMax": 0,
      "xMin": 108,
      "yMax": 1699,
      "yMin": 299
    },
    {
      "advanceWidth": 1251,
      "codePoint": 109,
      "height": -91,
      "leftSideBearing": 108,
      "width": -108,
      "xMax": 0,
      "xMin": 108,
      "yMax": 1052,
      "yMin": 1143
    },
    {
      "advanceWidth": 829,
      "codePoint": 110,
      "height": 331,
      "leftSideBearing": 108,
      "width": -108,
      "xMax": 0,
      "xMin": 108,
      "yMax": 1052,
      "yMin": 721
    },
    {
      "advanceWidth": 789,
      "codePoint": 111,
      "height": 333,
      "leftSideBearing": 69,
      "width": -85,
      "xMax": -16,
      "xMin": 69,
      "yMax": 1052,
      "yMin": 719
    },
    {
      "advanceWidth": 808,
      "codePoint": 112,
      "height": 314,
      "leftSideBearing": 108,
      "width": -532,
      "xMax": -424,
      "xMin": 108,
      "yMax": 1052,
      "yMin": 738
    },
    {
      "advanceWidth": 808,
      "codePoint": 113,
      "height": 353,
      "leftSideBearing": 69,
      "width": -493,
      "xMax": -424,
      "xMin": 69,
      "yMax": 1052,
      "yMin": 699
    },
    {
      "advanceWidth": 547,
      "codePoint": 114,
      "height": 536,
      "leftSideBearing": 108,
      "width": -108,
      "xMax": 0,
      "xMin": 108,
      "yMax": 1059,
      "yMin": 523
    },
    {
      "advanceWidth": 602,
      "codePoint": 115,
      "height": 502,
      "leftSideBearing": 57,
      "width": -73,
      "xMax": -16,
      "xMin": 57,
      "yMax": 1059,
      "yMin": 557
    },
    {
      "advanceWidth": 455,
      "codePoint": 116,
      "height": 899,
      "leftSideBearing": 26,
      "width": -26,
      "xMax": 0,
      "xMin": 26,
      "yMax": 1325,
      "yMin": 426
    },
    {
      "advanceWidth": 832,
      "codePoint": 117,
      "height": 311,
      "leftSideBearing": 108,
      "width": -124,
      "xMax": -16,
      "xMin": 108,
      "yMax": 1035,
      "yMin": 724
    },
    {
      "advanceWidth": 695,
      "codePoint": 118,
      "height": 348,
      "leftSideBearing": 8,
      "width": -8,
      "xMax": 0,
      "xMin": 8,
      "yMax": 1035,
      "yMin": 687
    },
    {
      "advanceWidth": 1039,
      "codePoint": 119,
      "height": 12,
      "leftSideBearing": 15,
      "width": -15,
      "xMax": 0,
      "xMin": 15,
      "yMax": 1035,
      "yMin": 1023
    },
    {
      "advanceWidth": 770,
      "codePoint": 120,
      "height": 273,
      "leftSideBearing": 8,
      "width": -8,
      "xMax": 0,
      "xMin": 8,
      "yMax": 1035,
      "yMin": 762
    },
    {
      "advanceWidth": 755,
      "codePoint": 121,
      "height": 287,
      "leftSideBearing": 8,
      "width": -432,
      "xMax": -424,
      "xMin": 8,
      "yMax": 1035,
      "yMin": 748
    },
    {
      "advanceWidth": 691,
      "codePoint": 122,
      "height": 375,
      "leftSideBearing": 31,
      "width": -31,
      "xMax": 0,
      "xMin": 31,
      "yMax": 1035,
      "yMin": 660
    },
    {
      "advanceWidth": 618,
      "codePoint": 123,
      "height": 1115,
      "leftSideBearing": 76,
      "width": -503,
      "xMax": -427,
      "xMin": 76,
      "yMax": 1702,
      "yMin": 587
    },
    {
      "advanceWidth": 1158,
      "codePoint": 124,
      "height": 864,
      "leftSideBearing": 479,
      "width": -864,
      "xMax": -385,
      "xMin": 479,
      "yMax": 1544,
      "yMin": 680
    },
    {
      "advanceWidth": 618,
      "codePoint": 125,
      "height": 1160,
      "leftSideBearing": 31,
      "width": -458,
      "xMax": -427,
      "xMin": 31,
      "yMax": 1702,
      "yMin": 542
    },
    {
      "advanceWidth": 1544,
      "codePoint": 126,
      "height": 368,
      "leftSideBearing": 213,
      "width": 1120,
      "xMax": 1333,
      "xMin": 213,
      "yMax": 1699,
      "yMin": 1331
    },
    {
      "advanceWidth": 424,
      "codePoint": 160,
      "height": 0,
      "leftSideBearing": 0,
      "width": 0,
      "xMax": 0,
      "xMin": 0,
      "yMax": 0,
      "yMin": 0
    },
    {
      "advanceWidth": 571,
      "codePoint": 161,
      "height": 726,
      "leftSideBearing": 162,
      "width": -586,
      "xMax": -424,
      "xMin": 162,
      "yMax": 1135,
      "yMin": 409
    },
    {
      "advanceWidth": 848,
      "codePoint": 162,
      "height": 796,
      "leftSideBearing": 208,
      "width": -105,
      "xMax": 103,
      "xMin": 208,
      "yMax": 1444,
      "yMin": 648
    },
    {
      "advanceWidth": 848,
      "codePoint": 163,
      "height": 761,
      "leftSideBearing": 45,
      "width": -66,
      "xMax": -21,
      "xMin": 45,
      "yMax": 1564,
      "yMin": 803
    },
    {
      "advanceWidth": 1544,
      "codePoint": 164,
      "height": 68,
      "leftSideBearing": 99,
      "width": 81,
      "xMax": 180,
      "xMin": 99,
      "yMax": 1513,
      "yMin": 1445
    },
    {
      "advanceWidth": 848,
      "codePoint": 165,
      "height": 715,
      "leftSideBearing": 16,
      "width": -16,
      "xMax": 0,
      "xMin": 16,
      "yMax": 1546,
      "yMin": 831
    },
    {
      "advanceWidth": 1158,
      "codePoint": 166,
      "height": 864,
      "leftSideBearing": 479,
      "width": -864,
      "xMax": -385,
      "xMin": 479,
      "yMax": 1544,
      "yMin": 680
    },
    {
      "advanceWidth": 848,
      "codePoint": 167,
      "height": 948,
      "leftSideBearing": 77,
      "width": -507,
      "xMax": -430,
      "xMin": 77,
      "yMax": 1719,
      "yMin": 771
    },
    {
      "advanceWidth": 1159,
      "codePoint": 168,
      "height": 558,
      "leftSideBearing": 288,
      "width": 909,
      "xMax": 1197,
      "xMin": 288,
      "yMax": 1429,
      "yMin": 871
    },
    {
      "advanceWidth": 1753,
      "codePoint": 169,
      "height": -102,
      "leftSideBearing": 77,
      "width": -105,
      "xMax": -28,
      "xMin": 77,
      "yMax": 1574,
      "yMin": 1676
    },
    {
      "advanceWidth": 619,
      "codePoint": 170,
      "height": 1016,
      "leftSideBearing": 78,
      "width": 563,
      "xMax": 641,
      "xMin": 78,
      "yMax": 1557,
      "yMin": 541
    },
    {
      "advanceWidth": 755,
      "codePoint": 171,
      "height": 317,
      "leftSideBearing": 77,
      "width": 5,
      "xMax": 82,
      "xMin": 77,
      "yMax": 995,
      "yMin": 678
    },
    {
      "advanceWidth": 1158,
      "codePoint": 172,
      "height": -463,
      "leftSideBearing": 77,
      "width": -77,
      "xMax": 0,
      "xMin": 77,
      "yMax": 618,
      "yMin": 1081
    },
    {
      "advanceWidth": 364,
      "codePoint": 173,
      "height": 244,
      "leftSideBearing": 0,
      "width": 452,
      "xMax": 452,
      "xMin": 0,
      "yMax": 608,
      "yMin": 364
    },
    {
      "advanceWidth": 1753,
      "codePoint": 174,
      "height": -102,
      "leftSideBearing": 77,
      "width": -105,
      "xMax": -28,
      "xMin": 77,
      "yMax": 1574,
      "yMin": 1676
    },
    {
      "advanceWidth": 1156,
      "codePoint": 175,
      "height": 554,
      "leftSideBearing": 326,
      "width": 915,
      "xMax": 1241,
      "xMin": 326,
      "yMax": 1385,
      "yMin": 831
    },
    {
      "advanceWidth": 880,
      "codePoint": 176,
      "height": 761,
      "leftSideBearing": 82,
      "width": 777,
      "xMax": 859,
      "xMin": 82,
      "yMax": 1560,
      "yMin": 799
    },
    {
      "advanceWidth": 848,
      "codePoint": 177,
      "height": 361,
      "leftSideBearing": 63,
      "width": 146,
      "xMax": 209,
      "xMin": 63,
      "yMax": 1146,
      "yMin": 785
    },
    {
      "advanceWidth": 586,
      "codePoint": 178,
      "height": 1036,
      "leftSideBearing": 62,
      "width": 556,
      "xMax": 618,
      "xMin": 62,
      "yMax": 1555,
      "yMin": 519
    },
    {
      "advanceWidth": 586,
      "codePoint": 179,
      "height": 1042,
      "leftSideBearing": 72,
      "width": 535,
      "xMax": 607,
      "xMin": 72,
      "yMax": 1557,
      "yMin": 515
    },
    {
      "advanceWidth": 1158,
      "codePoint": 180,
      "height": 713,
      "leftSideBearing": 534,
      "width": 655,
      "xMax": 1189,
      "xMin": 534,
      "yMax": 1553,
      "yMin": 840
    },
    {
      "advanceWidth": 832,
      "codePoint": 181,
      "height": 311,
      "leftSideBearing": 108,
      "width": -532,
      "xMax": -424,
      "xMin": 108,
      "yMax": 1035,
      "yMin": 724
    },
    {
      "advanceWidth": 848,
      "codePoint": 182,
      "height": 697,
      "leftSideBearing": 2,
      "width": -230,
      "xMax": -228,
      "xMin": 2,
      "yMax": 1544,
      "yMin": 847
    },
    {
      "advanceWidth": 424,
      "codePoint": 183,
      "height": 560,
      "leftSideBearing": 89,
      "width": 561,
      "xMax": 650,
      "xMin": 89,
      "yMax": 896,
      "yMin": 336
    },
    {
      "advanceWidth": 1158,
      "codePoint": 184,
      "height": -861,
      "leftSideBearing": 494,
      "width": -935,
      "xMax": -441,
      "xMin": 494,
      "yMax": -104,
      "yMin": 757
    },
    {
      "advanceWidth": 585,
      "codePoint": 185,
      "height": 1148,
      "leftSideBearing": 158,
      "width": 460,
      "xMax": 618,
      "xMin": 158,
      "yMax": 1544,
      "yMin": 396
    },
    {
      "advanceWidth": 619,
      "codePoint": 186,
      "height": 1015,
      "leftSideBearing": 78,
      "width": 563,
      "xMax": 641,
      "xMin": 78,
      "yMax": 1556,
      "yMin": 541
    },
    {
      "advanceWidth": 755,
      "codePoint": 187,
      "height": 317,
      "leftSideBearing": 77,
      "width": 5,
      "xMax": 82,
      "xMin": 77,
      "yMax": 995,
      "yMin": 678
    },
    {
      "advanceWidth": 1460,
      "codePoint": 188,
      "height": 148,
      "leftSideBearing": 158,
      "width": -158,
      "xMax": 0,
      "xMin": 158,
      "yMax": 1544,
      "yMin": 1396
    },
    {
      "advanceWidth": 1461,
      "codePoint": 189,
      "height": 150,
      "leftSideBearing": 158,
      "width": -158,
      "xMax": 0,
      "xMin": 158,
      "yMax": 1544,
      "yMin": 1394
    },
    {
      "advanceWidth": 1461,
      "codePoint": 190,
      "height": 159,
      "leftSideBearing": 72,
      "width": -72,
      "xMax": 0,
      "xMin": 72,
      "yMax": 1557,
      "yMin": 1398
    },
    {
      "advanceWidth": 763,
      "codePoint": 191,
      "height": 464,
      "leftSideBearing": 93,
      "width": -532,
      "xMax": -439,
      "xMin": 93,
      "yMax": 1135,
      "yMin": 671
    },
    {
      "advanceWidth": 835,
      "codePoint": 192,
      "height": 1146,
      "leftSideBearing": 3,
      "width": -3,
      "xMax": 0,
      "xMin": 3,
      "yMax": 1978,
      "yMin": 832
    },
    {
      "advanceWidth": 835,
      "codePoint": 193,
      "height": 1146,
      "leftSideBearing": 3,
      "width": -3,
      "xMax": 0,
      "xMin": 3,
      "yMax": 1978,
      "yMin": 832
    },
    {
      "advanceWidth": 835,
      "codePoint": 194,
      "height": 1170,
      "leftSideBearing": 3,
      "width": -3,
      "xMax": 0,
      "xMin": 3,
      "yMax": 2002,
      "yMin": 832
    },
    {
      "advanceWidth": 835,
      "codePoint": 195,
      "height": 1080,
      "leftSideBearing": 3,
      "width": -3,
      "xMax": 0,
      "xMin": 3,
      "yMax": 1912,
      "yMin": 832
    },
    {
      "advanceWidth": 835,
      "codePoint": 196,
      "height": 1096,
      "leftSideBearing": 3,
      "width": -3,
      "xMax": 0,
      "xMin": 3,
      "yMax": 1928,
      "yMin": 832
    },
    {
      "advanceWidth": 835,
      "codePoint": 197,
      "height": 1182,
      "leftSideBearing": 3,
      "width": -3,
      "xMax": 0,
      "xMin": 3,
      "yMax": 2014,
      "yMin": 832
    },
    {
      "advanceWidth": 1183,
      "codePoint": 198,
      "height": 364,
      "leftSideBearing": 3,
      "width": -3,
      "xMax": 0,
      "xMin": 3,
      "yMax": 1544,
      "yMin": 1180
    },
    {
      "advanceWidth": 781,
      "codePoint": 199,
      "height": 840,
      "leftSideBearing": 88,
      "width": -522,
      "xMax": -434,
      "xMin": 88,
      "yMax": 1565,
      "yMin": 725
    },
    {
      "advanceWidth": 744,
      "codePoint": 200,
      "height": 1306,
      "leftSideBearing": 119,
      "width": -119,
      "xMax": 0,
      "xMin": 119,
      "yMax": 1978,
      "yMin": 672
    },
    {
      "advanceWidth": 744,
      "codePoint": 201,
      "height": 1306,
      "leftSideBearing": 119,
      "width": -119,
      "xMax": 0,
      "xMin": 119,
      "yMax": 1978,
      "yMin": 672
    },
    {
      "advanceWidth": 744,
      "codePoint": 202,
      "height": 1330,
      "leftSideBearing": 119,
      "width": -119,
      "xMax": 0,
      "xMin": 119,
      "yMax": 2002,
      "yMin": 672
    },
    {
      "advanceWidth": 744,
      "codePoint": 203,
      "height": 1227,
      "leftSideBearing": 90,
      "width": -90,
      "xMax": 0,
      "xMin": 90,
      "yMax": 1928,
      "yMin": 701
    },
    {
      "advanceWidth": 446,
      "codePoint": 204,
      "height": 1651,
      "leftSideBearing": -2,
      "width": 2,
      "xMax": 0,
      "xMin": -2,
      "yMax": 1978,
      "yMin": 327
    },
    {
      "advanceWidth": 446,
      "codePoint": 205,
      "height": 1527,
      "leftSideBearing": 119,
      "width": -119,
      "xMax": 0,
      "xMin": 119,
      "yMax": 1978,
      "yMin": 451
    },
    {
      "advanceWidth": 446,
      "codePoint": 206,
      "height": 1521,
      "leftSideBearing": -30,
      "width": 30,
      "xMax": 0,
      "xMin": -30,
      "yMax": 2002,
      "yMin": 481
    },
    {
      "advanceWidth": 446,
      "codePoint": 207,
      "height": 1439,
      "leftSideBearing": -42,
      "width": 42,
      "xMax": 0,
      "xMin": -42,
      "yMax": 1928,
      "yMin": 489
    },
    {
      "advanceWidth": 953,
      "codePoint": 208,
      "height": 679,
      "leftSideBearing": 3,
      "width": -3,
      "xMax": 0,
      "xMin": 3,
      "yMax": 1544,
      "yMin": 865
    },
    {
      "advanceWidth": 958,
      "codePoint": 209,
      "height": 1073,
      "leftSideBearing": 119,
      "width": -119,
      "xMax": 0,
      "xMin": 119,
      "yMax": 1912,
      "yMin": 839
    },
    {
      "advanceWidth": 979,
      "codePoint": 210,
      "height": 1086,
      "leftSideBearing": 88,
      "width": -107,
      "xMax": -19,
      "xMin": 88,
      "yMax": 1978,
      "yMin": 892
    },
    {
      "advanceWidth": 979,
      "codePoint": 211,
      "height": 1086,
      "leftSideBearing": 88,
      "width": -107,
      "xMax": -19,
      "xMin": 88,
      "yMax": 1978,
      "yMin": 892
    },
    {
      "advanceWidth": 979,
      "codePoint": 212,
      "height": 1089,
      "leftSideBearing": 88,
      "width": -107,
      "xMax": -19,
      "xMin": 88,
      "yMax": 1981,
      "yMin": 892
    },
    {
      "advanceWidth": 979,
      "codePoint": 213,
      "height": 1020,
      "leftSideBearing": 88,
      "width": -107,
      "xMax": -19,
      "xMin": 88,
      "yMax": 1912,
      "yMin": 892
    },
    {
      "advanceWidth": 979,
      "codePoint": 214,
      "height": 1036,
      "leftSideBearing": 88,
      "width": -107,
      "xMax": -19,
      "xMin": 88,
      "yMax": 1928,
      "yMin": 892
    },
    {
      "advanceWidth": 848,
      "codePoint": 215,
      "height": 375,
      "leftSideBearing": 98,
      "width": 374,
      "xMax": 472,
      "xMin": 98,
      "yMax": 1125,
      "yMin": 750
    },
    {
      "advanceWidth": 979,
      "codePoint": 216,
      "height": 630,
      "leftSideBearing": 17,
      "width": -71,
      "xMax": -54,
      "xMin": 17,
      "yMax": 1583,
      "yMin": 953
    },
    {
      "advanceWidth": 948,
      "codePoint": 217,
      "height": 1149,
      "leftSideBearing": 119,
      "width": -138,
      "xMax": -19,
      "xMin": 119,
      "yMax": 1978,
      "yMin": 829
    },
    {
      "advanceWidth": 948,
      "codePoint": 218,
      "height": 1149,
      "leftSideBearing": 119,
      "width": -138,
      "xMax": -19,
      "xMin": 119,
      "yMax": 1978,
      "yMin": 829
    },
    {
      "advanceWidth": 948,
      "codePoint": 219,
      "height": 1173,
      "leftSideBearing": 119,
      "width": -138,
      "xMax": -19,
      "xMin": 119,
      "yMax": 2002,
      "yMin": 829
    },
    {
      "advanceWidth": 948,
      "codePoint": 220,
      "height": 1099,
      "leftSideBearing": 119,
      "width": -138,
      "xMax": -19,
      "xMin": 119,
      "yMax": 1928,
      "yMin": 829
    },
    {
      "advanceWidth": 791,
      "codePoint": 221,
      "height": 1183,
      "leftSideBearing": -4,
      "width": 4,
      "xMax": 0,
      "xMin": -4,
      "yMax": 1978,
      "yMin": 795
    },
    {
      "advanceWidth": 812,
      "codePoint": 222,
      "height": 773,
      "leftSideBearing": 119,
      "width": -119,
      "xMax": 0,
      "xMin": 119,
      "yMax": 1544,
      "yMin": 771
    },
    {
      "advanceWidth": 845,
      "codePoint": 223,
      "height": 964,
      "leftSideBearing": 108,
      "width": -110,
      "xMax": -2,
      "xMin": 108,
      "yMax": 1739,
      "yMin": 775
    },
    {
      "advanceWidth": 808,
      "codePoint": 224,
      "height": 854,
      "leftSideBearing": 69,
      "width": -85,
      "xMax": -16,
      "xMin": 69,
      "yMax": 1553,
      "yMin": 699
    },
    {
      "advanceWidth": 808,
      "codePoint": 225,
      "height": 854,
      "leftSideBearing": 69,
      "width": -85,
      "xMax": -16,
      "xMin": 69,
      "yMax": 1553,
      "yMin": 699
    },
    {
      "advanceWidth": 808,
      "codePoint": 226,
      "height": 855,
      "leftSideBearing": 69,
      "width": -85,
      "xMax": -16,
      "xMin": 69,
      "yMax": 1554,
      "yMin": 699
    },
    {
      "advanceWidth": 808,
      "codePoint": 227,
      "height": 717,
      "leftSideBearing": 69,
      "width": -85,
      "xMax": -16,
      "xMin": 69,
      "yMax": 1416,
      "yMin": 699
    },
    {
      "advanceWidth": 808,
      "codePoint": 228,
      "height": 730,
      "leftSideBearing": 69,
      "width": -85,
      "xMax": -16,
      "xMin": 69,
      "yMax": 1429,
      "yMin": 699
    },
    {
      "advanceWidth": 808,
      "codePoint": 229,
      "height": 805,
      "leftSideBearing": 69,
      "width": -85,
      "xMax": -16,
      "xMin": 69,
      "yMax": 1504,
      "yMin": 699
    },
    {
      "advanceWidth": 1170,
      "codePoint": 230,
      "height": -48,
      "leftSideBearing": 69,
      "width": -85,
      "xMax": -16,
      "xMin": 69,
      "yMax": 1052,
      "yMin": 1100
    },
    {
      "advanceWidth": 585,
      "codePoint": 231,
      "height": 521,
      "leftSideBearing": 69,
      "width": -510,
      "xMax": -441,
      "xMin": 69,
      "yMax": 1052,
      "yMin": 531
    },
    {
      "advanceWidth": 755,
      "codePoint": 232,
      "height": 860,
      "leftSideBearing": 69,
      "width": -85,
      "xMax": -16,
      "xMin": 69,
      "yMax": 1553,
      "yMin": 693
    },
    {
      "advanceWidth": 755,
      "codePoint": 233,
      "height": 860,
      "leftSideBearing": 69,
      "width": -85,
      "xMax": -16,
      "xMin": 69,
      "yMax": 1553,
      "yMin": 693
    },
    {
      "advanceWidth": 755,
      "codePoint": 234,
      "height": 861,
      "leftSideBearing": 69,
      "width": -85,
      "xMax": -16,
      "xMin": 69,
      "yMax": 1554,
      "yMin": 693
    },
    {
      "advanceWidth": 755,
      "codePoint": 235,
      "height": 736,
      "leftSideBearing": 69,
      "width": -85,
      "xMax": -16,
      "xMin": 69,
      "yMax": 1429,
      "yMin": 693
    },
    {
      "advanceWidth": 408,
      "codePoint": 236,
      "height": 1254,
      "leftSideBearing": -24,
      "width": 24,
      "xMax": 0,
      "xMin": -24,
      "yMax": 1553,
      "yMin": 299
    },
    {
      "advanceWidth": 408,
      "codePoint": 237,
      "height": 1117,
      "leftSideBearing": 108,
      "width": -108,
      "xMax": 0,
      "xMin": 108,
      "yMax": 1553,
      "yMin": 436
    },
    {
      "advanceWidth": 407,
      "codePoint": 238,
      "height": 1092,
      "leftSideBearing": -49,
      "width": 49,
      "xMax": 0,
      "xMin": -49,
      "yMax": 1554,
      "yMin": 462
    },
    {
      "advanceWidth": 407,
      "codePoint": 239,
      "height": 954,
      "leftSideBearing": -66,
      "width": 66,
      "xMax": 0,
      "xMin": -66,
      "yMax": 1429,
      "yMin": 475
    },
    {
      "advanceWidth": 791,
      "codePoint": 240,
      "height": 984,
      "leftSideBearing": 69,
      "width": -85,
      "xMax": -16,
      "xMin": 69,
      "yMax": 1705,
      "yMin": 721
    },
    {
      "advanceWidth": 829,
      "codePoint": 241,
      "height": 695,
      "leftSideBearing": 108,
      "width": -108,
      "xMax": 0,
      "xMin": 108,
      "yMax": 1416,
      "yMin": 721
    },
    {
      "advanceWidth": 789,
      "codePoint": 242,
      "height": 834,
      "leftSideBearing": 69,
      "width": -85,
      "xMax": -16,
      "xMin": 69,
      "yMax": 1553,
      "yMin": 719
    },
    {
      "advanceWidth": 789,
      "codePoint": 243,
      "height": 834,
      "leftSideBearing": 69,
      "width": -85,
      "xMax": -16,
      "xMin": 69,
      "yMax": 1553,
      "yMin": 719
    },
    {
      "advanceWidth": 789,
      "codePoint": 244,
      "height": 835,
      "leftSideBearing": 69,
      "width": -85,
      "xMax": -16,
      "xMin": 69,
      "yMax": 1554,
      "yMin": 719
    },
    {
      "advanceWidth": 789,
      "codePoint": 245,
      "height": 697,
      "leftSideBearing": 69,
      "width": -85,
      "xMax": -16,
      "xMin": 69,
      "yMax": 1416,
      "yMin": 719
    },
    {
      "advanceWidth": 789,
      "codePoint": 246,
      "height": 710,
      "leftSideBearing": 69,
      "width": -85,
      "xMax": -16,
      "xMin": 69,
      "yMax": 1429,
      "yMin": 719
    },
    {
      "advanceWidth": 848,
      "codePoint": 247,
      "height": 402,
      "leftSideBearing": 63,
      "width": 327,
      "xMax": 390,
      "xMin": 63,
      "yMax": 1187,
      "yMin": 785
    },
    {
      "advanceWidth": 789,
      "codePoint": 248,
      "height": 298,
      "leftSideBearing": 17,
      "width": -50,
      "xMax": -33,
      "xMin": 17,
      "yMax": 1070,
      "yMin": 772
    },
    {
      "advanceWidth": 832,
      "codePoint": 249,
      "height": 829,
      "leftSideBearing": 108,
      "width": -124,
      "xMax": -16,
      "xMin": 108,
      "yMax": 1553,
      "yMin": 724
    },
    {
      "advanceWidth": 832,
      "codePoint": 250,
      "height": 829,
      "leftSideBearing": 108,
      "width": -124,
      "xMax": -16,
      "xMin": 108,
      "yMax": 1553,
      "yMin": 724
    },
    {
      "advanceWidth": 832,
      "codePoint": 251,
      "height": 830,
      "leftSideBearing": 108,
      "width": -124,
      "xMax": -16,
      "xMin": 108,
      "yMax": 1554,
      "yMin": 724
    },
    {
      "advanceWidth": 832,
      "codePoint": 252,
      "height": 705,
      "leftSideBearing": 108,
      "width": -124,
      "xMax": -16,
      "xMin": 108,
      "yMax": 1429,
      "yMin": 724
    },
    {
      "advanceWidth": 755,
      "codePoint": 253,
      "height": 805,
      "leftSideBearing": 8,
      "width": -432,
      "xMax": -424,
      "xMin": 8,
      "yMax": 1553,
      "yMin": 748
    },
    {
      "advanceWidth": 808,
      "codePoint": 254,
      "height": 961,
      "leftSideBearing": 108,
      "width": -532,
      "xMax": -424,
      "xMin": 108,
      "yMax": 1699,
      "yMin": 738
    },
    {
      "advanceWidth": 755,
      "codePoint": 255,
      "height": 681,
      "leftSideBearing": 8,
      "width": -432,
      "xMax": -424,
      "xMin": 8,
      "yMax": 1429,
      "yMin": 748
    },
    {
      "advanceWidth": 835,
      "codePoint": 256,
      "height": 1040,
      "leftSideBearing": 3,
      "width": -3,
      "xMax": 0,
      "xMin": 3,
      "yMax": 1872,
      "yMin": 832
    },
    {
      "advanceWidth": 808,
      "codePoint": 257,
      "height": 686,
      "leftSideBearing": 69,
      "width": -85,
      "xMax": -16,
      "xMin": 69,
      "yMax": 1385,
      "yMin": 699
    },
    {
      "advanceWidth": 835,
      "codePoint": 258,
      "height": 1104,
      "leftSideBearing": 3,
      "width": -3,
      "xMax": 0,
      "xMin": 3,
      "yMax": 1936,
      "yMin": 832
    },
    {
      "advanceWidth": 808,
      "codePoint": 259,
      "height": 762,
      "leftSideBearing": 69,
      "width": -85,
      "xMax": -16,
      "xMin": 69,
      "yMax": 1461,
      "yMin": 699
    },
    {
      "advanceWidth": 835,
      "codePoint": 260,
      "height": 712,
      "leftSideBearing": 3,
      "width": -362,
      "xMax": -359,
      "xMin": 3,
      "yMax": 1544,
      "yMin": 832
    },
    {
      "advanceWidth": 808,
      "codePoint": 261,
      "height": 353,
      "leftSideBearing": 69,
      "width": -428,
      "xMax": -359,
      "xMin": 69,
      "yMax": 1052,
      "yMin": 699
    },
    {
      "advanceWidth": 781,
      "codePoint": 262,
      "height": 1237,
      "leftSideBearing": 88,
      "width": -107,
      "xMax": -19,
      "xMin": 88,
      "yMax": 1978,
      "yMin": 741
    },
    {
      "advanceWidth": 585,
      "codePoint": 263,
      "height": 975,
      "leftSideBearing": 69,
      "width": -85,
      "xMax": -16,
      "xMin": 69,
      "yMax": 1553,
      "yMin": 578
    },
    {
      "advanceWidth": 781,
      "codePoint": 264,
      "height": 1317,
      "leftSideBearing": 88,
      "width": -107,
      "xMax": -19,
      "xMin": 88,
      "yMax": 2069,
      "yMin": 752
    },
    {
      "advanceWidth": 585,
      "codePoint": 265,
      "height": 975,
      "leftSideBearing": 68,
      "width": -84,
      "xMax": -16,
      "xMin": 68,
      "yMax": 1554,
      "yMin": 579
    },
    {
      "advanceWidth": 781,
      "codePoint": 266,
      "height": 1216,
      "leftSideBearing": 88,
      "width": -107,
      "xMax": -19,
      "xMin": 88,
      "yMax": 1941,
      "yMin": 725
    },
    {
      "advanceWidth": 585,
      "codePoint": 267,
      "height": 917,
      "leftSideBearing": 69,
      "width": -85,
      "xMax": -16,
      "xMin": 69,
      "yMax": 1448,
      "yMin": 531
    },
    {
      "advanceWidth": 781,
      "codePoint": 268,
      "height": 1245,
      "leftSideBearing": 88,
      "width": -107,
      "xMax": -19,
      "xMin": 88,
      "yMax": 2002,
      "yMin": 757
    },
    {
      "advanceWidth": 585,
      "codePoint": 269,
      "height": 942,
      "leftSideBearing": 70,
      "width": -86,
      "xMax": -16,
      "xMin": 70,
      "yMax": 1554,
      "yMin": 612
    },
    {
      "advanceWidth": 953,
      "codePoint": 270,
      "height": 1137,
      "leftSideBearing": 119,
      "width": -119,
      "xMax": 0,
      "xMin": 119,
      "yMax": 2002,
      "yMin": 865
    },
    {
      "advanceWidth": 987,
      "codePoint": 271,
      "height": 754,
      "leftSideBearing": 69,
      "width": -85,
      "xMax": -16,
      "xMin": 69,
      "yMax": 1699,
      "yMin": 945
    },
    {
      "advanceWidth": 953,
      "codePoint": 272,
      "height": 679,
      "leftSideBearing": 3,
      "width": -3,
      "xMax": 0,
      "xMin": 3,
      "yMax": 1544,
      "yMin": 865
    },
    {
      "advanceWidth": 808,
      "codePoint": 273,
      "height": 859,
      "leftSideBearing": 69,
      "width": -85,
      "xMax": -16,
      "xMin": 69,
      "yMax": 1699,
      "yMin": 840
    },
    {
      "advanceWidth": 744,
      "codePoint": 274,
      "height": 1200,
      "leftSideBearing": 119,
      "width": -119,
      "xMax": 0,
      "xMin": 119,
      "yMax": 1872,
      "yMin": 672
    },
    {
      "advanceWidth": 755,
      "codePoint": 275,
      "height": 692,
      "leftSideBearing": 69,
      "width": -85,
      "xMax": -16,
      "xMin": 69,
      "yMax": 1385,
      "yMin": 693
    },
    {
      "advanceWidth": 744,
      "codePoint": 276,
      "height": 1289,
      "leftSideBearing": 119,
      "width": -119,
      "xMax": 0,
      "xMin": 119,
      "yMax": 1961,
      "yMin": 672
    },
    {
      "advanceWidth": 755,
      "codePoint": 277,
      "height": 768,
      "leftSideBearing": 69,
      "width": -85,
      "xMax": -16,
      "xMin": 69,
      "yMax": 1461,
      "yMin": 693
    },
    {
      "advanceWidth": 744,
      "codePoint": 278,
      "height": 1268,
      "leftSideBearing": 119,
      "width": -119,
      "xMax": 0,
      "xMin": 119,
      "yMax": 1940,
      "yMin": 672
    },
    {
      "advanceWidth": 755,
      "codePoint": 279,
      "height": 748,
      "leftSideBearing": 69,
      "width": -85,
      "xMax": -16,
      "xMin": 69,
      "yMax": 1441,
      "yMin": 693
    },
    {
      "advanceWidth": 744,
      "codePoint": 280,
      "height": 792,
      "leftSideBearing": 119,
      "width": -478,
      "xMax": -359,
      "xMin": 119,
      "yMax": 1544,
      "yMin": 752
    },
    {
      "advanceWidth": 755,
      "codePoint": 281,
      "height": 359,
      "leftSideBearing": 69,
      "width": -428,
      "xMax": -359,
      "xMin": 69,
      "yMax": 1052,
      "yMin": 693
    },
    {
      "advanceWidth": 744,
      "codePoint": 282,
      "height": 1330,
      "leftSideBearing": 119,
      "width": -119,
      "xMax": 0,
      "xMin": 119,
      "yMax": 2002,
      "yMin": 672
    },
    {
      "advanceWidth": 755,
      "codePoint": 283,
      "height": 861,
      "leftSideBearing": 69,
      "width": -85,
      "xMax": -16,
      "xMin": 69,
      "yMax": 1554,
      "yMin": 693
    },
    {
      "advanceWidth": 955,
      "codePoint": 284,
      "height": 1195,
      "leftSideBearing": 88,
      "width": -107,
      "xMax": -19,
      "xMin": 88,
      "yMax": 2062,
      "yMin": 867
    },
    {
      "advanceWidth": 809,
      "codePoint": 285,
      "height": 867,
      "leftSideBearing": 69,
      "width": -504,
      "xMax": -435,
      "xMin": 69,
      "yMax": 1568,
      "yMin": 701
    },
    {
      "advanceWidth": 955,
      "codePoint": 286,
      "height": 1069,
      "leftSideBearing": 88,
      "width": -107,
      "xMax": -19,
      "xMin": 88,
      "yMax": 1936,
      "yMin": 867
    },
    {
      "advanceWidth": 809,
      "codePoint": 287,
      "height": 760,
      "leftSideBearing": 69,
      "width": -504,
      "xMax": -435,
      "xMin": 69,
      "yMax": 1461,
      "yMin": 701
    },
    {
      "advanceWidth": 955,
      "codePoint": 288,
      "height": 1074,
      "leftSideBearing": 88,
      "width": -107,
      "xMax": -19,
      "xMin": 88,
      "yMax": 1941,
      "yMin": 867
    },
    {
      "advanceWidth": 809,
      "codePoint": 289,
      "height": 740,
      "leftSideBearing": 69,
      "width": -504,
      "xMax": -435,
      "xMin": 69,
      "yMax": 1441,
      "yMin": 701
    },
    {
      "advanceWidth": 955,
      "codePoint": 290,
      "height": 697,
      "leftSideBearing": 88,
      "width": -578,
      "xMax": -490,
      "xMin": 88,
      "yMax": 1564,
      "yMin": 867
    },
    {
      "advanceWidth": 809,
      "codePoint": 291,
      "height": 879,
      "leftSideBearing": 69,
      "width": -504,
      "xMax": -435,
      "xMin": 69,
      "yMax": 1580,
      "yMin": 701
    },
    {
      "advanceWidth": 959,
      "codePoint": 292,
      "height": 1222,
      "leftSideBearing": 119,
      "width": -119,
      "xMax": 0,
      "xMin": 119,
      "yMax": 2062,
      "yMin": 840
    },
    {
      "advanceWidth": 829,
      "codePoint": 293,
      "height": 1341,
      "leftSideBearing": -50,
      "width": 50,
      "xMax": 0,
      "xMin": -50,
      "yMax": 2062,
      "yMin": 721
    },
    {
      "advanceWidth": 1161,
      "codePoint": 294,
      "height": 387,
      "leftSideBearing": -7,
      "width": 1,
      "xMax": -6,
      "xMin": -7,
      "yMax": 1538,
      "yMin": 1151
    },
    {
      "advanceWidth": 917,
      "codePoint": 295,
      "height": 896,
      "leftSideBearing": -6,
      "width": 0,
      "xMax": -6,
      "xMin": -6,
      "yMax": 1693,
      "yMin": 797
    },
    {
      "advanceWidth": 507,
      "codePoint": 296,
      "height": 1391,
      "leftSideBearing": -6,
      "width": 6,
      "xMax": 0,
      "xMin": -6,
      "yMax": 1902,
      "yMin": 511
    },
    {
      "advanceWidth": 514,
      "codePoint": 297,
      "height": 898,
      "leftSideBearing": 1,
      "width": 6,
      "xMax": 7,
      "xMin": 1,
      "yMax": 1416,
      "yMin": 518
    },
    {
      "advanceWidth": 446,
      "codePoint": 298,
      "height": 1436,
      "leftSideBearing": 7,
      "width": -7,
      "xMax": 0,
      "xMin": 7,
      "yMax": 1872,
      "yMin": 436
    },
    {
      "advanceWidth": 408,
      "codePoint": 299,
      "height": 973,
      "leftSideBearing": 1,
      "width": -1,
      "xMax": 0,
      "xMin": 1,
      "yMax": 1385,
      "yMin": 412
    },
    {
      "advanceWidth": 500,
      "codePoint": 300,
      "height": 1461,
      "leftSideBearing": -8,
      "width": 8,
      "xMax": 0,
      "xMin": -8,
      "yMax": 1961,
      "yMin": 500
    },
    {
      "advanceWidth": 514,
      "codePoint": 301,
      "height": 961,
      "leftSideBearing": -1,
      "width": -12,
      "xMax": -13,
      "xMin": -1,
      "yMax": 1468,
      "yMin": 507
    },
    {
      "advanceWidth": 446,
      "codePoint": 302,
      "height": 1138,
      "leftSideBearing": 105,
      "width": -464,
      "xMax": -359,
      "xMin": 105,
      "yMax": 1544,
      "yMin": 406
    },
    {
      "advanceWidth": 407,
      "codePoint": 303,
      "height": 1096,
      "leftSideBearing": 67,
      "width": -426,
      "xMax": -359,
      "xMin": 67,
      "yMax": 1475,
      "yMin": 379
    },
    {
      "advanceWidth": 446,
      "codePoint": 304,
      "height": 1597,
      "leftSideBearing": 103,
      "width": -103,
      "xMax": 0,
      "xMin": 103,
      "yMax": 1940,
      "yMin": 343
    },
    {
      "advanceWidth": 408,
      "codePoint": 305,
      "height": 736,
      "leftSideBearing": 108,
      "width": -108,
      "xMax": 0,
      "xMin": 108,
      "yMax": 1035,
      "yMin": 299
    },
    {
      "advanceWidth": 1216,
      "codePoint": 306,
      "height": 529,
      "leftSideBearing": 119,
      "width": -138,
      "xMax": -19,
      "xMin": 119,
      "yMax": 1544,
      "yMin": 1015
    },
    {
      "advanceWidth": 848,
      "codePoint": 307,
      "height": 739,
      "leftSideBearing": 67,
      "width": -491,
      "xMax": -424,
      "xMin": 67,
      "yMax": 1475,
      "yMin": 736
    },
    {
      "advanceWidth": 639,
      "codePoint": 308,
      "height": 1427,
      "leftSideBearing": -4,
      "width": -15,
      "xMax": -19,
      "xMin": -4,
      "yMax": 2055,
      "yMin": 628
    },
    {
      "advanceWidth": 500,
      "codePoint": 309,
      "height": 1059,
      "leftSideBearing": -9,
      "width": -421,
      "xMax": -430,
      "xMin": -9,
      "yMax": 1561,
      "yMin": 502
    },
    {
      "advanceWidth": 862,
      "codePoint": 310,
      "height": 693,
      "leftSideBearing": 119,
      "width": -609,
      "xMax": -490,
      "xMin": 119,
      "yMax": 1544,
      "yMin": 851
    },
    {
      "advanceWidth": 801,
      "codePoint": 311,
      "height": 906,
      "leftSideBearing": 108,
      "width": -598,
      "xMax": -490,
      "xMin": 108,
      "yMax": 1699,
      "yMin": 793
    },
    {
      "advanceWidth": 801,
      "codePoint": 312,
      "height": 242,
      "leftSideBearing": 108,
      "width": -108,
      "xMax": 0,
      "xMin": 108,
      "yMax": 1035,
      "yMin": 793
    },
    {
      "advanceWidth": 678,
      "codePoint": 313,
      "height": 1311,
      "leftSideBearing": 119,
      "width": -119,
      "xMax": 0,
      "xMin": 119,
      "yMax": 1978,
      "yMin": 667
    },
    {
      "advanceWidth": 408,
      "codePoint": 314,
      "height": 1601,
      "leftSideBearing": 108,
      "width": -108,
      "xMax": 0,
      "xMin": 108,
      "yMax": 2040,
      "yMin": 439
    },
    {
      "advanceWidth": 678,
      "codePoint": 315,
      "height": 877,
      "leftSideBearing": 119,
      "width": -609,
      "xMax": -490,
      "xMin": 119,
      "yMax": 1544,
      "yMin": 667
    },
    {
      "advanceWidth": 408,
      "codePoint": 316,
      "height": 1400,
      "leftSideBearing": 108,
      "width": -598,
      "xMax": -490,
      "xMin": 108,
      "yMax": 1699,
      "yMin": 299
    },
    {
      "advanceWidth": 678,
      "codePoint": 317,
      "height": 864,
      "leftSideBearing": 119,
      "width": -119,
      "xMax": 0,
      "xMin": 119,
      "yMax": 1544,
      "yMin": 680
    },
    {
      "advanceWidth": 555,
      "codePoint": 318,
      "height": 1154,
      "leftSideBearing": 108,
      "width": -108,
      "xMax": 0,
      "xMin": 108,
      "yMax": 1699,
      "yMin": 545
    },
    {
      "advanceWidth": 778,
      "codePoint": 319,
      "height": 822,
      "leftSideBearing": 119,
      "width": -119,
      "xMax": 0,
      "xMin": 119,
      "yMax": 1544,
      "yMin": 722
    },
    {
      "advanceWidth": 841,
      "codePoint": 320,
      "height": 998,
      "leftSideBearing": 108,
      "width": -108,
      "xMax": 0,
      "xMin": 108,
      "yMax": 1699,
      "yMin": 701
    },
    {
      "advanceWidth": 678,
      "codePoint": 321,
      "height": 877,
      "leftSideBearing": 0,
      "width": 0,
      "xMax": 0,
      "xMin": 0,
      "yMax": 1544,
      "yMin": 667
    },
    {
      "advanceWidth": 445,
      "codePoint": 322,
      "height": 1254,
      "leftSideBearing": 0,
      "width": 0,
      "xMax": 0,
      "xMin": 0,
      "yMax": 1699,
      "yMin": 445
    },
    {
      "advanceWidth": 958,
      "codePoint": 323,
      "height": 1139,
      "leftSideBearing": 119,
      "width": -119,
      "xMax": 0,
      "xMin": 119,
      "yMax": 1978,
      "yMin": 839
    },
    {
      "advanceWidth": 829,
      "codePoint": 324,
      "height": 832,
      "leftSideBearing": 108,
      "width": -108,
      "xMax": 0,
      "xMin": 108,
      "yMax": 1553,
      "yMin": 721
    },
    {
      "advanceWidth": 958,
      "codePoint": 325,
      "height": 705,
      "leftSideBearing": 119,
      "width": -609,
      "xMax": -490,
      "xMin": 119,
      "yMax": 1544,
      "yMin": 839
    },
    {
      "advanceWidth": 829,
      "codePoint": 326,
      "height": 331,
      "leftSideBearing": 108,
      "width": -598,
      "xMax": -490,
      "xMin": 108,
      "yMax": 1052,
      "yMin": 721
    },
    {
      "advanceWidth": 958,
      "codePoint": 327,
      "height": 1163,
      "leftSideBearing": 119,
      "width": -119,
      "xMax": 0,
      "xMin": 119,
      "yMax": 2002,
      "yMin": 839
    },
    {
      "advanceWidth": 829,
      "codePoint": 328,
      "height": 833,
      "leftSideBearing": 108,
      "width": -108,
      "xMax": 0,
      "xMin": 108,
      "yMax": 1554,
      "yMin": 721
    },
    {
      "advanceWidth": 829,
      "codePoint": 329,
      "height": 622,
      "leftSideBearing": 93,
      "width": -93,
      "xMax": 0,
      "xMin": 93,
      "yMax": 1593,
      "yMin": 971
    },
    {
      "advanceWidth": 979,
      "codePoint": 332,
      "height": 980,
      "leftSideBearing": 88,
      "width": -107,
      "xMax": -19,
      "xMin": 88,
      "yMax": 1872,
      "yMin": 892
    },
    {
      "advanceWidth": 789,
      "codePoint": 333,
      "height": 666,
      "leftSideBearing": 69,
      "width": -85,
      "xMax": -16,
      "xMin": 69,
      "yMax": 1385,
      "yMin": 719
    },
    {
      "advanceWidth": 979,
      "codePoint": 334,
      "height": 1062,
      "leftSideBearing": 88,
      "width": -107,
      "xMax": -19,
      "xMin": 88,
      "yMax": 1954,
      "yMin": 892
    },
    {
      "advanceWidth": 789,
      "codePoint": 335,
      "height": 749,
      "leftSideBearing": 69,
      "width": -85,
      "xMax": -16,
      "xMin": 69,
      "yMax": 1468,
      "yMin": 719
    },
    {
      "advanceWidth": 979,
      "codePoint": 336,
      "height": 1086,
      "leftSideBearing": 88,
      "width": -107,
      "xMax": -19,
      "xMin": 88,
      "yMax": 1978,
      "yMin": 892
    },
    {
      "advanceWidth": 789,
      "codePoint": 337,
      "height": 831,
      "leftSideBearing": 69,
      "width": -85,
      "xMax": -16,
      "xMin": 69,
      "yMax": 1554,
      "yMin": 723
    },
    {
      "advanceWidth": 1306,
      "codePoint": 338,
      "height": 346,
      "leftSideBearing": 88,
      "width": -107,
      "xMax": -19,
      "xMin": 88,
      "yMax": 1564,
      "yMin": 1218
    },
    {
      "advanceWidth": 1213,
      "codePoint": 339,
      "height": -91,
      "leftSideBearing": 69,
      "width": -85,
      "xMax": -16,
      "xMin": 69,
      "yMax": 1052,
      "yMin": 1143
    },
    {
      "advanceWidth": 863,
      "codePoint": 340,
      "height": 1157,
      "leftSideBearing": 119,
      "width": -119,
      "xMax": 0,
      "xMin": 119,
      "yMax": 1978,
      "yMin": 821
    },
    {
      "advanceWidth": 547,
      "codePoint": 341,
      "height": 1030,
      "leftSideBearing": 108,
      "width": -108,
      "xMax": 0,
      "xMin": 108,
      "yMax": 1553,
      "yMin": 523
    },
    {
      "advanceWidth": 863,
      "codePoint": 342,
      "height": 723,
      "leftSideBearing": 119,
      "width": -609,
      "xMax": -490,
      "xMin": 119,
      "yMax": 1544,
      "yMin": 821
    },
    {
      "advanceWidth": 547,
      "codePoint": 343,
      "height": 536,
      "leftSideBearing": 108,
      "width": -598,
      "xMax": -490,
      "xMin": 108,
      "yMax": 1059,
      "yMin": 523
    },
    {
      "advanceWidth": 863,
      "codePoint": 344,
      "height": 1181,
      "leftSideBearing": 119,
      "width": -119,
      "xMax": 0,
      "xMin": 119,
      "yMax": 2002,
      "yMin": 821
    },
    {
      "advanceWidth": 547,
      "codePoint": 345,
      "height": 1009,
      "leftSideBearing": 34,
      "width": -34,
      "xMax": 0,
      "xMin": 34,
      "yMax": 1554,
      "yMin": 545
    },
    {
      "advanceWidth": 764,
      "codePoint": 346,
      "height": 1270,
      "leftSideBearing": 73,
      "width": -92,
      "xMax": -19,
      "xMin": 73,
      "yMax": 1978,
      "yMin": 708
    },
    {
      "advanceWidth": 602,
      "codePoint": 347,
      "height": 996,
      "leftSideBearing": 57,
      "width": -73,
      "xMax": -16,
      "xMin": 57,
      "yMax": 1553,
      "yMin": 557
    },
    {
      "advanceWidth": 764,
      "codePoint": 348,
      "height": 1354,
      "leftSideBearing": 73,
      "width": -92,
      "xMax": -19,
      "xMin": 73,
      "yMax": 2062,
      "yMin": 708
    },
    {
      "advanceWidth": 602,
      "codePoint": 349,
      "height": 982,
      "leftSideBearing": 57,
      "width": -73,
      "xMax": -16,
      "xMin": 57,
      "yMax": 1561,
      "yMin": 579
    },
    {
      "advanceWidth": 764,
      "codePoint": 350,
      "height": 857,
      "leftSideBearing": 73,
      "width": -514,
      "xMax": -441,
      "xMin": 73,
      "yMax": 1565,
      "yMin": 708
    },
    {
      "advanceWidth": 602,
      "codePoint": 351,
      "height": 502,
      "leftSideBearing": 57,
      "width": -498,
      "xMax": -441,
      "xMin": 57,
      "yMax": 1059,
      "yMin": 557
    },
    {
      "advanceWidth": 764,
      "codePoint": 352,
      "height": 1294,
      "leftSideBearing": 73,
      "width": -92,
      "xMax": -19,
      "xMin": 73,
      "yMax": 2002,
      "yMin": 708
    },
    {
      "advanceWidth": 602,
      "codePoint": 353,
      "height": 995,
      "leftSideBearing": 48,
      "width": -64,
      "xMax": -16,
      "xMin": 48,
      "yMax": 1554,
      "yMin": 559
    },
    {
      "advanceWidth": 669,
      "codePoint": 354,
      "height": 871,
      "leftSideBearing": -4,
      "width": -486,
      "xMax": -490,
      "xMin": -4,
      "yMax": 1544,
      "yMin": 673
    },
    {
      "advanceWidth": 455,
      "codePoint": 355,
      "height": 899,
      "leftSideBearing": 26,
      "width": -516,
      "xMax": -490,
      "xMin": 26,
      "yMax": 1325,
      "yMin": 426
    },
    {
      "advanceWidth": 669,
      "codePoint": 356,
      "height": 1329,
      "leftSideBearing": -4,
      "width": 4,
      "xMax": 0,
      "xMin": -4,
      "yMax": 2002,
      "yMin": 673
    },
    {
      "advanceWidth": 679,
      "codePoint": 357,
      "height": 889,
      "leftSideBearing": 26,
      "width": -26,
      "xMax": 0,
      "xMin": 26,
      "yMax": 1544,
      "yMin": 655
    },
    {
      "advanceWidth": 669,
      "codePoint": 358,
      "height": 871,
      "leftSideBearing": -4,
      "width": 4,
      "xMax": 0,
      "xMin": -4,
      "yMax": 1544,
      "yMin": 673
    },
    {
      "advanceWidth": 563,
      "codePoint": 359,
      "height": 780,
      "leftSideBearing": -6,
      "width": 1,
      "xMax": -5,
      "xMin": -6,
      "yMax": 1320,
      "yMin": 540
    },
    {
      "advanceWidth": 948,
      "codePoint": 360,
      "height": 1073,
      "leftSideBearing": 119,
      "width": -138,
      "xMax": -19,
      "xMin": 119,
      "yMax": 1902,
      "yMin": 829
    },
    {
      "advanceWidth": 832,
      "codePoint": 361,
      "height": 692,
      "leftSideBearing": 108,
      "width": -124,
      "xMax": -16,
      "xMin": 108,
      "yMax": 1416,
      "yMin": 724
    },
    {
      "advanceWidth": 948,
      "codePoint": 362,
      "height": 1043,
      "leftSideBearing": 119,
      "width": -138,
      "xMax": -19,
      "xMin": 119,
      "yMax": 1872,
      "yMin": 829
    },
    {
      "advanceWidth": 832,
      "codePoint": 363,
      "height": 661,
      "leftSideBearing": 108,
      "width": -124,
      "xMax": -16,
      "xMin": 108,
      "yMax": 1385,
      "yMin": 724
    },
    {
      "advanceWidth": 948,
      "codePoint": 364,
      "height": 1132,
      "leftSideBearing": 119,
      "width": -138,
      "xMax": -19,
      "xMin": 119,
      "yMax": 1961,
      "yMin": 829
    },
    {
      "advanceWidth": 832,
      "codePoint": 365,
      "height": 744,
      "leftSideBearing": 108,
      "width": -124,
      "xMax": -16,
      "xMin": 108,
      "yMax": 1468,
      "yMin": 724
    },
    {
      "advanceWidth": 948,
      "codePoint": 366,
      "height": 1185,
      "leftSideBearing": 119,
      "width": -138,
      "xMax": -19,
      "xMin": 119,
      "yMax": 2014,
      "yMin": 829
    },
    {
      "advanceWidth": 832,
      "codePoint": 367,
      "height": 780,
      "leftSideBearing": 108,
      "width": -124,
      "xMax": -16,
      "xMin": 108,
      "yMax": 1504,
      "yMin": 724
    },
    {
      "advanceWidth": 948,
      "codePoint": 368,
      "height": 1144,
      "leftSideBearing": 119,
      "width": -138,
      "xMax": -19,
      "xMin": 119,
      "yMax": 1978,
      "yMin": 834
    },
    {
      "advanceWidth": 832,
      "codePoint": 369,
      "height": 816,
      "leftSideBearing": 108,
      "width": -124,
      "xMax": -16,
      "xMin": 108,
      "yMax": 1554,
      "yMin": 738
    },
    {
      "advanceWidth": 948,
      "codePoint": 370,
      "height": 715,
      "leftSideBearing": 119,
      "width": -478,
      "xMax": -359,
      "xMin": 119,
      "yMax": 1544,
      "yMin": 829
    },
    {
      "advanceWidth": 832,
      "codePoint": 371,
      "height": 311,
      "leftSideBearing": 108,
      "width": -467,
      "xMax": -359,
      "xMin": 108,
      "yMax": 1035,
      "yMin": 724
    },
    {
      "advanceWidth": 1214,
      "codePoint": 372,
      "height": 844,
      "leftSideBearing": 3,
      "width": -3,
      "xMax": 0,
      "xMin": 3,
      "yMax": 2055,
      "yMin": 1211
    },
    {
      "advanceWidth": 1039,
      "codePoint": 373,
      "height": 531,
      "leftSideBearing": 15,
      "width": -15,
      "xMax": 0,
      "xMin": 15,
      "yMax": 1554,
      "yMin": 1023
    },
    {
      "advanceWidth": 791,
      "codePoint": 374,
      "height": 1267,
      "leftSideBearing": -4,
      "width": 4,
      "xMax": 0,
      "xMin": -4,
      "yMax": 2062,
      "yMin": 795
    },
    {
      "advanceWidth": 755,
      "codePoint": 375,
      "height": 820,
      "leftSideBearing": 8,
      "width": -432,
      "xMax": -424,
      "xMin": 8,
      "yMax": 1568,
      "yMin": 748
    },
    {
      "advanceWidth": 791,
      "codePoint": 376,
      "height": 1133,
      "leftSideBearing": -4,
      "width": 4,
      "xMax": 0,
      "xMin": -4,
      "yMax": 1928,
      "yMin": 795
    },
    {
      "advanceWidth": 773,
      "codePoint": 377,
      "height": 1217,
      "leftSideBearing": 26,
      "width": -26,
      "xMax": 0,
      "xMin": 26,
      "yMax": 1978,
      "yMin": 761
    },
    {
      "advanceWidth": 691,
      "codePoint": 378,
      "height": 893,
      "leftSideBearing": 31,
      "width": -31,
      "xMax": 0,
      "xMin": 31,
      "yMax": 1553,
      "yMin": 660
    },
    {
      "advanceWidth": 773,
      "codePoint": 379,
      "height": 1179,
      "leftSideBearing": 26,
      "width": -26,
      "xMax": 0,
      "xMin": 26,
      "yMax": 1940,
      "yMin": 761
    },
    {
      "advanceWidth": 691,
      "codePoint": 380,
      "height": 781,
      "leftSideBearing": 31,
      "width": -31,
      "xMax": 0,
      "xMin": 31,
      "yMax": 1441,
      "yMin": 660
    },
    {
      "advanceWidth": 773,
      "codePoint": 381,
      "height": 1241,
      "leftSideBearing": 26,
      "width": -26,
      "xMax": 0,
      "xMin": 26,
      "yMax": 2002,
      "yMin": 761
    },
    {
      "advanceWidth": 691,
      "codePoint": 382,
      "height": 894,
      "leftSideBearing": 31,
      "width": -31,
      "xMax": 0,
      "xMin": 31,
      "yMax": 1554,
      "yMin": 660
    },
    {
      "advanceWidth": 879,
      "codePoint": 402,
      "height": 838,
      "leftSideBearing": -28,
      "width": -277,
      "xMax": -305,
      "xMin": -28,
      "yMax": 1716,
      "yMin": 878
    },
    {
      "advanceWidth": 764,
      "codePoint": 536,
      "height": 857,
      "leftSideBearing": 73,
      "width": -563,
      "xMax": -490,
      "xMin": 73,
      "yMax": 1565,
      "yMin": 708
    },
    {
      "advanceWidth": 602,
      "codePoint": 537,
      "height": 502,
      "leftSideBearing": 57,
      "width": -547,
      "xMax": -490,
      "xMin": 57,
      "yMax": 1059,
      "yMin": 557
    },
    {
      "advanceWidth": 669,
      "codePoint": 538,
      "height": 871,
      "leftSideBearing": -4,
      "width": -486,
      "xMax": -490,
      "xMin": -4,
      "yMax": 1544,
      "yMin": 673
    },
    {
      "advanceWidth": 455,
      "codePoint": 539,
      "height": 899,
      "leftSideBearing": 26,
      "width": -516,
      "xMax": -490,
      "xMin": 26,
      "yMax": 1325,
      "yMin": 426
    },
    {
      "advanceWidth": 473,
      "codePoint": 699,
      "height": 1241,
      "leftSideBearing": 93,
      "width": 951,
      "xMax": 1044,
      "xMin": 93,
      "yMax": 1637,
      "yMin": 396
    },
    {
      "advanceWidth": 473,
      "codePoint": 700,
      "height": 1197,
      "leftSideBearing": 93,
      "width": 907,
      "xMax": 1000,
      "xMin": 93,
      "yMax": 1593,
      "yMin": 396
    },
    {
      "advanceWidth": 1158,
      "codePoint": 710,
      "height": 719,
      "leftSideBearing": 324,
      "width": 865,
      "xMax": 1189,
      "xMin": 324,
      "yMax": 1554,
      "yMin": 835
    },
    {
      "advanceWidth": 1158,
      "codePoint": 711,
      "height": 719,
      "leftSideBearing": 324,
      "width": 865,
      "xMax": 1189,
      "xMin": 324,
      "yMax": 1554,
      "yMin": 835
    },
    {
      "advanceWidth": 1156,
      "codePoint": 713,
      "height": 554,
      "leftSideBearing": 326,
      "width": 915,
      "xMax": 1241,
      "xMin": 326,
      "yMax": 1385,
      "yMin": 831
    },
    {
      "advanceWidth": 1158,
      "codePoint": 728,
      "height": 628,
      "leftSideBearing": 325,
      "width": 869,
      "xMax": 1194,
      "xMin": 325,
      "yMax": 1461,
      "yMin": 833
    },
    {
      "advanceWidth": 1159,
      "codePoint": 729,
      "height": 740,
      "leftSideBearing": 457,
      "width": 740,
      "xMax": 1197,
      "xMin": 457,
      "yMax": 1441,
      "yMin": 701
    },
    {
      "advanceWidth": 1157,
      "codePoint": 730,
      "height": 759,
      "leftSideBearing": 412,
      "width": 759,
      "xMax": 1171,
      "xMin": 412,
      "yMax": 1504,
      "yMin": 745
    },
    {
      "advanceWidth": 1158,
      "codePoint": 731,
      "height": -784,
      "leftSideBearing": 483,
      "width": -842,
      "xMax": -359,
      "xMin": 483,
      "yMax": 0,
      "yMin": 784
    },
    {
      "advanceWidth": 1158,
      "codePoint": 732,
      "height": 579,
      "leftSideBearing": 320,
      "width": 884,
      "xMax": 1204,
      "xMin": 320,
      "yMax": 1416,
      "yMin": 837
    },
    {
      "advanceWidth": 1158,
      "codePoint": 733,
      "height": 623,
      "leftSideBearing": 398,
      "width": 791,
      "xMax": 1189,
      "xMin": 398,
      "yMax": 1554,
      "yMin": 931
    },
    {
      "advanceWidth": 0,
      "codePoint": 768,
      "height": 2086,
      "leftSideBearing": -839,
      "width": 2028,
      "xMax": 1189,
      "xMin": -839,
      "yMax": 1553,
      "yMin": -533
    },
    {
      "advanceWidth": 0,
      "codePoint": 769,
      "height": 1870,
      "leftSideBearing": -623,
      "width": 1812,
      "xMax": 1189,
      "xMin": -623,
      "yMax": 1553,
      "yMin": -317
    },
    {
      "advanceWidth": 0,
      "codePoint": 770,
      "height": 1876,
      "leftSideBearing": -833,
      "width": 2022,
      "xMax": 1189,
      "xMin": -833,
      "yMax": 1554,
      "yMin": -322
    },
    {
      "advanceWidth": 0,
      "codePoint": 771,
      "height": 1736,
      "leftSideBearing": -837,
      "width": 2041,
      "xMax": 1204,
      "xMin": -837,
      "yMax": 1416,
      "yMin": -320
    },
    {
      "advanceWidth": 0,
      "codePoint": 772,
      "height": 1709,
      "leftSideBearing": -829,
      "width": 2070,
      "xMax": 1241,
      "xMin": -829,
      "yMax": 1385,
      "yMin": -324
    },
    {
      "advanceWidth": 0,
      "codePoint": 774,
      "height": 1785,
      "leftSideBearing": -832,
      "width": 2026,
      "xMax": 1194,
      "xMin": -832,
      "yMax": 1461,
      "yMin": -324
    },
    {
      "advanceWidth": 0,
      "codePoint": 775,
      "height": 1898,
      "leftSideBearing": -701,
      "width": 1898,
      "xMax": 1197,
      "xMin": -701,
      "yMax": 1441,
      "yMin": -457
    },
    {
      "advanceWidth": 0,
      "codePoint": 776,
      "height": 1716,
      "leftSideBearing": -870,
      "width": 2067,
      "xMax": 1197,
      "xMin": -870,
      "yMax": 1429,
      "yMin": -287
    },
    {
      "advanceWidth": 0,
      "codePoint": 778,
      "height": 1915,
      "leftSideBearing": -744,
      "width": 1915,
      "xMax": 1171,
      "xMin": -744,
      "yMax": 1504,
      "yMin": -411
    },
    {
      "advanceWidth": 0,
      "codePoint": 779,
      "height": 1780,
      "leftSideBearing": -759,
      "width": 1948,
      "xMax": 1189,
      "xMin": -759,
      "yMax": 1554,
      "yMin": -226
    },
    {
      "advanceWidth": 0,
      "codePoint": 780,
      "height": 1876,
      "leftSideBearing": -833,
      "width": 2022,
      "xMax": 1189,
      "xMin": -833,
      "yMax": 1554,
      "yMin": -322
    },
    {
      "advanceWidth": 0,
      "codePoint": 806,
      "height": 7,
      "leftSideBearing": -270,
      "width": -220,
      "xMax": -490,
      "xMin": -270,
      "yMax": -110,
      "yMin": -117
    },
    {
      "advanceWidth": 0,
      "codePoint": 807,
      "height": 296,
      "leftSideBearing": -663,
      "width": 222,
      "xMax": -441,
      "xMin": -663,
      "yMax": -104,
      "yMin": -400
    },
    {
      "advanceWidth": 0,
      "codePoint": 808,
      "height": 373,
      "leftSideBearing": -674,
      "width": 315,
      "xMax": -359,
      "xMin": -674,
      "yMax": 0,
      "yMin": -373
    },
    {
      "advanceWidth": 0,
      "codePoint": 824,
      "height": 1637,
      "leftSideBearing": -1021,
      "width": 597,
      "xMax": -424,
      "xMin": -1021,
      "yMax": 1699,
      "yMin": 62
    },
    {
      "advanceWidth": 424,
      "codePoint": 894,
      "height": 708,
      "leftSideBearing": 29,
      "width": -405,
      "xMax": -376,
      "xMin": 29,
      "yMax": 1050,
      "yMin": 342
    },
    {
      "advanceWidth": 1544,
      "codePoint": 916,
      "height": 58,
      "leftSideBearing": 57,
      "width": -57,
      "xMax": 0,
      "xMin": 57,
      "yMax": 1544,
      "yMin": 1486
    },
    {
      "advanceWidth": 1544,
      "codePoint": 937,
      "height": 103,
      "leftSideBearing": 66,
      "width": -66,
      "xMax": 0,
      "xMin": 66,
      "yMax": 1582,
      "yMin": 1479
    },
    {
      "advanceWidth": 1393,
      "codePoint": 960,
      "height": -213,
      "leftSideBearing": 71,
      "width": -71,
      "xMax": 0,
      "xMin": 71,
      "yMax": 1110,
      "yMin": 1323
    },
    {
      "advanceWidth": 808,
      "codePoint": 1045,
      "height": 897,
      "leftSideBearing": 69,
      "width": -85,
      "xMax": -16,
      "xMin": 69,
      "yMax": 1699,
      "yMin": 802
    },
    {
      "advanceWidth": 0,
      "codePoint": 8205,
      "height": 0,
      "leftSideBearing": 0,
      "width": 0,
      "xMax": 0,
      "xMin": 0,
      "yMax": 0,
      "yMin": 0
    },
    {
      "advanceWidth": 878,
      "codePoint": 8211,
      "height": -140,
      "leftSideBearing": 131,
      "width": 323,
      "xMax": 454,
      "xMin": 131,
      "yMax": 607,
      "yMin": 747
    },
    {
      "advanceWidth": 1033,
      "codePoint": 8212,
      "height": -426,
      "leftSideBearing": 0,
      "width": 454,
      "xMax": 454,
      "xMin": 0,
      "yMax": 607,
      "yMin": 1033
    },
    {
      "advanceWidth": 473,
      "codePoint": 8216,
      "height": 1241,
      "leftSideBearing": 93,
      "width": 951,
      "xMax": 1044,
      "xMin": 93,
      "yMax": 1637,
      "yMin": 396
    },
    {
      "advanceWidth": 473,
      "codePoint": 8217,
      "height": 1197,
      "leftSideBearing": 93,
      "width": 907,
      "xMax": 1000,
      "xMin": 93,
      "yMax": 1593,
      "yMin": 396
    },
    {
      "advanceWidth": 473,
      "codePoint": 8218,
      "height": -164,
      "leftSideBearing": 77,
      "width": -453,
      "xMax": -376,
      "xMin": 77,
      "yMax": 216,
      "yMin": 380
    },
    {
      "advanceWidth": 754,
      "codePoint": 8220,
      "height": 960,
      "leftSideBearing": 93,
      "width": 951,
      "xMax": 1044,
      "xMin": 93,
      "yMax": 1637,
      "yMin": 677
    },
    {
      "advanceWidth": 754,
      "codePoint": 8221,
      "height": 916,
      "leftSideBearing": 93,
      "width": 907,
      "xMax": 1000,
      "xMin": 93,
      "yMax": 1593,
      "yMin": 677
    },
    {
      "advanceWidth": 754,
      "codePoint": 8222,
      "height": -445,
      "leftSideBearing": 77,
      "width": -453,
      "xMax": -376,
      "xMin": 77,
      "yMax": 216,
      "yMin": 661
    },
    {
      "advanceWidth": 880,
      "codePoint": 8224,
      "height": 951,
      "leftSideBearing": 132,
      "width": -525,
      "xMax": -393,
      "xMin": 132,
      "yMax": 1699,
      "yMin": 748
    },
    {
      "advanceWidth": 880,
      "codePoint": 8225,
      "height": 951,
      "leftSideBearing": 132,
      "width": -525,
      "xMax": -393,
      "xMin": 132,
      "yMax": 1699,
      "yMin": 748
    },
    {
      "advanceWidth": 1544,
      "codePoint": 8226,
      "height": 22,
      "leftSideBearing": 454,
      "width": 9,
      "xMax": 463,
      "xMin": 454,
      "yMax": 1112,
      "yMin": 1090
    },
    {
      "advanceWidth": 1297,
      "codePoint": 8230,
      "height": -973,
      "leftSideBearing": 93,
      "width": -107,
      "xMax": -14,
      "xMin": 93,
      "yMax": 232,
      "yMin": 1205
    },
    {
      "advanceWidth": 2268,
      "codePoint": 8240,
      "height": -693,
      "leftSideBearing": 46,
      "width": -71,
      "xMax": -25,
      "xMin": 46,
      "yMax": 1529,
      "yMin": 2222
    },
    {
      "advanceWidth": 511,
      "codePoint": 8249,
      "height": 562,
      "leftSideBearing": 77,
      "width": 5,
      "xMax": 82,
      "xMin": 77,
      "yMax": 995,
      "yMin": 433
    },
    {
      "advanceWidth": 511,
      "codePoint": 8250,
      "height": 562,
      "leftSideBearing": 77,
      "width": 5,
      "xMax": 82,
      "xMin": 77,
      "yMax": 995,
      "yMin": 433
    },
    {
      "advanceWidth": 291,
      "codePoint": 8260,
      "height": 952,
      "leftSideBearing": -300,
      "width": 300,
      "xMax": 0,
      "xMin": -300,
      "yMax": 1544,
      "yMin": 592
    },
    {
      "advanceWidth": 848,
      "codePoint": 8364,
      "height": 817,
      "leftSideBearing": 100,
      "width": -118,
      "xMax": -18,
      "xMin": 100,
      "yMax": 1566,
      "yMin": 749
    },
    {
      "advanceWidth": 1150,
      "codePoint": 8482,
      "height": 418,
      "leftSideBearing": -10,
      "width": 674,
      "xMax": 664,
      "xMin": -10,
      "yMax": 1544,
      "yMin": 1126
    },
    {
      "advanceWidth": 1544,
      "codePoint": 8486,
      "height": 103,
      "leftSideBearing": 66,
      "width": -66,
      "xMax": 0,
      "xMin": 66,
      "yMax": 1582,
      "yMin": 1479
    },
    {
      "advanceWidth": 1158,
      "codePoint": 8706,
      "height": 453,
      "leftSideBearing": 63,
      "width": -86,
      "xMax": -23,
      "xMin": 63,
      "yMax": 1549,
      "yMin": 1096
    },
    {
      "advanceWidth": 1544,
      "codePoint": 8710,
      "height": 58,
      "leftSideBearing": 57,
      "width": -57,
      "xMax": 0,
      "xMin": 57,
      "yMax": 1544,
      "yMin": 1486
    },
    {
      "advanceWidth": 1638,
      "codePoint": 8719,
      "height": 186,
      "leftSideBearing": 87,
      "width": -665,
      "xMax": -578,
      "xMin": 87,
      "yMax": 1737,
      "yMin": 1551
    },
    {
      "advanceWidth": 1544,
      "codePoint": 8721,
      "height": 317,
      "leftSideBearing": 61,
      "width": -639,
      "xMax": -578,
      "xMin": 61,
      "yMax": 1737,
      "yMin": 1420
    },
    {
      "advanceWidth": 880,
      "codePoint": 8722,
      "height": 73,
      "leftSideBearing": 80,
      "width": 624,
      "xMax": 704,
      "xMin": 80,
      "yMax": 875,
      "yMin": 802
    },
    {
      "advanceWidth": 291,
      "codePoint": 8725,
      "height": 952,
      "leftSideBearing": -300,
      "width": 300,
      "xMax": 0,
      "xMin": -300,
      "yMax": 1544,
      "yMin": 592
    },
    {
      "advanceWidth": 424,
      "codePoint": 8729,
      "height": 560,
      "leftSideBearing": 89,
      "width": 561,
      "xMax": 650,
      "xMin": 89,
      "yMax": 896,
      "yMin": 336
    },
    {
      "advanceWidth": 1544,
      "codePoint": 8730,
      "height": 377,
      "leftSideBearing": 0,
      "width": 0,
      "xMax": 0,
      "xMin": 0,
      "yMax": 1921,
      "yMin": 1544
    },
    {
      "advanceWidth": 1544,
      "codePoint": 8734,
      "height": -354,
      "leftSideBearing": 42,
      "width": 385,
      "xMax": 427,
      "xMin": 42,
      "yMax": 1149,
      "yMin": 1503
    },
    {
      "advanceWidth": 1158,
      "codePoint": 8747,
      "height": 774,
      "leftSideBearing": 194,
      "width": -769,
      "xMax": -575,
      "xMin": 194,
      "yMax": 1737,
      "yMin": 963
    },
    {
      "advanceWidth": 1158,
      "codePoint": 8776,
      "height": 27,
      "leftSideBearing": 21,
      "width": 377,
      "xMax": 398,
      "xMin": 21,
      "yMax": 1165,
      "yMin": 1138
    },
    {
      "advanceWidth": 1158,
      "codePoint": 8800,
      "height": 238,
      "leftSideBearing": 77,
      "width": 171,
      "xMax": 248,
      "xMin": 77,
      "yMax": 1319,
      "yMin": 1081
    },
    {
      "advanceWidth": 1158,
      "codePoint": 8804,
      "height": 365,
      "leftSideBearing": 77,
      "width": 25,
      "xMax": 102,
      "xMin": 77,
      "yMax": 1446,
      "yMin": 1081
    },
    {
      "advanceWidth": 1158,
      "codePoint": 8805,
      "height": 365,
      "leftSideBearing": 77,
      "width": 25,
      "xMax": 102,
      "xMin": 77,
      "yMax": 1446,
      "yMin": 1081
    },
    {
      "advanceWidth": 1544,
      "codePoint": 9674,
      "height": 231,
      "leftSideBearing": 171,
      "width": -230,
      "xMax": -59,
      "xMin": 171,
      "yMax": 1605,
      "yMin": 1374
    },
    {
      "advanceWidth": 1618,
      "codePoint": 63743,
      "height": 127,
      "leftSideBearing": 104,
      "width": -145,
      "xMax": -41,
      "xMin": 104,
      "yMax": 1661,
      "yMin": 1534
    },
    {
      "advanceWidth": 863,
      "codePoint": 64257,
      "height": 963,
      "leftSideBearing": 35,
      "width": -35,
      "xMax": 0,
      "xMin": 35,
      "yMax": 1719,
      "yMin": 756
    },
    {
      "advanceWidth": 863,
      "codePoint": 64258,
      "height": 963,
      "leftSideBearing": 35,
      "width": -35,
      "xMax": 0,
      "xMin": 35,
      "yMax": 1719,
      "yMin": 756
    }
  ],
  "descent": -448,
  "familyName": "Futura",
  "features": [{ "name": "kern", "type": "positioning" }],
  "fullName": "Futura Condensed Medium",
  "id": "futura-condensed-medium",
  "lineGap": 60,
  "postScriptName": "Futura-CondensedMedium",
  "subfamilyName": "Condensed Medium",
  "typographicFamilyName": "Futura",
  "typographicSubfamilyName": "Condensed Medium",
  "unitsPerEm": 2048,
  "variable": false,
  "wwsFamilyName": null,
  "wwsSubFamilyName": null,
  "xHeight": 1044,
  "xWidthAvg": 828
}
